Workbook

Sheet JOB
A1: JOB - one job: BOM, freight, labor, other direct costs, price build-up and close-out
A3: Job name | B3: Sample: 5 kWp / 6 kW / 11.7 kWh hybrid
A4: Client
A5: Site address | B5: Pila-area site
A6: Date
A7: Extra km beyond a Pila-area site, one way | B7: 0 | C7: Input. Adds to the truck run and to crew transport each day
A8: Extra toll per round trip for a farther site | B8: 0 | C8: Input
A9: Net metering application? (Yes/No) | B9: Yes
A10: LABOR INPUTS
A11: Roof difficulty factor | B11: ='LABOR RATES'!B63 -> 0.75 | C11: Simple roof by default; 1.00 = your 9.12 kWp multi-face roof; 1.25 two-storey or steep; 1.50 tile
A12: Roof closed within (days) | B12: 1
A13: Max installation days | B13: 2
A14: Max pairs | B14: 2 | C14: Pairs of 1 skilled + 1 laborer on top of team lead + 1 laborer
A15: Battery hauling hours per pack | B15: 0.5 | C15: 0.5 ground floor, short carry; 1.0 or more upstairs or long carry
A16: Your days on site (optional) | B16: 0
A18: TAKEOFF FOR LABOR (worked out from the BOM below; type over a cell if a count is wrong)
A19: Panels | B19: =SUMIF($D$33:$D$72,"Solar Panel",$B$33:$B$72) -> 8
A20: Hybrid inverters (incl. all-in-one) | B20: =SUMPRODUCT($R$33:$R$72,$B$33:$B$72) -> 1
A21: Grid-tie inverters | B21: =SUMIF($D$33:$D$72,"Inverter",$B$33:$B$72)-SUMPRODUCT(($D$33:$D$72="Inverter")*$R$33:$R$72*$B$33:$B$72) -> 0
A22: Battery packs | B22: =SUMIF($D$33:$D$72,"Battery",$B$33:$B$72) -> 1
A23: Heaviest battery pack, kg | B23: =IF(B22=0,0,SUMPRODUCT(MAX(($D$33:$D$72="Battery")*$M$33:$M$72))) -> 111
A24: Enclosures (boxes) | B24: =SUMPRODUCT(($D$33:$D$72="Enclosures and Raceways")*((ISNUMBER(SEARCH("box",$C$33:$C$72))+ISNUMBER(SEARCH("enclosure",$C$33:$C$72)))>0)*$B$33:$B$72) -> 2
A25: Breakers, SPDs, ATS | B25: =SUMIF($D$33:$D$72,"Protective Devices",$B$33:$B$72) -> 13
A26: Conduit and cable tray, m | B26: =SUMPRODUCT(($D$33:$D$72="Enclosures and Raceways")*($F$33:$F$72="m")*$B$33:$B$72)+2*SUMPRODUCT(($D$33:$D$72="Enclosures and Raceways")*ISNUMBER(SEARCH("tray",$C$33:$C$72))*($F$33:$F$72="pc")*$B$33:$B$72) -> 32 | C26: Tray pieces counted as 2 m each; conduit sold by the roll is not counted - type over if needed
A27: Wire, m | B27: =SUMPRODUCT(($D$33:$D$72="Wires and Terminations")*($F$33:$F$72="m")*$B$33:$B$72) -> 65
A28: String home-run MC4 pairs | B28: =SUMPRODUCT(ISNUMBER(SEARCH("MC4",$C$33:$C$72))*$B$33:$B$72) -> 4
A29: Ground rods | B29: =SUMPRODUCT(($D$33:$D$72="Grounding")*ISNUMBER(SEARCH("rod",$C$33:$C$72))*$B$33:$B$72) -> 1
A31: BOM - enter DB codes and quantities (sample: the 6 kW hybrid from your rev2 package)
A32: Code (input) | B32: Qty (input) | C32: Item | D32: Category | E32: Supplier | F32: Unit | G32: Landed cost per unit, before freight | H32: Markup tier | I32: Landed cost, line | J32: Markup, line | K32: Selling price, line | L32: Truck share, line | M32: Weight per unit, kg | N32: Actual cost, line (close-out input) | O32: Variance (actual - estimate) | P32: Remarks | Q32: Rating | R32: Hybrid inverter? (1/0)
A33: BC-PNL-004 | B33: 8 | C33: =IF($A33="","",IFERROR(INDEX('MATERIALS DB'!$D$4:$D$465,MATCH($A33,'MATERIALS DB'!$A$4:$A$465,0)),"Code not found")) -> 630W Bifacial solar panel | D33: =IF($A33="","",IFERROR(INDEX('MATERIALS DB'!$B$4:$B$465,MATCH($A33,'MATERIALS DB'!$A$4:$A$465,0)),"")) -> Solar Panel | E33: =IF($A33="","",IFERROR(INDEX('MATERIALS DB'!$C$4:$C$465,MATCH($A33,'MATERIALS DB'!$A$4:$A$465,0)),"")) -> Blue Carbon | F33: =IF($A33="","",IFERROR(INDEX('MATERIALS DB'!$F$4:$F$465,MATCH($A33,'MATERIALS DB'!$A$4:$A$465,0)),"")) -> pc | G33: =IF($A33="",0,IFERROR(INDEX('MATERIALS DB'!$W$4:$W$465,MATCH($A33,'MATERIALS DB'!$A$4:$A$465,0)),0)) -> 5497.9295 | H33: =IF($A33="",0,IFERROR(INDEX('MATERIALS DB'!$Y$4:$Y$465,MATCH($A33,'MATERIALS DB'!$A$4:$A$465,0)),0)) -> 0.1 | I33: =B33*G33 -> 43983.436 | J33: =I33*H33 -> 4398.3436 | K33: =I33+J33 -> 48381.78 | L33: =IF($A33="",0,IFERROR(B33*INDEX('MATERIALS DB'!$Q$4:$Q$465,MATCH($A33,'MATERIALS DB'!$A$4:$A$465,0))*(INDEX(SUPPLIERS!$F$3:$F$30,MATCH(E33,SUPPLIERS!$A$3:$A$30,0))<>"Yes"),0)) -> 0.073866667 | M33: =IF($A33="",0,IFERROR(INDEX('MATERIALS DB'!$N$4:$N$465,MATCH($A33,'MATERIALS DB'!$A$4:$A$465,0)),0)) -> 27.7 | O33: =IF(N33="","",N33-I33) | Q33: =IF($A33="",0,IFERROR(INDEX('MATERIALS DB'!$K$4:$K$465,MATCH($A33,'MATERIALS DB'!$A$4:$A$465,0)),0)) -> 630 | R33: =IF($A33="",0,IF(OR(D33="All-in-one System",AND(D33="Inverter",OR(ISNUMBER(SEARCH("hybrid",C33)),ISNUMBER(SEARCH("off-grid",C33))))),1,0)) -> 0
A34: FS-INV-001 | B34: 1 | C34: =IF($A34="","",IFERROR(INDEX('MATERIALS DB'!$D$4:$D$465,MATCH($A34,'MATERIALS DB'!$A$4:$A$465,0)),"Code not found")) -> 6 kW low-voltage hybrid inverter (grid-tie + backup) | D34: =IF($A34="","",IFERROR(INDEX('MATERIALS DB'!$B$4:$B$465,MATCH($A34,'MATERIALS DB'!$A$4:$A$465,0)),"")) -> Inverter | E34: =IF($A34="","",IFERROR(INDEX('MATERIALS DB'!$C$4:$C$465,MATCH($A34,'MATERIALS DB'!$A$4:$A$465,0)),"")) -> Felicity Solar | F34: =IF($A34="","",IFERROR(INDEX('MATERIALS DB'!$F$4:$F$465,MATCH($A34,'MATERIALS DB'!$A$4:$A$465,0)),"")) -> pc | G34: =IF($A34="",0,IFERROR(INDEX('MATERIALS DB'!$W$4:$W$465,MATCH($A34,'MATERIALS DB'!$A$4:$A$465,0)),0)) -> 43042.393 | H34: =IF($A34="",0,IFERROR(INDEX('MATERIALS DB'!$Y$4:$Y$465,MATCH($A34,'MATERIALS DB'!$A$4:$A$465,0)),0)) -> 0.1 | I34: =B34*G34 -> 43042.393 | J34: =I34*H34 -> 4304.2393 | K34: =I34+J34 -> 47346.632 | L34: =IF($A34="",0,IFERROR(B34*INDEX('MATERIALS DB'!$Q$4:$Q$465,MATCH($A34,'MATERIALS DB'!$A$4:$A$465,0))*(INDEX(SUPPLIERS!$F$3:$F$30,MATCH(E34,SUPPLIERS!$A$3:$A$30,0))<>"Yes"),0)) -> 0.0081666667 | M34: =IF($A34="",0,IFERROR(INDEX('MATERIALS DB'!$N$4:$N$465,MATCH($A34,'MATERIALS DB'!$A$4:$A$465,0)),0)) -> 24.5 | O34: =IF(N34="","",N34-I34) | Q34: =IF($A34="",0,IFERROR(INDEX('MATERIALS DB'!$K$4:$K$465,MATCH($A34,'MATERIALS DB'!$A$4:$A$465,0)),0)) -> 6 | R34: =IF($A34="",0,IF(OR(D34="All-in-one System",AND(D34="Inverter",OR(ISNUMBER(SEARCH("hybrid",C34)),ISNUMBER(SEARCH("off-grid",C34))))),1,0)) -> 1
A35: FS-BAT-006 | B35: 1 | C35: =IF($A35="","",IFERROR(INDEX('MATERIALS DB'!$D$4:$D$465,MATCH($A35,'MATERIALS DB'!$A$4:$A$465,0)),"Code not found")) -> LiFePO4 51.2V 230Ah (11.7 kWh), FLB IP65 | D35: =IF($A35="","",IFERROR(INDEX('MATERIALS DB'!$B$4:$B$465,MATCH($A35,'MATERIALS DB'!$A$4:$A$465,0)),"")) -> Battery | E35: =IF($A35="","",IFERROR(INDEX('MATERIALS DB'!$C$4:$C$465,MATCH($A35,'MATERIALS DB'!$A$4:$A$465,0)),"")) -> Felicity Solar | F35: =IF($A35="","",IFERROR(INDEX('MATERIALS DB'!$F$4:$F$465,MATCH($A35,'MATERIALS DB'!$A$4:$A$465,0)),"")) -> pc | G35: =IF($A35="",0,IFERROR(INDEX('MATERIALS DB'!$W$4:$W$465,MATCH($A35,'MATERIALS DB'!$A$4:$A$465,0)),0)) -> 87192.064 | H35: =IF($A35="",0,IFERROR(INDEX('MATERIALS DB'!$Y$4:$Y$465,MATCH($A35,'MATERIALS DB'!$A$4:$A$465,0)),0)) -> 0.15 | I35: =B35*G35 -> 87192.064 | J35: =I35*H35 -> 13078.81 | K35: =I35+J35 -> 100270.87 | L35: =IF($A35="",0,IFERROR(B35*INDEX('MATERIALS DB'!$Q$4:$Q$465,MATCH($A35,'MATERIALS DB'!$A$4:$A$465,0))*(INDEX(SUPPLIERS!$F$3:$F$30,MATCH(E35,SUPPLIERS!$A$3:$A$30,0))<>"Yes"),0)) -> 0.037 | M35: =IF($A35="",0,IFERROR(INDEX('MATERIALS DB'!$N$4:$N$465,MATCH($A35,'MATERIALS DB'!$A$4:$A$465,0)),0)) -> 111 | O35: =IF(N35="","",N35-I35) | Q35: =IF($A35="",0,IFERROR(INDEX('MATERIALS DB'!$K$4:$K$465,MATCH($A35,'MATERIALS DB'!$A$4:$A$465,0)),0)) -> 11.7 | R35: =IF($A35="",0,IF(OR(D35="All-in-one System",AND(D35="Inverter",OR(ISNUMBER(SEARCH("hybrid",C35)),ISNUMBER(SEARCH("off-grid",C35))))),1,0)) -> 0
A36: BC-MNT-001 | B36: 8 | C36: =IF($A36="","",IFERROR(INDEX('MATERIALS DB'!$D$4:$D$465,MATCH($A36,'MATERIALS DB'!$A$4:$A$465,0)),"Code not found")) -> Rail 2.4 m | D36: =IF($A36="","",IFERROR(INDEX('MATERIALS DB'!$B$4:$B$465,MATCH($A36,'MATERIALS DB'!$A$4:$A$465,0)),"")) -> Mounting | E36: =IF($A36="","",IFERROR(INDEX('MATERIALS DB'!$C$4:$C$465,MATCH($A36,'MATERIALS DB'!$A$4:$A$465,0)),"")) -> Blue Carbon | F36: =IF($A36="","",IFERROR(INDEX('MATERIALS DB'!$F$4:$F$465,MATCH($A36,'MATERIALS DB'!$A$4:$A$465,0)),"")) -> pc | G36: =IF($A36="",0,IFERROR(INDEX('MATERIALS DB'!$W$4:$W$465,MATCH($A36,'MATERIALS DB'!$A$4:$A$465,0)),0)) -> 555.2988 | H36: =IF($A36="",0,IFERROR(INDEX('MATERIALS DB'!$Y$4:$Y$465,MATCH($A36,'MATERIALS DB'!$A$4:$A$465,0)),0)) -> 0.3 | I36: =B36*G36 -> 4442.3904 | J36: =I36*H36 -> 1332.7171 | K36: =I36+J36 -> 5775.1075 | L36: =IF($A36="",0,IFERROR(B36*INDEX('MATERIALS DB'!$Q$4:$Q$465,MATCH($A36,'MATERIALS DB'!$A$4:$A$465,0))*(INDEX(SUPPLIERS!$F$3:$F$30,MATCH(E36,SUPPLIERS!$A$3:$A$30,0))<>"Yes"),0)) -> 0.0069333333 | M36: =IF($A36="",0,IFERROR(INDEX('MATERIALS DB'!$N$4:$N$465,MATCH($A36,'MATERIALS DB'!$A$4:$A$465,0)),0)) -> 2.6 | O36: =IF(N36="","",N36-I36) | Q36: =IF($A36="",0,IFERROR(INDEX('MATERIALS DB'!$K$4:$K$465,MATCH($A36,'MATERIALS DB'!$A$4:$A$465,0)),0)) -> 0 | R36: =IF($A36="",0,IF(OR(D36="All-in-one System",AND(D36="Inverter",OR(ISNUMBER(SEARCH("hybrid",C36)),ISNUMBER(SEARCH("off-grid",C36))))),1,0)) -> 0
A37: BC-MNT-006 | B37: 24 | C37: =IF($A37="","",IFERROR(INDEX('MATERIALS DB'!$D$4:$D$465,MATCH($A37,'MATERIALS DB'!$A$4:$A$465,0)),"Code not found")) -> L-leg (L-foot) | D37: =IF($A37="","",IFERROR(INDEX('MATERIALS DB'!$B$4:$B$465,MATCH($A37,'MATERIALS DB'!$A$4:$A$465,0)),"")) -> Mounting | E37: =IF($A37="","",IFERROR(INDEX('MATERIALS DB'!$C$4:$C$465,MATCH($A37,'MATERIALS DB'!$A$4:$A$465,0)),"")) -> Blue Carbon | F37: =IF($A37="","",IFERROR(INDEX('MATERIALS DB'!$F$4:$F$465,MATCH($A37,'MATERIALS DB'!$A$4:$A$465,0)),"")) -> pc | G37: =IF($A37="",0,IFERROR(INDEX('MATERIALS DB'!$W$4:$W$465,MATCH($A37,'MATERIALS DB'!$A$4:$A$465,0)),0)) -> 71.659546 | H37: =IF($A37="",0,IFERROR(INDEX('MATERIALS DB'!$Y$4:$Y$465,MATCH($A37,'MATERIALS DB'!$A$4:$A$465,0)),0)) -> 0.3 | I37: =B37*G37 -> 1719.8291 | J37: =I37*H37 -> 515.94873 | K37: =I37+J37 -> 2235.7778 | L37: =IF($A37="",0,IFERROR(B37*INDEX('MATERIALS DB'!$Q$4:$Q$465,MATCH($A37,'MATERIALS DB'!$A$4:$A$465,0))*(INDEX(SUPPLIERS!$F$3:$F$30,MATCH(E37,SUPPLIERS!$A$3:$A$30,0))<>"Yes"),0)) -> 0.0012 | M37: =IF($A37="",0,IFERROR(INDEX('MATERIALS DB'!$N$4:$N$465,MATCH($A37,'MATERIALS DB'!$A$4:$A$465,0)),0)) -> 0.15 | O37: =IF(N37="","",N37-I37) | Q37: =IF($A37="",0,IFERROR(INDEX('MATERIALS DB'!$K$4:$K$465,MATCH($A37,'MATERIALS DB'!$A$4:$A$465,0)),0)) -> 0 | R37: =IF($A37="",0,IF(OR(D37="All-in-one System",AND(D37="Inverter",OR(ISNUMBER(SEARCH("hybrid",C37)),ISNUMBER(SEARCH("off-grid",C37))))),1,0)) -> 0
A38: BC-MNT-003 | B38: 8 | C38: =IF($A38="","",IFERROR(INDEX('MATERIALS DB'!$D$4:$D$465,MATCH($A38,'MATERIALS DB'!$A$4:$A$465,0)),"Code not found")) -> End clamp | D38: =IF($A38="","",IFERROR(INDEX('MATERIALS DB'!$B$4:$B$465,MATCH($A38,'MATERIALS DB'!$A$4:$A$465,0)),"")) -> Mounting | E38: =IF($A38="","",IFERROR(INDEX('MATERIALS DB'!$C$4:$C$465,MATCH($A38,'MATERIALS DB'!$A$4:$A$465,0)),"")) -> Blue Carbon | F38: =IF($A38="","",IFERROR(INDEX('MATERIALS DB'!$F$4:$F$465,MATCH($A38,'MATERIALS DB'!$A$4:$A$465,0)),"")) -> pc | G38: =IF($A38="",0,IFERROR(INDEX('MATERIALS DB'!$W$4:$W$465,MATCH($A38,'MATERIALS DB'!$A$4:$A$465,0)),0)) -> 39.918425 | H38: =IF($A38="",0,IFERROR(INDEX('MATERIALS DB'!$Y$4:$Y$465,MATCH($A38,'MATERIALS DB'!$A$4:$A$465,0)),0)) -> 0.3 | I38: =B38*G38 -> 319.3474 | J38: =I38*H38 -> 95.804219 | K38: =I38+J38 -> 415.15162 | L38: =IF($A38="",0,IFERROR(B38*INDEX('MATERIALS DB'!$Q$4:$Q$465,MATCH($A38,'MATERIALS DB'!$A$4:$A$465,0))*(INDEX(SUPPLIERS!$F$3:$F$30,MATCH(E38,SUPPLIERS!$A$3:$A$30,0))<>"Yes"),0)) -> 0.00021333333 | M38: =IF($A38="",0,IFERROR(INDEX('MATERIALS DB'!$N$4:$N$465,MATCH($A38,'MATERIALS DB'!$A$4:$A$465,0)),0)) -> 0.08 | O38: =IF(N38="","",N38-I38) | Q38: =IF($A38="",0,IFERROR(INDEX('MATERIALS DB'!$K$4:$K$465,MATCH($A38,'MATERIALS DB'!$A$4:$A$465,0)),0)) -> 0 | R38: =IF($A38="",0,IF(OR(D38="All-in-one System",AND(D38="Inverter",OR(ISNUMBER(SEARCH("hybrid",C38)),ISNUMBER(SEARCH("off-grid",C38))))),1,0)) -> 0
A39: BC-MNT-004 | B39: 12 | C39: =IF($A39="","",IFERROR(INDEX('MATERIALS DB'!$D$4:$D$465,MATCH($A39,'MATERIALS DB'!$A$4:$A$465,0)),"Code not found")) -> Mid clamp | D39: =IF($A39="","",IFERROR(INDEX('MATERIALS DB'!$B$4:$B$465,MATCH($A39,'MATERIALS DB'!$A$4:$A$465,0)),"")) -> Mounting | E39: =IF($A39="","",IFERROR(INDEX('MATERIALS DB'!$C$4:$C$465,MATCH($A39,'MATERIALS DB'!$A$4:$A$465,0)),"")) -> Blue Carbon | F39: =IF($A39="","",IFERROR(INDEX('MATERIALS DB'!$F$4:$F$465,MATCH($A39,'MATERIALS DB'!$A$4:$A$465,0)),"")) -> pc | G39: =IF($A39="",0,IFERROR(INDEX('MATERIALS DB'!$W$4:$W$465,MATCH($A39,'MATERIALS DB'!$A$4:$A$465,0)),0)) -> 43.998425 | H39: =IF($A39="",0,IFERROR(INDEX('MATERIALS DB'!$Y$4:$Y$465,MATCH($A39,'MATERIALS DB'!$A$4:$A$465,0)),0)) -> 0.3 | I39: =B39*G39 -> 527.9811 | J39: =I39*H39 -> 158.39433 | K39: =I39+J39 -> 686.37543 | L39: =IF($A39="",0,IFERROR(B39*INDEX('MATERIALS DB'!$Q$4:$Q$465,MATCH($A39,'MATERIALS DB'!$A$4:$A$465,0))*(INDEX(SUPPLIERS!$F$3:$F$30,MATCH(E39,SUPPLIERS!$A$3:$A$30,0))<>"Yes"),0)) -> 0.00032 | M39: =IF($A39="",0,IFERROR(INDEX('MATERIALS DB'!$N$4:$N$465,MATCH($A39,'MATERIALS DB'!$A$4:$A$465,0)),0)) -> 0.08 | O39: =IF(N39="","",N39-I39) | Q39: =IF($A39="",0,IFERROR(INDEX('MATERIALS DB'!$K$4:$K$465,MATCH($A39,'MATERIALS DB'!$A$4:$A$465,0)),0)) -> 0 | R39: =IF($A39="",0,IF(OR(D39="All-in-one System",AND(D39="Inverter",OR(ISNUMBER(SEARCH("hybrid",C39)),ISNUMBER(SEARCH("off-grid",C39))))),1,0)) -> 0
A40: BC-MNT-005 | B40: 4 | C40: =IF($A40="","",IFERROR(INDEX('MATERIALS DB'!$D$4:$D$465,MATCH($A40,'MATERIALS DB'!$A$4:$A$465,0)),"Code not found")) -> Rail splice | D40: =IF($A40="","",IFERROR(INDEX('MATERIALS DB'!$B$4:$B$465,MATCH($A40,'MATERIALS DB'!$A$4:$A$465,0)),"")) -> Mounting | E40: =IF($A40="","",IFERROR(INDEX('MATERIALS DB'!$C$4:$C$465,MATCH($A40,'MATERIALS DB'!$A$4:$A$465,0)),"")) -> Blue Carbon | F40: =IF($A40="","",IFERROR(INDEX('MATERIALS DB'!$F$4:$F$465,MATCH($A40,'MATERIALS DB'!$A$4:$A$465,0)),"")) -> pc | G40: =IF($A40="",0,IFERROR(INDEX('MATERIALS DB'!$W$4:$W$465,MATCH($A40,'MATERIALS DB'!$A$4:$A$465,0)),0)) -> 61.459546 | H40: =IF($A40="",0,IFERROR(INDEX('MATERIALS DB'!$Y$4:$Y$465,MATCH($A40,'MATERIALS DB'!$A$4:$A$465,0)),0)) -> 0.3 | I40: =B40*G40 -> 245.83819 | J40: =I40*H40 -> 73.751456 | K40: =I40+J40 -> 319.58964 | L40: =IF($A40="",0,IFERROR(B40*INDEX('MATERIALS DB'!$Q$4:$Q$465,MATCH($A40,'MATERIALS DB'!$A$4:$A$465,0))*(INDEX(SUPPLIERS!$F$3:$F$30,MATCH(E40,SUPPLIERS!$A$3:$A$30,0))<>"Yes"),0)) -> 0.0002 | M40: =IF($A40="",0,IFERROR(INDEX('MATERIALS DB'!$N$4:$N$465,MATCH($A40,'MATERIALS DB'!$A$4:$A$465,0)),0)) -> 0.15 | O40: =IF(N40="","",N40-I40) | Q40: =IF($A40="",0,IFERROR(INDEX('MATERIALS DB'!$K$4:$K$465,MATCH($A40,'MATERIALS DB'!$A$4:$A$465,0)),0)) -> 0 | R40: =IF($A40="",0,IF(OR(D40="All-in-one System",AND(D40="Inverter",OR(ISNUMBER(SEARCH("hybrid",C40)),ISNUMBER(SEARCH("off-grid",C40))))),1,0)) -> 0
A41: BC-WIR-001 | B41: 15 | C41: =IF($A41="","",IFERROR(INDEX('MATERIALS DB'!$D$4:$D$465,MATCH($A41,'MATERIALS DB'!$A$4:$A$465,0)),"Code not found")) -> Solar cable 4mm2, red | D41: =IF($A41="","",IFERROR(INDEX('MATERIALS DB'!$B$4:$B$465,MATCH($A41,'MATERIALS DB'!$A$4:$A$465,0)),"")) -> Wires and Terminations | E41: =IF($A41="","",IFERROR(INDEX('MATERIALS DB'!$C$4:$C$465,MATCH($A41,'MATERIALS DB'!$A$4:$A$465,0)),"")) -> Blue Carbon | F41: =IF($A41="","",IFERROR(INDEX('MATERIALS DB'!$F$4:$F$465,MATCH($A41,'MATERIALS DB'!$A$4:$A$465,0)),"")) -> m | G41: =IF($A41="",0,IFERROR(INDEX('MATERIALS DB'!$W$4:$W$465,MATCH($A41,'MATERIALS DB'!$A$4:$A$465,0)),0)) -> 48.920167 | H41: =IF($A41="",0,IFERROR(INDEX('MATERIALS DB'!$Y$4:$Y$465,MATCH($A41,'MATERIALS DB'!$A$4:$A$465,0)),0)) -> 0.3 | I41: =B41*G41 -> 733.8025 | J41: =I41*H41 -> 220.14075 | K41: =I41+J41 -> 953.94326 | L41: =IF($A41="",0,IFERROR(B41*INDEX('MATERIALS DB'!$Q$4:$Q$465,MATCH($A41,'MATERIALS DB'!$A$4:$A$465,0))*(INDEX(SUPPLIERS!$F$3:$F$30,MATCH(E41,SUPPLIERS!$A$3:$A$30,0))<>"Yes"),0)) -> 0.000275 | M41: =IF($A41="",0,IFERROR(INDEX('MATERIALS DB'!$N$4:$N$465,MATCH($A41,'MATERIALS DB'!$A$4:$A$465,0)),0)) -> 0.055 | O41: =IF(N41="","",N41-I41) | Q41: =IF($A41="",0,IFERROR(INDEX('MATERIALS DB'!$K$4:$K$465,MATCH($A41,'MATERIALS DB'!$A$4:$A$465,0)),0)) -> 0 | R41: =IF($A41="",0,IF(OR(D41="All-in-one System",AND(D41="Inverter",OR(ISNUMBER(SEARCH("hybrid",C41)),ISNUMBER(SEARCH("off-grid",C41))))),1,0)) -> 0
A42: BC-WIR-002 | B42: 15 | C42: =IF($A42="","",IFERROR(INDEX('MATERIALS DB'!$D$4:$D$465,MATCH($A42,'MATERIALS DB'!$A$4:$A$465,0)),"Code not found")) -> Solar cable 4mm2, black | D42: =IF($A42="","",IFERROR(INDEX('MATERIALS DB'!$B$4:$B$465,MATCH($A42,'MATERIALS DB'!$A$4:$A$465,0)),"")) -> Wires and Terminations | E42: =IF($A42="","",IFERROR(INDEX('MATERIALS DB'!$C$4:$C$465,MATCH($A42,'MATERIALS DB'!$A$4:$A$465,0)),"")) -> Blue Carbon | F42: =IF($A42="","",IFERROR(INDEX('MATERIALS DB'!$F$4:$F$465,MATCH($A42,'MATERIALS DB'!$A$4:$A$465,0)),"")) -> m | G42: =IF($A42="",0,IFERROR(INDEX('MATERIALS DB'!$W$4:$W$465,MATCH($A42,'MATERIALS DB'!$A$4:$A$465,0)),0)) -> 48.920167 | H42: =IF($A42="",0,IFERROR(INDEX('MATERIALS DB'!$Y$4:$Y$465,MATCH($A42,'MATERIALS DB'!$A$4:$A$465,0)),0)) -> 0.3 | I42: =B42*G42 -> 733.8025 | J42: =I42*H42 -> 220.14075 | K42: =I42+J42 -> 953.94326 | L42: =IF($A42="",0,IFERROR(B42*INDEX('MATERIALS DB'!$Q$4:$Q$465,MATCH($A42,'MATERIALS DB'!$A$4:$A$465,0))*(INDEX(SUPPLIERS!$F$3:$F$30,MATCH(E42,SUPPLIERS!$A$3:$A$30,0))<>"Yes"),0)) -> 0.000275 | M42: =IF($A42="",0,IFERROR(INDEX('MATERIALS DB'!$N$4:$N$465,MATCH($A42,'MATERIALS DB'!$A$4:$A$465,0)),0)) -> 0.055 | O42: =IF(N42="","",N42-I42) | Q42: =IF($A42="",0,IFERROR(INDEX('MATERIALS DB'!$K$4:$K$465,MATCH($A42,'MATERIALS DB'!$A$4:$A$465,0)),0)) -> 0 | R42: =IF($A42="",0,IF(OR(D42="All-in-one System",AND(D42="Inverter",OR(ISNUMBER(SEARCH("hybrid",C42)),ISNUMBER(SEARCH("off-grid",C42))))),1,0)) -> 0
A43: IAN-WIR-004 | B43: 35 | C43: =IF($A43="","",IFERROR(INDEX('MATERIALS DB'!$D$4:$D$465,MATCH($A43,'MATERIALS DB'!$A$4:$A$465,0)),"Code not found")) -> THHN 8.0mm2 EURO WIRES | D43: =IF($A43="","",IFERROR(INDEX('MATERIALS DB'!$B$4:$B$465,MATCH($A43,'MATERIALS DB'!$A$4:$A$465,0)),"")) -> Wires and Terminations | E43: =IF($A43="","",IFERROR(INDEX('MATERIALS DB'!$C$4:$C$465,MATCH($A43,'MATERIALS DB'!$A$4:$A$465,0)),"")) -> IAN Solar | F43: =IF($A43="","",IFERROR(INDEX('MATERIALS DB'!$F$4:$F$465,MATCH($A43,'MATERIALS DB'!$A$4:$A$465,0)),"")) -> m | G43: =IF($A43="",0,IFERROR(INDEX('MATERIALS DB'!$W$4:$W$465,MATCH($A43,'MATERIALS DB'!$A$4:$A$465,0)),0)) -> 94.678222 | H43: =IF($A43="",0,IFERROR(INDEX('MATERIALS DB'!$Y$4:$Y$465,MATCH($A43,'MATERIALS DB'!$A$4:$A$465,0)),0)) -> 0.3 | I43: =B43*G43 -> 3313.7378 | J43: =I43*H43 -> 994.12133 | K43: =I43+J43 -> 4307.8591 | L43: =IF($A43="",0,IFERROR(B43*INDEX('MATERIALS DB'!$Q$4:$Q$465,MATCH($A43,'MATERIALS DB'!$A$4:$A$465,0))*(INDEX(SUPPLIERS!$F$3:$F$30,MATCH(E43,SUPPLIERS!$A$3:$A$30,0))<>"Yes"),0)) -> 0.0012016667 | M43: =IF($A43="",0,IFERROR(INDEX('MATERIALS DB'!$N$4:$N$465,MATCH($A43,'MATERIALS DB'!$A$4:$A$465,0)),0)) -> 0.103 | O43: =IF(N43="","",N43-I43) | Q43: =IF($A43="",0,IFERROR(INDEX('MATERIALS DB'!$K$4:$K$465,MATCH($A43,'MATERIALS DB'!$A$4:$A$465,0)),0)) -> 0 | R43: =IF($A43="",0,IF(OR(D43="All-in-one System",AND(D43="Inverter",OR(ISNUMBER(SEARCH("hybrid",C43)),ISNUMBER(SEARCH("off-grid",C43))))),1,0)) -> 0
A44: OP-WIR-007 | B44: 2 | C44: =IF($A44="","",IFERROR(INDEX('MATERIALS DB'!$D$4:$D$465,MATCH($A44,'MATERIALS DB'!$A$4:$A$465,0)),"Code not found")) -> 35mm2 - 1M w/ LUG PAIR | D44: =IF($A44="","",IFERROR(INDEX('MATERIALS DB'!$B$4:$B$465,MATCH($A44,'MATERIALS DB'!$A$4:$A$465,0)),"")) -> Wires and Terminations | E44: =IF($A44="","",IFERROR(INDEX('MATERIALS DB'!$C$4:$C$465,MATCH($A44,'MATERIALS DB'!$A$4:$A$465,0)),"")) -> One Point | F44: =IF($A44="","",IFERROR(INDEX('MATERIALS DB'!$F$4:$F$465,MATCH($A44,'MATERIALS DB'!$A$4:$A$465,0)),"")) -> pair | G44: =IF($A44="",0,IFERROR(INDEX('MATERIALS DB'!$W$4:$W$465,MATCH($A44,'MATERIALS DB'!$A$4:$A$465,0)),0)) -> 1050.8132 | H44: =IF($A44="",0,IFERROR(INDEX('MATERIALS DB'!$Y$4:$Y$465,MATCH($A44,'MATERIALS DB'!$A$4:$A$465,0)),0)) -> 0.3 | I44: =B44*G44 -> 2101.6265 | J44: =I44*H44 -> 630.48795 | K44: =I44+J44 -> 2732.1144 | L44: =IF($A44="",0,IFERROR(B44*INDEX('MATERIALS DB'!$Q$4:$Q$465,MATCH($A44,'MATERIALS DB'!$A$4:$A$465,0))*(INDEX(SUPPLIERS!$F$3:$F$30,MATCH(E44,SUPPLIERS!$A$3:$A$30,0))<>"Yes"),0)) -> 0.00031333333 | M44: =IF($A44="",0,IFERROR(INDEX('MATERIALS DB'!$N$4:$N$465,MATCH($A44,'MATERIALS DB'!$A$4:$A$465,0)),0)) -> 0.47 | O44: =IF(N44="","",N44-I44) | Q44: =IF($A44="",0,IFERROR(INDEX('MATERIALS DB'!$K$4:$K$465,MATCH($A44,'MATERIALS DB'!$A$4:$A$465,0)),0)) -> 0 | R44: =IF($A44="",0,IF(OR(D44="All-in-one System",AND(D44="Inverter",OR(ISNUMBER(SEARCH("hybrid",C44)),ISNUMBER(SEARCH("off-grid",C44))))),1,0)) -> 0
... A57: IAN-CSM-001 | B57: 2 | C57: =IF($A57="","",IFERROR(INDEX('MATERIALS DB'!$D$4:$D$465,MATCH($A57,'MATERIALS DB'!$A$4:$A$465,0)),"Code not found")) -> SEALANT BLACK | D57: =IF($A57="","",IFERROR(INDEX('MATERIALS DB'!$B$4:$B$465,MATCH($A57,'MATERIALS DB'!$A$4:$A$465,0)),"")) -> Consumables | E57: =IF($A57="","",IFERROR(INDEX('MATERIALS DB'!$C$4:$C$465,MATCH($A57,'MATERIALS DB'!$A$4:$A$465,0)),"")) -> IAN Solar | F57: =IF($A57="","",IFERROR(INDEX('MATERIALS DB'!$F$4:$F$465,MATCH($A57,'MATERIALS DB'!$A$4:$A$465,0)),"")) -> pc | G57: =IF($A57="",0,IFERROR(INDEX('MATERIALS DB'!$W$4:$W$465,MATCH($A57,'MATERIALS DB'!$A$4:$A$465,0)),0)) -> 330.60561 | H57: =IF($A57="",0,IFERROR(INDEX('MATERIALS DB'!$Y$4:$Y$465,MATCH($A57,'MATERIALS DB'!$A$4:$A$465,0)),0)) -> 0.3 | I57: =B57*G57 -> 661.21122 | J57: =I57*H57 -> 198.36336 | K57: =I57+J57 -> 859.57458 | L57: =IF($A57="",0,IFERROR(B57*INDEX('MATERIALS DB'!$Q$4:$Q$465,MATCH($A57,'MATERIALS DB'!$A$4:$A$465,0))*(INDEX(SUPPLIERS!$F$3:$F$30,MATCH(E57,SUPPLIERS!$A$3:$A$30,0))<>"Yes"),0)) -> 0.00023333333 | M57: =IF($A57="",0,IFERROR(INDEX('MATERIALS DB'!$N$4:$N$465,MATCH($A57,'MATERIALS DB'!$A$4:$A$465,0)),0)) -> 0.35 | O57: =IF(N57="","",N57-I57) | Q57: =IF($A57="",0,IFERROR(INDEX('MATERIALS DB'!$K$4:$K$465,MATCH($A57,'MATERIALS DB'!$A$4:$A$465,0)),0)) -> 0 | R57: =IF($A57="",0,IF(OR(D57="All-in-one System",AND(D57="Inverter",OR(ISNUMBER(SEARCH("hybrid",C57)),ISNUMBER(SEARCH("off-grid",C57))))),1,0)) -> 0
C58: =IF($A58="","",IFERROR(INDEX('MATERIALS DB'!$D$4:$D$465,MATCH($A58,'MATERIALS DB'!$A$4:$A$465,0)),"Code not found")) | D58: =IF($A58="","",IFERROR(INDEX('MATERIALS DB'!$B$4:$B$465,MATCH($A58,'MATERIALS DB'!$A$4:$A$465,0)),"")) | E58: =IF($A58="","",IFERROR(INDEX('MATERIALS DB'!$C$4:$C$465,MATCH($A58,'MATERIALS DB'!$A$4:$A$465,0)),"")) | F58: =IF($A58="","",IFERROR(INDEX('MATERIALS DB'!$F$4:$F$465,MATCH($A58,'MATERIALS DB'!$A$4:$A$465,0)),"")) | G58: =IF($A58="",0,IFERROR(INDEX('MATERIALS DB'!$W$4:$W$465,MATCH($A58,'MATERIALS DB'!$A$4:$A$465,0)),0)) -> 0 | H58: =IF($A58="",0,IFERROR(INDEX('MATERIALS DB'!$Y$4:$Y$465,MATCH($A58,'MATERIALS DB'!$A$4:$A$465,0)),0)) -> 0 | I58: =B58*G58 -> 0 | J58: =I58*H58 -> 0 | K58: =I58+J58 -> 0 | L58: =IF($A58="",0,IFERROR(B58*INDEX('MATERIALS DB'!$Q$4:$Q$465,MATCH($A58,'MATERIALS DB'!$A$4:$A$465,0))*(INDEX(SUPPLIERS!$F$3:$F$30,MATCH(E58,SUPPLIERS!$A$3:$A$30,0))<>"Yes"),0)) -> 0 | M58: =IF($A58="",0,IFERROR(INDEX('MATERIALS DB'!$N$4:$N$465,MATCH($A58,'MATERIALS DB'!$A$4:$A$465,0)),0)) -> 0 | O58: =IF(N58="","",N58-I58) | Q58: =IF($A58="",0,IFERROR(INDEX('MATERIALS DB'!$K$4:$K$465,MATCH($A58,'MATERIALS DB'!$A$4:$A$465,0)),0)) -> 0 | R58: =IF($A58="",0,IF(OR(D58="All-in-one System",AND(D58="Inverter",OR(ISNUMBER(SEARCH("hybrid",C58)),ISNUMBER(SEARCH("off-grid",C58))))),1,0)) -> 0
C59: =IF($A59="","",IFERROR(INDEX('MATERIALS DB'!$D$4:$D$465,MATCH($A59,'MATERIALS DB'!$A$4:$A$465,0)),"Code not found")) | D59: =IF($A59="","",IFERROR(INDEX('MATERIALS DB'!$B$4:$B$465,MATCH($A59,'MATERIALS DB'!$A$4:$A$465,0)),"")) | E59: =IF($A59="","",IFERROR(INDEX('MATERIALS DB'!$C$4:$C$465,MATCH($A59,'MATERIALS DB'!$A$4:$A$465,0)),"")) | F59: =IF($A59="","",IFERROR(INDEX('MATERIALS DB'!$F$4:$F$465,MATCH($A59,'MATERIALS DB'!$A$4:$A$465,0)),"")) | G59: =IF($A59="",0,IFERROR(INDEX('MATERIALS DB'!$W$4:$W$465,MATCH($A59,'MATERIALS DB'!$A$4:$A$465,0)),0)) -> 0 | H59: =IF($A59="",0,IFERROR(INDEX('MATERIALS DB'!$Y$4:$Y$465,MATCH($A59,'MATERIALS DB'!$A$4:$A$465,0)),0)) -> 0 | I59: =B59*G59 -> 0 | J59: =I59*H59 -> 0 | K59: =I59+J59 -> 0 | L59: =IF($A59="",0,IFERROR(B59*INDEX('MATERIALS DB'!$Q$4:$Q$465,MATCH($A59,'MATERIALS DB'!$A$4:$A$465,0))*(INDEX(SUPPLIERS!$F$3:$F$30,MATCH(E59,SUPPLIERS!$A$3:$A$30,0))<>"Yes"),0)) -> 0 | M59: =IF($A59="",0,IFERROR(INDEX('MATERIALS DB'!$N$4:$N$465,MATCH($A59,'MATERIALS DB'!$A$4:$A$465,0)),0)) -> 0 | O59: =IF(N59="","",N59-I59) | Q59: =IF($A59="",0,IFERROR(INDEX('MATERIALS DB'!$K$4:$K$465,MATCH($A59,'MATERIALS DB'!$A$4:$A$465,0)),0)) -> 0 | R59: =IF($A59="",0,IF(OR(D59="All-in-one System",AND(D59="Inverter",OR(ISNUMBER(SEARCH("hybrid",C59)),ISNUMBER(SEARCH("off-grid",C59))))),1,0)) -> 0
C60: =IF($A60="","",IFERROR(INDEX('MATERIALS DB'!$D$4:$D$465,MATCH($A60,'MATERIALS DB'!$A$4:$A$465,0)),"Code not found")) | D60: =IF($A60="","",IFERROR(INDEX('MATERIALS DB'!$B$4:$B$465,MATCH($A60,'MATERIALS DB'!$A$4:$A$465,0)),"")) | E60: =IF($A60="","",IFERROR(INDEX('MATERIALS DB'!$C$4:$C$465,MATCH($A60,'MATERIALS DB'!$A$4:$A$465,0)),"")) | F60: =IF($A60="","",IFERROR(INDEX('MATERIALS DB'!$F$4:$F$465,MATCH($A60,'MATERIALS DB'!$A$4:$A$465,0)),"")) | G60: =IF($A60="",0,IFERROR(INDEX('MATERIALS DB'!$W$4:$W$465,MATCH($A60,'MATERIALS DB'!$A$4:$A$465,0)),0)) -> 0 | H60: =IF($A60="",0,IFERROR(INDEX('MATERIALS DB'!$Y$4:$Y$465,MATCH($A60,'MATERIALS DB'!$A$4:$A$465,0)),0)) -> 0 | I60: =B60*G60 -> 0 | J60: =I60*H60 -> 0 | K60: =I60+J60 -> 0 | L60: =IF($A60="",0,IFERROR(B60*INDEX('MATERIALS DB'!$Q$4:$Q$465,MATCH($A60,'MATERIALS DB'!$A$4:$A$465,0))*(INDEX(SUPPLIERS!$F$3:$F$30,MATCH(E60,SUPPLIERS!$A$3:$A$30,0))<>"Yes"),0)) -> 0 | M60: =IF($A60="",0,IFERROR(INDEX('MATERIALS DB'!$N$4:$N$465,MATCH($A60,'MATERIALS DB'!$A$4:$A$465,0)),0)) -> 0 | O60: =IF(N60="","",N60-I60) | Q60: =IF($A60="",0,IFERROR(INDEX('MATERIALS DB'!$K$4:$K$465,MATCH($A60,'MATERIALS DB'!$A$4:$A$465,0)),0)) -> 0 | R60: =IF($A60="",0,IF(OR(D60="All-in-one System",AND(D60="Inverter",OR(ISNUMBER(SEARCH("hybrid",C60)),ISNUMBER(SEARCH("off-grid",C60))))),1,0)) -> 0
C61: =IF($A61="","",IFERROR(INDEX('MATERIALS DB'!$D$4:$D$465,MATCH($A61,'MATERIALS DB'!$A$4:$A$465,0)),"Code not found")) | D61: =IF($A61="","",IFERROR(INDEX('MATERIALS DB'!$B$4:$B$465,MATCH($A61,'MATERIALS DB'!$A$4:$A$465,0)),"")) | E61: =IF($A61="","",IFERROR(INDEX('MATERIALS DB'!$C$4:$C$465,MATCH($A61,'MATERIALS DB'!$A$4:$A$465,0)),"")) | F61: =IF($A61="","",IFERROR(INDEX('MATERIALS DB'!$F$4:$F$465,MATCH($A61,'MATERIALS DB'!$A$4:$A$465,0)),"")) | G61: =IF($A61="",0,IFERROR(INDEX('MATERIALS DB'!$W$4:$W$465,MATCH($A61,'MATERIALS DB'!$A$4:$A$465,0)),0)) -> 0 | H61: =IF($A61="",0,IFERROR(INDEX('MATERIALS DB'!$Y$4:$Y$465,MATCH($A61,'MATERIALS DB'!$A$4:$A$465,0)),0)) -> 0 | I61: =B61*G61 -> 0 | J61: =I61*H61 -> 0 | K61: =I61+J61 -> 0 | L61: =IF($A61="",0,IFERROR(B61*INDEX('MATERIALS DB'!$Q$4:$Q$465,MATCH($A61,'MATERIALS DB'!$A$4:$A$465,0))*(INDEX(SUPPLIERS!$F$3:$F$30,MATCH(E61,SUPPLIERS!$A$3:$A$30,0))<>"Yes"),0)) -> 0 | M61: =IF($A61="",0,IFERROR(INDEX('MATERIALS DB'!$N$4:$N$465,MATCH($A61,'MATERIALS DB'!$A$4:$A$465,0)),0)) -> 0 | O61: =IF(N61="","",N61-I61) | Q61: =IF($A61="",0,IFERROR(INDEX('MATERIALS DB'!$K$4:$K$465,MATCH($A61,'MATERIALS DB'!$A$4:$A$465,0)),0)) -> 0 | R61: =IF($A61="",0,IF(OR(D61="All-in-one System",AND(D61="Inverter",OR(ISNUMBER(SEARCH("hybrid",C61)),ISNUMBER(SEARCH("off-grid",C61))))),1,0)) -> 0
C62: =IF($A62="","",IFERROR(INDEX('MATERIALS DB'!$D$4:$D$465,MATCH($A62,'MATERIALS DB'!$A$4:$A$465,0)),"Code not found")) | D62: =IF($A62="","",IFERROR(INDEX('MATERIALS DB'!$B$4:$B$465,MATCH($A62,'MATERIALS DB'!$A$4:$A$465,0)),"")) | E62: =IF($A62="","",IFERROR(INDEX('MATERIALS DB'!$C$4:$C$465,MATCH($A62,'MATERIALS DB'!$A$4:$A$465,0)),"")) | F62: =IF($A62="","",IFERROR(INDEX('MATERIALS DB'!$F$4:$F$465,MATCH($A62,'MATERIALS DB'!$A$4:$A$465,0)),"")) | G62: =IF($A62="",0,IFERROR(INDEX('MATERIALS DB'!$W$4:$W$465,MATCH($A62,'MATERIALS DB'!$A$4:$A$465,0)),0)) -> 0 | H62: =IF($A62="",0,IFERROR(INDEX('MATERIALS DB'!$Y$4:$Y$465,MATCH($A62,'MATERIALS DB'!$A$4:$A$465,0)),0)) -> 0 | I62: =B62*G62 -> 0 | J62: =I62*H62 -> 0 | K62: =I62+J62 -> 0 | L62: =IF($A62="",0,IFERROR(B62*INDEX('MATERIALS DB'!$Q$4:$Q$465,MATCH($A62,'MATERIALS DB'!$A$4:$A$465,0))*(INDEX(SUPPLIERS!$F$3:$F$30,MATCH(E62,SUPPLIERS!$A$3:$A$30,0))<>"Yes"),0)) -> 0 | M62: =IF($A62="",0,IFERROR(INDEX('MATERIALS DB'!$N$4:$N$465,MATCH($A62,'MATERIALS DB'!$A$4:$A$465,0)),0)) -> 0 | O62: =IF(N62="","",N62-I62) | Q62: =IF($A62="",0,IFERROR(INDEX('MATERIALS DB'!$K$4:$K$465,MATCH($A62,'MATERIALS DB'!$A$4:$A$465,0)),0)) -> 0 | R62: =IF($A62="",0,IF(OR(D62="All-in-one System",AND(D62="Inverter",OR(ISNUMBER(SEARCH("hybrid",C62)),ISNUMBER(SEARCH("off-grid",C62))))),1,0)) -> 0
C63: =IF($A63="","",IFERROR(INDEX('MATERIALS DB'!$D$4:$D$465,MATCH($A63,'MATERIALS DB'!$A$4:$A$465,0)),"Code not found")) | D63: =IF($A63="","",IFERROR(INDEX('MATERIALS DB'!$B$4:$B$465,MATCH($A63,'MATERIALS DB'!$A$4:$A$465,0)),"")) | E63: =IF($A63="","",IFERROR(INDEX('MATERIALS DB'!$C$4:$C$465,MATCH($A63,'MATERIALS DB'!$A$4:$A$465,0)),"")) | F63: =IF($A63="","",IFERROR(INDEX('MATERIALS DB'!$F$4:$F$465,MATCH($A63,'MATERIALS DB'!$A$4:$A$465,0)),"")) | G63: =IF($A63="",0,IFERROR(INDEX('MATERIALS DB'!$W$4:$W$465,MATCH($A63,'MATERIALS DB'!$A$4:$A$465,0)),0)) -> 0 | H63: =IF($A63="",0,IFERROR(INDEX('MATERIALS DB'!$Y$4:$Y$465,MATCH($A63,'MATERIALS DB'!$A$4:$A$465,0)),0)) -> 0 | I63: =B63*G63 -> 0 | J63: =I63*H63 -> 0 | K63: =I63+J63 -> 0 | L63: =IF($A63="",0,IFERROR(B63*INDEX('MATERIALS DB'!$Q$4:$Q$465,MATCH($A63,'MATERIALS DB'!$A$4:$A$465,0))*(INDEX(SUPPLIERS!$F$3:$F$30,MATCH(E63,SUPPLIERS!$A$3:$A$30,0))<>"Yes"),0)) -> 0 | M63: =IF($A63="",0,IFERROR(INDEX('MATERIALS DB'!$N$4:$N$465,MATCH($A63,'MATERIALS DB'!$A$4:$A$465,0)),0)) -> 0 | O63: =IF(N63="","",N63-I63) | Q63: =IF($A63="",0,IFERROR(INDEX('MATERIALS DB'!$K$4:$K$465,MATCH($A63,'MATERIALS DB'!$A$4:$A$465,0)),0)) -> 0 | R63: =IF($A63="",0,IF(OR(D63="All-in-one System",AND(D63="Inverter",OR(ISNUMBER(SEARCH("hybrid",C63)),ISNUMBER(SEARCH("off-grid",C63))))),1,0)) -> 0
C64: =IF($A64="","",IFERROR(INDEX('MATERIALS DB'!$D$4:$D$465,MATCH($A64,'MATERIALS DB'!$A$4:$A$465,0)),"Code not found")) | D64: =IF($A64="","",IFERROR(INDEX('MATERIALS DB'!$B$4:$B$465,MATCH($A64,'MATERIALS DB'!$A$4:$A$465,0)),"")) | E64: =IF($A64="","",IFERROR(INDEX('MATERIALS DB'!$C$4:$C$465,MATCH($A64,'MATERIALS DB'!$A$4:$A$465,0)),"")) | F64: =IF($A64="","",IFERROR(INDEX('MATERIALS DB'!$F$4:$F$465,MATCH($A64,'MATERIALS DB'!$A$4:$A$465,0)),"")) | G64: =IF($A64="",0,IFERROR(INDEX('MATERIALS DB'!$W$4:$W$465,MATCH($A64,'MATERIALS DB'!$A$4:$A$465,0)),0)) -> 0 | H64: =IF($A64="",0,IFERROR(INDEX('MATERIALS DB'!$Y$4:$Y$465,MATCH($A64,'MATERIALS DB'!$A$4:$A$465,0)),0)) -> 0 | I64: =B64*G64 -> 0 | J64: =I64*H64 -> 0 | K64: =I64+J64 -> 0 | L64: =IF($A64="",0,IFERROR(B64*INDEX('MATERIALS DB'!$Q$4:$Q$465,MATCH($A64,'MATERIALS DB'!$A$4:$A$465,0))*(INDEX(SUPPLIERS!$F$3:$F$30,MATCH(E64,SUPPLIERS!$A$3:$A$30,0))<>"Yes"),0)) -> 0 | M64: =IF($A64="",0,IFERROR(INDEX('MATERIALS DB'!$N$4:$N$465,MATCH($A64,'MATERIALS DB'!$A$4:$A$465,0)),0)) -> 0 | O64: =IF(N64="","",N64-I64) | Q64: =IF($A64="",0,IFERROR(INDEX('MATERIALS DB'!$K$4:$K$465,MATCH($A64,'MATERIALS DB'!$A$4:$A$465,0)),0)) -> 0 | R64: =IF($A64="",0,IF(OR(D64="All-in-one System",AND(D64="Inverter",OR(ISNUMBER(SEARCH("hybrid",C64)),ISNUMBER(SEARCH("off-grid",C64))))),1,0)) -> 0
C65: =IF($A65="","",IFERROR(INDEX('MATERIALS DB'!$D$4:$D$465,MATCH($A65,'MATERIALS DB'!$A$4:$A$465,0)),"Code not found")) | D65: =IF($A65="","",IFERROR(INDEX('MATERIALS DB'!$B$4:$B$465,MATCH($A65,'MATERIALS DB'!$A$4:$A$465,0)),"")) | E65: =IF($A65="","",IFERROR(INDEX('MATERIALS DB'!$C$4:$C$465,MATCH($A65,'MATERIALS DB'!$A$4:$A$465,0)),"")) | F65: =IF($A65="","",IFERROR(INDEX('MATERIALS DB'!$F$4:$F$465,MATCH($A65,'MATERIALS DB'!$A$4:$A$465,0)),"")) | G65: =IF($A65="",0,IFERROR(INDEX('MATERIALS DB'!$W$4:$W$465,MATCH($A65,'MATERIALS DB'!$A$4:$A$465,0)),0)) -> 0 | H65: =IF($A65="",0,IFERROR(INDEX('MATERIALS DB'!$Y$4:$Y$465,MATCH($A65,'MATERIALS DB'!$A$4:$A$465,0)),0)) -> 0 | I65: =B65*G65 -> 0 | J65: =I65*H65 -> 0 | K65: =I65+J65 -> 0 | L65: =IF($A65="",0,IFERROR(B65*INDEX('MATERIALS DB'!$Q$4:$Q$465,MATCH($A65,'MATERIALS DB'!$A$4:$A$465,0))*(INDEX(SUPPLIERS!$F$3:$F$30,MATCH(E65,SUPPLIERS!$A$3:$A$30,0))<>"Yes"),0)) -> 0 | M65: =IF($A65="",0,IFERROR(INDEX('MATERIALS DB'!$N$4:$N$465,MATCH($A65,'MATERIALS DB'!$A$4:$A$465,0)),0)) -> 0 | O65: =IF(N65="","",N65-I65) | Q65: =IF($A65="",0,IFERROR(INDEX('MATERIALS DB'!$K$4:$K$465,MATCH($A65,'MATERIALS DB'!$A$4:$A$465,0)),0)) -> 0 | R65: =IF($A65="",0,IF(OR(D65="All-in-one System",AND(D65="Inverter",OR(ISNUMBER(SEARCH("hybrid",C65)),ISNUMBER(SEARCH("off-grid",C65))))),1,0)) -> 0
C66: =IF($A66="","",IFERROR(INDEX('MATERIALS DB'!$D$4:$D$465,MATCH($A66,'MATERIALS DB'!$A$4:$A$465,0)),"Code not found")) | D66: =IF($A66="","",IFERROR(INDEX('MATERIALS DB'!$B$4:$B$465,MATCH($A66,'MATERIALS DB'!$A$4:$A$465,0)),"")) | E66: =IF($A66="","",IFERROR(INDEX('MATERIALS DB'!$C$4:$C$465,MATCH($A66,'MATERIALS DB'!$A$4:$A$465,0)),"")) | F66: =IF($A66="","",IFERROR(INDEX('MATERIALS DB'!$F$4:$F$465,MATCH($A66,'MATERIALS DB'!$A$4:$A$465,0)),"")) | G66: =IF($A66="",0,IFERROR(INDEX('MATERIALS DB'!$W$4:$W$465,MATCH($A66,'MATERIALS DB'!$A$4:$A$465,0)),0)) -> 0 | H66: =IF($A66="",0,IFERROR(INDEX('MATERIALS DB'!$Y$4:$Y$465,MATCH($A66,'MATERIALS DB'!$A$4:$A$465,0)),0)) -> 0 | I66: =B66*G66 -> 0 | J66: =I66*H66 -> 0 | K66: =I66+J66 -> 0 | L66: =IF($A66="",0,IFERROR(B66*INDEX('MATERIALS DB'!$Q$4:$Q$465,MATCH($A66,'MATERIALS DB'!$A$4:$A$465,0))*(INDEX(SUPPLIERS!$F$3:$F$30,MATCH(E66,SUPPLIERS!$A$3:$A$30,0))<>"Yes"),0)) -> 0 | M66: =IF($A66="",0,IFERROR(INDEX('MATERIALS DB'!$N$4:$N$465,MATCH($A66,'MATERIALS DB'!$A$4:$A$465,0)),0)) -> 0 | O66: =IF(N66="","",N66-I66) | Q66: =IF($A66="",0,IFERROR(INDEX('MATERIALS DB'!$K$4:$K$465,MATCH($A66,'MATERIALS DB'!$A$4:$A$465,0)),0)) -> 0 | R66: =IF($A66="",0,IF(OR(D66="All-in-one System",AND(D66="Inverter",OR(ISNUMBER(SEARCH("hybrid",C66)),ISNUMBER(SEARCH("off-grid",C66))))),1,0)) -> 0
C67: =IF($A67="","",IFERROR(INDEX('MATERIALS DB'!$D$4:$D$465,MATCH($A67,'MATERIALS DB'!$A$4:$A$465,0)),"Code not found")) | D67: =IF($A67="","",IFERROR(INDEX('MATERIALS DB'!$B$4:$B$465,MATCH($A67,'MATERIALS DB'!$A$4:$A$465,0)),"")) | E67: =IF($A67="","",IFERROR(INDEX('MATERIALS DB'!$C$4:$C$465,MATCH($A67,'MATERIALS DB'!$A$4:$A$465,0)),"")) | F67: =IF($A67="","",IFERROR(INDEX('MATERIALS DB'!$F$4:$F$465,MATCH($A67,'MATERIALS DB'!$A$4:$A$465,0)),"")) | G67: =IF($A67="",0,IFERROR(INDEX('MATERIALS DB'!$W$4:$W$465,MATCH($A67,'MATERIALS DB'!$A$4:$A$465,0)),0)) -> 0 | H67: =IF($A67="",0,IFERROR(INDEX('MATERIALS DB'!$Y$4:$Y$465,MATCH($A67,'MATERIALS DB'!$A$4:$A$465,0)),0)) -> 0 | I67: =B67*G67 -> 0 | J67: =I67*H67 -> 0 | K67: =I67+J67 -> 0 | L67: =IF($A67="",0,IFERROR(B67*INDEX('MATERIALS DB'!$Q$4:$Q$465,MATCH($A67,'MATERIALS DB'!$A$4:$A$465,0))*(INDEX(SUPPLIERS!$F$3:$F$30,MATCH(E67,SUPPLIERS!$A$3:$A$30,0))<>"Yes"),0)) -> 0 | M67: =IF($A67="",0,IFERROR(INDEX('MATERIALS DB'!$N$4:$N$465,MATCH($A67,'MATERIALS DB'!$A$4:$A$465,0)),0)) -> 0 | O67: =IF(N67="","",N67-I67) | Q67: =IF($A67="",0,IFERROR(INDEX('MATERIALS DB'!$K$4:$K$465,MATCH($A67,'MATERIALS DB'!$A$4:$A$465,0)),0)) -> 0 | R67: =IF($A67="",0,IF(OR(D67="All-in-one System",AND(D67="Inverter",OR(ISNUMBER(SEARCH("hybrid",C67)),ISNUMBER(SEARCH("off-grid",C67))))),1,0)) -> 0
C68: =IF($A68="","",IFERROR(INDEX('MATERIALS DB'!$D$4:$D$465,MATCH($A68,'MATERIALS DB'!$A$4:$A$465,0)),"Code not found")) | D68: =IF($A68="","",IFERROR(INDEX('MATERIALS DB'!$B$4:$B$465,MATCH($A68,'MATERIALS DB'!$A$4:$A$465,0)),"")) | E68: =IF($A68="","",IFERROR(INDEX('MATERIALS DB'!$C$4:$C$465,MATCH($A68,'MATERIALS DB'!$A$4:$A$465,0)),"")) | F68: =IF($A68="","",IFERROR(INDEX('MATERIALS DB'!$F$4:$F$465,MATCH($A68,'MATERIALS DB'!$A$4:$A$465,0)),"")) | G68: =IF($A68="",0,IFERROR(INDEX('MATERIALS DB'!$W$4:$W$465,MATCH($A68,'MATERIALS DB'!$A$4:$A$465,0)),0)) -> 0 | H68: =IF($A68="",0,IFERROR(INDEX('MATERIALS DB'!$Y$4:$Y$465,MATCH($A68,'MATERIALS DB'!$A$4:$A$465,0)),0)) -> 0 | I68: =B68*G68 -> 0 | J68: =I68*H68 -> 0 | K68: =I68+J68 -> 0 | L68: =IF($A68="",0,IFERROR(B68*INDEX('MATERIALS DB'!$Q$4:$Q$465,MATCH($A68,'MATERIALS DB'!$A$4:$A$465,0))*(INDEX(SUPPLIERS!$F$3:$F$30,MATCH(E68,SUPPLIERS!$A$3:$A$30,0))<>"Yes"),0)) -> 0 | M68: =IF($A68="",0,IFERROR(INDEX('MATERIALS DB'!$N$4:$N$465,MATCH($A68,'MATERIALS DB'!$A$4:$A$465,0)),0)) -> 0 | O68: =IF(N68="","",N68-I68) | Q68: =IF($A68="",0,IFERROR(INDEX('MATERIALS DB'!$K$4:$K$465,MATCH($A68,'MATERIALS DB'!$A$4:$A$465,0)),0)) -> 0 | R68: =IF($A68="",0,IF(OR(D68="All-in-one System",AND(D68="Inverter",OR(ISNUMBER(SEARCH("hybrid",C68)),ISNUMBER(SEARCH("off-grid",C68))))),1,0)) -> 0
C69: =IF($A69="","",IFERROR(INDEX('MATERIALS DB'!$D$4:$D$465,MATCH($A69,'MATERIALS DB'!$A$4:$A$465,0)),"Code not found")) | D69: =IF($A69="","",IFERROR(INDEX('MATERIALS DB'!$B$4:$B$465,MATCH($A69,'MATERIALS DB'!$A$4:$A$465,0)),"")) | E69: =IF($A69="","",IFERROR(INDEX('MATERIALS DB'!$C$4:$C$465,MATCH($A69,'MATERIALS DB'!$A$4:$A$465,0)),"")) | F69: =IF($A69="","",IFERROR(INDEX('MATERIALS DB'!$F$4:$F$465,MATCH($A69,'MATERIALS DB'!$A$4:$A$465,0)),"")) | G69: =IF($A69="",0,IFERROR(INDEX('MATERIALS DB'!$W$4:$W$465,MATCH($A69,'MATERIALS DB'!$A$4:$A$465,0)),0)) -> 0 | H69: =IF($A69="",0,IFERROR(INDEX('MATERIALS DB'!$Y$4:$Y$465,MATCH($A69,'MATERIALS DB'!$A$4:$A$465,0)),0)) -> 0 | I69: =B69*G69 -> 0 | J69: =I69*H69 -> 0 | K69: =I69+J69 -> 0 | L69: =IF($A69="",0,IFERROR(B69*INDEX('MATERIALS DB'!$Q$4:$Q$465,MATCH($A69,'MATERIALS DB'!$A$4:$A$465,0))*(INDEX(SUPPLIERS!$F$3:$F$30,MATCH(E69,SUPPLIERS!$A$3:$A$30,0))<>"Yes"),0)) -> 0 | M69: =IF($A69="",0,IFERROR(INDEX('MATERIALS DB'!$N$4:$N$465,MATCH($A69,'MATERIALS DB'!$A$4:$A$465,0)),0)) -> 0 | O69: =IF(N69="","",N69-I69) | Q69: =IF($A69="",0,IFERROR(INDEX('MATERIALS DB'!$K$4:$K$465,MATCH($A69,'MATERIALS DB'!$A$4:$A$465,0)),0)) -> 0 | R69: =IF($A69="",0,IF(OR(D69="All-in-one System",AND(D69="Inverter",OR(ISNUMBER(SEARCH("hybrid",C69)),ISNUMBER(SEARCH("off-grid",C69))))),1,0)) -> 0
... C72: =IF($A72="","",IFERROR(INDEX('MATERIALS DB'!$D$4:$D$465,MATCH($A72,'MATERIALS DB'!$A$4:$A$465,0)),"Code not found")) | D72: =IF($A72="","",IFERROR(INDEX('MATERIALS DB'!$B$4:$B$465,MATCH($A72,'MATERIALS DB'!$A$4:$A$465,0)),"")) | E72: =IF($A72="","",IFERROR(INDEX('MATERIALS DB'!$C$4:$C$465,MATCH($A72,'MATERIALS DB'!$A$4:$A$465,0)),"")) | F72: =IF($A72="","",IFERROR(INDEX('MATERIALS DB'!$F$4:$F$465,MATCH($A72,'MATERIALS DB'!$A$4:$A$465,0)),"")) | G72: =IF($A72="",0,IFERROR(INDEX('MATERIALS DB'!$W$4:$W$465,MATCH($A72,'MATERIALS DB'!$A$4:$A$465,0)),0)) -> 0 | H72: =IF($A72="",0,IFERROR(INDEX('MATERIALS DB'!$Y$4:$Y$465,MATCH($A72,'MATERIALS DB'!$A$4:$A$465,0)),0)) -> 0 | I72: =B72*G72 -> 0 | J72: =I72*H72 -> 0 | K72: =I72+J72 -> 0 | L72: =IF($A72="",0,IFERROR(B72*INDEX('MATERIALS DB'!$Q$4:$Q$465,MATCH($A72,'MATERIALS DB'!$A$4:$A$465,0))*(INDEX(SUPPLIERS!$F$3:$F$30,MATCH(E72,SUPPLIERS!$A$3:$A$30,0))<>"Yes"),0)) -> 0 | M72: =IF($A72="",0,IFERROR(INDEX('MATERIALS DB'!$N$4:$N$465,MATCH($A72,'MATERIALS DB'!$A$4:$A$465,0)),0)) -> 0 | O72: =IF(N72="","",N72-I72) | Q72: =IF($A72="",0,IFERROR(INDEX('MATERIALS DB'!$K$4:$K$465,MATCH($A72,'MATERIALS DB'!$A$4:$A$465,0)),0)) -> 0 | R72: =IF($A72="",0,IF(OR(D72="All-in-one System",AND(D72="Inverter",OR(ISNUMBER(SEARCH("hybrid",C72)),ISNUMBER(SEARCH("off-grid",C72))))),1,0)) -> 0
A73: BOM total | I73: =SUM(I33:I72) -> 207458.82 | J73: =SUM(J33:J72) -> 31753.671 | K73: =SUM(K33:K72) -> 239212.49 | L73: =SUM(L33:L72) -> 0.14471623 | N73: =SUM(N33:N72) -> 0 | P73: Add rows above 72 by inserting inside the range so the totals follow
A75: FREIGHT - pickup run for the suppliers this job buys from
A76: Stop | B76: Location # | C76: On this run? | D76: Last stop so far | E76: Leg km | F76: Leg toll
A77: Pila base | B77: 1 | C77: Yes | D77: =B77 -> 1 | E77: 0 | F77: 0
A78: IAN Solar | B78: 2 | C78: =IF(AND(INDEX(SUPPLIERS!$F$3:$F$30,MATCH(A78,SUPPLIERS!$A$3:$A$30,0))<>"Yes",SUMPRODUCT(($E$33:$E$72=A78)*($B$33:$B$72>0))>0),"Yes","No") -> Yes | D78: =IF(C78="Yes",B78,D77) -> 2 | E78: =IF(C78="Yes",INDEX(ROUTE!$B$13:$G$18,D77,B78),0) -> 110 | F78: =IF(C78="Yes",INDEX(ROUTE!$B$22:$G$27,D77,B78),0) -> 1110
A79: Felicity Solar | B79: 3 | C79: =IF(AND(INDEX(SUPPLIERS!$F$3:$F$30,MATCH(A79,SUPPLIERS!$A$3:$A$30,0))<>"Yes",SUMPRODUCT(($E$33:$E$72=A79)*($B$33:$B$72>0))>0),"Yes","No") -> Yes | D79: =IF(C79="Yes",B79,D78) -> 3 | E79: =IF(C79="Yes",INDEX(ROUTE!$B$13:$G$18,D78,B79),0) -> 22 | F79: =IF(C79="Yes",INDEX(ROUTE!$B$22:$G$27,D78,B79),0) -> 528
A80: One Point | B80: 4 | C80: =IF(AND(INDEX(SUPPLIERS!$F$3:$F$30,MATCH(A80,SUPPLIERS!$A$3:$A$30,0))<>"Yes",SUMPRODUCT(($E$33:$E$72=A80)*($B$33:$B$72>0))>0),"Yes","No") -> Yes | D80: =IF(C80="Yes",B80,D79) -> 4 | E80: =IF(C80="Yes",INDEX(ROUTE!$B$13:$G$18,D79,B80),0) -> 18 | F80: =IF(C80="Yes",INDEX(ROUTE!$B$22:$G$27,D79,B80),0) -> 329
A81: Blue Carbon | B81: 5 | C81: =IF(AND(INDEX(SUPPLIERS!$F$3:$F$30,MATCH(A81,SUPPLIERS!$A$3:$A$30,0))<>"Yes",SUMPRODUCT(($E$33:$E$72=A81)*($B$33:$B$72>0))>0),"Yes","No") -> Yes | D81: =IF(C81="Yes",B81,D80) -> 5 | E81: =IF(C81="Yes",INDEX(ROUTE!$B$13:$G$18,D80,B81),0) -> 20 | F81: =IF(C81="Yes",INDEX(ROUTE!$B$22:$G$27,D80,B81),0) -> 149
A82: Job site | B82: 6 | C82: Yes | D82: =IF(C82="Yes",B82,D81) -> 6 | E82: =IF(C82="Yes",INDEX(ROUTE!$B$13:$G$18,D81,B82),0) -> 55 | F82: =IF(C82="Yes",INDEX(ROUTE!$B$22:$G$27,D81,B82),0) -> 104
A83: Pila base | B83: 1 | C83: Yes | D83: =IF(C83="Yes",B83,D82) -> 1 | E83: =IF(C83="Yes",INDEX(ROUTE!$B$13:$G$18,D82,B83),0) -> 10 | F83: =IF(C83="Yes",INDEX(ROUTE!$B$22:$G$27,D82,B83),0) -> 0
A84: Loop km (+ 2 x extra km) | B84: =SUM(E77:E83)+2*B7 -> 235
A85: Toll (+ extra toll) | B85: =SUM(F77:F83)+B8 -> 2220
A86: Run cost | B86: =(DRIVERS!B7+DRIVERS!B8+DRIVERS!B9)*DRIVERS!B18+B84*DRIVERS!B13+B85 -> 17282.143 | C86: Ownership, driver, helper per trip-day + km x running cost + toll
A87: Truck share of this BOM | B87: =L73 -> 0.14471623
A88: Trips | B88: =IF(L73=0,0,ROUNDUP(L73,0)) -> 1 | C88: A second trip is assumed to repeat the whole route
A89: Freight | B89: =B88*B86 -> 17282.143
A91: LABOR, MOB/DEMOB AND TOOLS (from LABOR CALC, last column)
A92: Installation man-hours | B92: ='LABOR CALC'!I41 -> 15.864372
A93: Crew | B93: ='LABOR CALC'!I58 -> 1 team lead, 1 skilled, 2 laborers
A94: Persons on site | B94: ='LABOR CALC'!I57 -> 4
A95: Installation days | B95: ='LABOR CALC'!I56 -> 1
A96: Person-days | B96: ='LABOR CALC'!I67 -> 4
A97: Labor | B97: ='LABOR CALC'!I66 -> 6500
A98: Mob/demob | B98: ='LABOR CALC'!I73+B95*(2*B7*'MOB-DEMOB'!B12+B8) -> 1300 | C98: Extra km for a farther site added per day
A99: Tools | B99: ='LABOR CALC'!I80 -> 905.62498
A101: PRICE BUILD-UP
A102: Markup on labor, mob/demob, tools, PPE and the seal (input) | B102: 0.3 | C102: Your "all others" tier
A103: PPE per person-day (input) | B103: 100 | C103: Est. - harnesses, lifeline, insulated gloves, hard hats over about 3 years, plus disposable gloves and masks. Replace once you buy the PPE
A104: OCM share of markup (input) | B104: 0.5 | C104: The rest is OP
A106: Line | B106: Direct cost | C106: Markup tier | D106: Markup | E106: Selling price (before commission, VAT) | F106: Actual cost (close-out input) | G106: Remarks
A107: Materials (BOM) | B107: =I73 -> 207458.82 | C107: By item | D107: =J73 -> 31753.671 | E107: =B107+D107 -> 239212.49 | F107: =IF(COUNT(N33:N72)=0,"",SUM(N33:N72)+SUMPRODUCT((N33:N72="")*I33:I72)) | G107: Item tiers: panels and inverters 10%, batteries 15%, others 30%
A108: Freight | B108: =B89 -> 17282.143 | C108: =DRIVERS!B28 -> 0.15 | D108: =B108*C108 -> 2592.3214 | E108: =B108+D108 -> 19874.464
A109: Labor | B109: =B97 -> 6500 | C109: =$B$102 -> 0.3 | D109: =B109*C109 -> 1950 | E109: =B109+D109 -> 8450
A110: Mob/demob | B110: =B98 -> 1300 | C110: =$B$102 -> 0.3 | D110: =B110*C110 -> 390 | E110: =B110+D110 -> 1690
A111: Tools | B111: =B99 -> 905.62498 | C111: =$B$102 -> 0.3 | D111: =B111*C111 -> 271.68749 | E111: =B111+D111 -> 1177.3125
A112: PPE | B112: =B96*$B$103 -> 400 | C112: =$B$102 -> 0.3 | D112: =B112*C112 -> 120 | E112: =B112+D112 -> 520 | G112: Est. per person-day
A113: PEE sign and seal | B113: 1000 | C113: =$B$102 -> 0.3 | D113: =B113*C113 -> 300 | E113: =B113+D113 -> 1300 | G113: Your figure: P1,000, one seal per job
A114: LGU electrical permit and CFEI | B114: 5000 | C114: 0 | D114: =B114*C114 -> 0 | E114: =B114+D114 -> 5000 | G114: Est. - ask the municipal engineering office for the actual fees. Passed through at cost
A115: ERC Certificate of Compliance fee (net metering) | B115: =IF(($B$9="Yes"),1500,0) -> 1500 | C115: 0 | D115: =B115*C115 -> 0 | E115: =B115+D115 -> 1500 | G115: P1,500 per Meralco. Passed through at cost
A116: Bi-directional meter difference (net metering) | B116: =IF(($B$9="Yes"),3000,0) -> 3000 | C116: 0 | D116: =B116*C116 -> 0 | E116: =B116+D116 -> 3000 | G116: Up to P3,000 for residential per Meralco (ERC advisory, Sep 22, 2025). Passed through at cost
A117: Total | B117: =SUM(B107:B116) -> 244346.59 | C117: =D117/B117 -> 0.15296993 | D117: =SUM(D107:D116) -> 37377.68 | E117: =SUM(E107:E116) -> 281724.27 | G117: Markup over direct cost
A119: Agent commission (5% of direct cost) | B119: =B117*DRIVERS!B26 -> 12217.329
A120: Contract price, VAT-exclusive | B120: =E117+B119 -> 293941.6
A121: VAT 12% | B121: =B120*DRIVERS!B27 -> 35272.992
A122: CONTRACT PRICE, VAT-inclusive | B122: =B120+B121 -> 329214.59
...

Sheet MATERIALS DB
A1: MATERIALS DB - landed cost per unit before freight, and selling price. Freight is one line per job. Sorted by category, then supplier
A3: Code | B3: Category (input) | C3: Supplier (input) | D3: Item | E3: Model / spec | F3: Unit | G3: Sold as | H3: List price, VAT-ex (input) | I3: Dealer discount | J3: Net price | K3: Rating (input) | L3: Rating unit | M3: Net price per rating unit | N3: Package weight kg (input) | O3: Package volume m3 (input) | P3: Weight/volume source | Q3: Truck share per unit | R3: Units per full truck | S3: Handling | T3: Wastage | U3: Payment fee | V3: Storage (input) | W3: LANDED COST before freight | X3: Landed over net price | Y3: Markup tier | Z3: Selling price (before freight, commission, VAT) | AA3: Customer price (with 5% commission, VAT; freight not included) | AB3: Price list date | AC3: Previous price (Sep 7) | AD3: Remarks
A4: BC-PNL-001 | B4: Solar Panel | C4: Blue Carbon | D4: 585W Monofacial solar panel | E4: BCT-585M10NH-144, TOPCon, 2278x1134x30 mm | F4: pc | G4: pc | H4: 4950 | I4: =INDEX(SUPPLIERS!$D$3:$D$30,MATCH(C4,SUPPLIERS!$A$3:$A$30,0)) -> 0 | J4: =H4*(1-I4) -> 4950 | K4: 585 | L4: W | M4: =IF(K4="","",J4/K4) -> 8.4615385 | N4: 26 | O4: 0.08525 | P4: Datasheet (volume +10% packing) | Q4: =MAX(N4/DRIVERS!$B$5,O4/DRIVERS!$B$6) -> 0.0086666667 | R4: =ROUNDDOWN(1/Q4,0) -> 115 | S4: =DRIVERS!$B$23*Q4/DRIVERS!$B$24 -> 44.988024 | T4: =J4*INDEX(DRIVERS!$C$32:$C$42,MATCH(B4,DRIVERS!$A$32:$A$42,0)) -> 0 | U4: =J4*INDEX(SUPPLIERS!$E$3:$E$30,MATCH(C4,SUPPLIERS!$A$3:$A$30,0)) -> 0 | V4: 0 | W4: =J4+S4+T4+U4+V4 -> 4994.988 | X4: =W4/J4-1 -> 0.0090884897 | Y4: =INDEX(DRIVERS!$B$32:$B$42,MATCH(B4,DRIVERS!$A$32:$A$42,0)) -> 0.1 | Z4: =W4*(1+Y4) -> 5494.4868 | AA4: =W4*(1+Y4+DRIVERS!$B$26)*(1+DRIVERS!$B$27) -> 6433.5446 | AB4: Sep 19, 2026 | AC4: 4950 | AD4: Price list model code BCT-16M-144-585W
A5: BC-PNL-002 | B5: Solar Panel | C5: Blue Carbon | D5: 585W Bifacial solar panel | E5: BCT-585M10NHB-144, TOPCon, 2278x1134x30 mm | F5: pc | G5: pc | H5: 4980 | I5: =INDEX(SUPPLIERS!$D$3:$D$30,MATCH(C5,SUPPLIERS!$A$3:$A$30,0)) -> 0 | J5: =H5*(1-I5) -> 4980 | K5: 585 | L5: W | M5: =IF(K5="","",J5/K5) -> 8.5128205 | N5: 30.2 | O5: 0.08525 | P5: Datasheet (volume +10% packing) | Q5: =MAX(N5/DRIVERS!$B$5,O5/DRIVERS!$B$6) -> 0.010066667 | R5: =ROUNDDOWN(1/Q5,0) -> 99 | S5: =DRIVERS!$B$23*Q5/DRIVERS!$B$24 -> 52.25532 | T5: =J5*INDEX(DRIVERS!$C$32:$C$42,MATCH(B5,DRIVERS!$A$32:$A$42,0)) -> 0 | U5: =J5*INDEX(SUPPLIERS!$E$3:$E$30,MATCH(C5,SUPPLIERS!$A$3:$A$30,0)) -> 0 | V5: 0 | W5: =J5+S5+T5+U5+V5 -> 5032.2553 | X5: =W5/J5-1 -> 0.010493036 | Y5: =INDEX(DRIVERS!$B$32:$B$42,MATCH(B5,DRIVERS!$A$32:$A$42,0)) -> 0.1 | Z5: =W5*(1+Y5) -> 5535.4809 | AA5: =W5*(1+Y5+DRIVERS!$B$26)*(1+DRIVERS!$B$27) -> 6481.5449 | AB5: Sep 19, 2026 | AC5: 4980
A6: BC-PNL-003 | B6: Solar Panel | C6: Blue Carbon | D6: 600W Monofacial solar panel | E6: BCT-600G12RNH-132, TOPCon, 2382x1134x30 mm | F6: pc | G6: pc | H6: 4999 | I6: =INDEX(SUPPLIERS!$D$3:$D$30,MATCH(C6,SUPPLIERS!$A$3:$A$30,0)) -> 0 | J6: =H6*(1-I6) -> 4999 | K6: 600 | L6: W | M6: =IF(K6="","",J6/K6) -> 8.3316667 | N6: 27.7 | O6: 0.08914 | P6: Datasheet (volume +10% packing) | Q6: =MAX(N6/DRIVERS!$B$5,O6/DRIVERS!$B$6) -> 0.0092333333 | R6: =ROUNDDOWN(1/Q6,0) -> 108 | S6: =DRIVERS!$B$23*Q6/DRIVERS!$B$24 -> 47.929548 | T6: =J6*INDEX(DRIVERS!$C$32:$C$42,MATCH(B6,DRIVERS!$A$32:$A$42,0)) -> 0 | U6: =J6*INDEX(SUPPLIERS!$E$3:$E$30,MATCH(C6,SUPPLIERS!$A$3:$A$30,0)) -> 0 | V6: 0 | W6: =J6+S6+T6+U6+V6 -> 5046.9295 | X6: =W6/J6-1 -> 0.0095878273 | Y6: =INDEX(DRIVERS!$B$32:$B$42,MATCH(B6,DRIVERS!$A$32:$A$42,0)) -> 0.1 | Z6: =W6*(1+Y6) -> 5551.6225 | AA6: =W6*(1+Y6+DRIVERS!$B$26)*(1+DRIVERS!$B$27) -> 6500.4453 | AB6: Sep 19, 2026 | AC6: 4999 | AD6: CHECK: the Sep 7 list gives model BCT-G12RNHB-132-600, which is the bifacial code (32.0 kg). Confirm mono or bifacial
A7: BC-PNL-004 | B7: Solar Panel | C7: Blue Carbon | D7: 630W Bifacial solar panel | E7: Datasheet received: BCT-630G12RNH-132 (monofacial), 2382x1134x30 mm | F7: pc | G7: pc | H7: 5450 | I7: =INDEX(SUPPLIERS!$D$3:$D$30,MATCH(C7,SUPPLIERS!$A$3:$A$30,0)) -> 0 | J7: =H7*(1-I7) -> 5450 | K7: 630 | L7: W | M7: =IF(K7="","",J7/K7) -> 8.6507937 | N7: 27.7 | O7: 0.08914 | P7: Datasheet (volume +10% packing) | Q7: =MAX(N7/DRIVERS!$B$5,O7/DRIVERS!$B$6) -> 0.0092333333 | R7: =ROUNDDOWN(1/Q7,0) -> 108 | S7: =DRIVERS!$B$23*Q7/DRIVERS!$B$24 -> 47.929548 | T7: =J7*INDEX(DRIVERS!$C$32:$C$42,MATCH(B7,DRIVERS!$A$32:$A$42,0)) -> 0 | U7: =J7*INDEX(SUPPLIERS!$E$3:$E$30,MATCH(C7,SUPPLIERS!$A$3:$A$30,0)) -> 0 | V7: 0 | W7: =J7+S7+T7+U7+V7 -> 5497.9295 | X7: =W7/J7-1 -> 0.0087944126 | Y7: =INDEX(DRIVERS!$B$32:$B$42,MATCH(B7,DRIVERS!$A$32:$A$42,0)) -> 0.1 | Z7: =W7*(1+Y7) -> 6047.7225 | AA7: =W7*(1+Y7+DRIVERS!$B$26)*(1+DRIVERS!$B$27) -> 7081.3333 | AB7: Sep 19, 2026 | AD7: CHECK: price list says bifacial, datasheet is monofacial. A bifacial 630 W would weigh about 32 kg. New on the Sep 19 list
A8: IAN-PNL-001 | B8: Solar Panel | C8: IAN Solar | D8: JA JAM66D46 720W N-TYPE BIFACIAL | E8: JA Solar; 720 W; N-type; bifacial; Luzon branch price; large-format panel | F8: pc | G8: pc | H8: 6750 | I8: =INDEX(SUPPLIERS!$D$3:$D$30,MATCH(C8,SUPPLIERS!$A$3:$A$30,0)) -> 0 | J8: =H8*(1-I8) -> 6750 | K8: 720 | L8: W | M8: =IF(K8="","",J8/K8) -> 9.375 | N8: 38.2 | O8: 0.11276 | P8: List panel weight; volume = panel size +10% (list packaging is per pallet) | Q8: =MAX(N8/DRIVERS!$B$5,O8/DRIVERS!$B$6) -> 0.012733333 | R8: =ROUNDDOWN(1/Q8,0) -> 78 | S8: =DRIVERS!$B$23*Q8/DRIVERS!$B$24 -> 66.097789 | T8: =J8*INDEX(DRIVERS!$C$32:$C$42,MATCH(B8,DRIVERS!$A$32:$A$42,0)) -> 0 | U8: =J8*INDEX(SUPPLIERS!$E$3:$E$30,MATCH(C8,SUPPLIERS!$A$3:$A$30,0)) -> 0 | V8: 0 | W8: =J8+S8+T8+U8+V8 -> 6816.0978 | X8: =W8/J8-1 -> 0.009792265 | Y8: =INDEX(DRIVERS!$B$32:$B$42,MATCH(B8,DRIVERS!$A$32:$A$42,0)) -> 0.1 | Z8: =W8*(1+Y8) -> 7497.7076 | AA8: =W8*(1+Y8+DRIVERS!$B$26)*(1+DRIVERS!$B$27) -> 8779.134 | AB8: Sep 3, 2026
A9: IAN-PNL-002 | B9: Solar Panel | C9: IAN Solar | D9: IAN670-132BCDGF 670W N-TYPE BIFACIAL BC | E9: IAN Solar; 670 W; N-type; bifacial; back-contact; Luzon branch price | F9: pc | G9: pc | H9: 6400 | I9: =INDEX(SUPPLIERS!$D$3:$D$30,MATCH(C9,SUPPLIERS!$A$3:$A$30,0)) -> 0 | J9: =H9*(1-I9) -> 6400 | K9: 670 | L9: W | M9: =IF(K9="","",J9/K9) -> 9.5522388 | N9: 32.5 | O9: 0.08914 | P9: List panel weight; volume = panel size +10% (list packaging is per pallet) | Q9: =MAX(N9/DRIVERS!$B$5,O9/DRIVERS!$B$6) -> 0.010833333 | R9: =ROUNDDOWN(1/Q9,0) -> 92 | S9: =DRIVERS!$B$23*Q9/DRIVERS!$B$24 -> 56.23503 | T9: =J9*INDEX(DRIVERS!$C$32:$C$42,MATCH(B9,DRIVERS!$A$32:$A$42,0)) -> 0 | U9: =J9*INDEX(SUPPLIERS!$E$3:$E$30,MATCH(C9,SUPPLIERS!$A$3:$A$30,0)) -> 0 | V9: 0 | W9: =J9+S9+T9+U9+V9 -> 6456.235 | X9: =W9/J9-1 -> 0.0087867234 | Y9: =INDEX(DRIVERS!$B$32:$B$42,MATCH(B9,DRIVERS!$A$32:$A$42,0)) -> 0.1 | Z9: =W9*(1+Y9) -> 7101.8585 | AA9: =W9*(1+Y9+DRIVERS!$B$26)*(1+DRIVERS!$B$27) -> 8315.6307 | AB9: Sep 3, 2026
A10: IAN-PNL-003 | B10: Solar Panel | C10: IAN Solar | D10: JA JAM66D45 625W N-TYPE BIFACIAL | E10: JA Solar; 625 W; N-type; bifacial; Luzon branch price | F10: pc | G10: pc | H10: 6150 | I10: =INDEX(SUPPLIERS!$D$3:$D$30,MATCH(C10,SUPPLIERS!$A$3:$A$30,0)) -> 0 | J10: =H10*(1-I10) -> 6150 | K10: 625 | L10: W | M10: =IF(K10="","",J10/K10) -> 9.84 | N10: 33.1 | O10: 0.08914 | P10: List panel weight; volume = panel size +10% (list packaging is per pallet) | Q10: =MAX(N10/DRIVERS!$B$5,O10/DRIVERS!$B$6) -> 0.011033333 | R10: =ROUNDDOWN(1/Q10,0) -> 90 | S10: =DRIVERS!$B$23*Q10/DRIVERS!$B$24 -> 57.273215 | T10: =J10*INDEX(DRIVERS!$C$32:$C$42,MATCH(B10,DRIVERS!$A$32:$A$42,0)) -> 0 | U10: =J10*INDEX(SUPPLIERS!$E$3:$E$30,MATCH(C10,SUPPLIERS!$A$3:$A$30,0)) -> 0 | V10: 0 | W10: =J10+S10+T10+U10+V10 -> 6207.2732 | X10: =W10/J10-1 -> 0.0093127179 | Y10: =INDEX(DRIVERS!$B$32:$B$42,MATCH(B10,DRIVERS!$A$32:$A$42,0)) -> 0.1 | Z10: =W10*(1+Y10) -> 6828.0005 | AA10: =W10*(1+Y10+DRIVERS!$B$26)*(1+DRIVERS!$B$27) -> 7994.9679 | AB10: Sep 3, 2026
A11: IAN-PNL-004 | B11: Solar Panel | C11: IAN Solar | D11: JA JAM66D45 630W N-TYPE BIFACIAL | E11: JA Solar; 630 W; N-type; bifacial; Luzon branch price | F11: pc | G11: pc | H11: 6250 | I11: =INDEX(SUPPLIERS!$D$3:$D$30,MATCH(C11,SUPPLIERS!$A$3:$A$30,0)) -> 0 | J11: =H11*(1-I11) -> 6250 | K11: 630 | L11: W | M11: =IF(K11="","",J11/K11) -> 9.9206349 | N11: 33.1 | O11: 0.08914 | P11: List panel weight; volume = panel size +10% (list packaging is per pallet) | Q11: =MAX(N11/DRIVERS!$B$5,O11/DRIVERS!$B$6) -> 0.011033333 | R11: =ROUNDDOWN(1/Q11,0) -> 90 | S11: =DRIVERS!$B$23*Q11/DRIVERS!$B$24 -> 57.273215 | T11: =J11*INDEX(DRIVERS!$C$32:$C$42,MATCH(B11,DRIVERS!$A$32:$A$42,0)) -> 0 | U11: =J11*INDEX(SUPPLIERS!$E$3:$E$30,MATCH(C11,SUPPLIERS!$A$3:$A$30,0)) -> 0 | V11: 0 | W11: =J11+S11+T11+U11+V11 -> 6307.2732 | X11: =W11/J11-1 -> 0.0091637144 | Y11: =INDEX(DRIVERS!$B$32:$B$42,MATCH(B11,DRIVERS!$A$32:$A$42,0)) -> 0.1 | Z11: =W11*(1+Y11) -> 6938.0005 | AA11: =W11*(1+Y11+DRIVERS!$B$26)*(1+DRIVERS!$B$27) -> 8123.7679 | AB11: Sep 3, 2026
A12: OP-PNL-001 | B12: Solar Panel | C12: One Point | D12: 200W 10BB MONO | E12: Solar Homes; 200 W; Solar Homes | F12: pc | G12: pc | H12: 3000 | I12: =INDEX(SUPPLIERS!$D$3:$D$30,MATCH(C12,SUPPLIERS!$A$3:$A$30,0)) -> 0 | J12: =H12*(1-I12) -> 3000 | K12: 200 | L12: W | M12: =IF(K12="","",J12/K12) -> 15 | N12: 14 | O12: 0.04884 | P12: List panel weight; volume = panel size +10% (list packaging is per pallet) | Q12: =MAX(N12/DRIVERS!$B$5,O12/DRIVERS!$B$6) -> 0.0046666667 | R12: =ROUNDDOWN(1/Q12,0) -> 214 | S12: =DRIVERS!$B$23*Q12/DRIVERS!$B$24 -> 24.224321 | T12: =J12*INDEX(DRIVERS!$C$32:$C$42,MATCH(B12,DRIVERS!$A$32:$A$42,0)) -> 0 | U12: =J12*INDEX(SUPPLIERS!$E$3:$E$30,MATCH(C12,SUPPLIERS!$A$3:$A$30,0)) -> 0 | V12: 0 | W12: =J12+S12+T12+U12+V12 -> 3024.2243 | X12: =W12/J12-1 -> 0.0080747735 | Y12: =INDEX(DRIVERS!$B$32:$B$42,MATCH(B12,DRIVERS!$A$32:$A$42,0)) -> 0.1 | Z12: =W12*(1+Y12) -> 3326.6468 | AA12: =W12*(1+Y12+DRIVERS!$B$26)*(1+DRIVERS!$B$27) -> 3895.2009 | AB12: Sep 11, 2026
A13: OP-PNL-002 | B13: Solar Panel | C13: One Point | D13: 150W 10BB MONO | E13: Solar Homes; 150 W; Solar Homes | F13: pc | G13: pc | H13: 2500 | I13: =INDEX(SUPPLIERS!$D$3:$D$30,MATCH(C13,SUPPLIERS!$A$3:$A$30,0)) -> 0 | J13: =H13*(1-I13) -> 2500 | K13: 150 | L13: W | M13: =IF(K13="","",J13/K13) -> 16.666667 | N13: 9.5 | O13: 0.02638 | P13: List panel weight; volume = panel size +10% (list packaging is per pallet) | Q13: =MAX(N13/DRIVERS!$B$5,O13/DRIVERS!$B$6) -> 0.0031666667 | R13: =ROUNDDOWN(1/Q13,0) -> 315 | S13: =DRIVERS!$B$23*Q13/DRIVERS!$B$24 -> 16.437932 | T13: =J13*INDEX(DRIVERS!$C$32:$C$42,MATCH(B13,DRIVERS!$A$32:$A$42,0)) -> 0 | U13: =J13*INDEX(SUPPLIERS!$E$3:$E$30,MATCH(C13,SUPPLIERS!$A$3:$A$30,0)) -> 0 | V13: 0 | W13: =J13+S13+T13+U13+V13 -> 2516.4379 | X13: =W13/J13-1 -> 0.0065751727 | Y13: =INDEX(DRIVERS!$B$32:$B$42,MATCH(B13,DRIVERS!$A$32:$A$42,0)) -> 0.1 | Z13: =W13*(1+Y13) -> 2768.0817 | AA13: =W13*(1+Y13+DRIVERS!$B$26)*(1+DRIVERS!$B$27) -> 3241.1721 | AB13: Sep 11, 2026
A14: OP-PNL-003 | B14: Solar Panel | C14: One Point | D14: 100W 10BB MONO | E14: Solar Homes; 100 W; Solar Homes | F14: pc | G14: pc | H14: 2000 | I14: =INDEX(SUPPLIERS!$D$3:$D$30,MATCH(C14,SUPPLIERS!$A$3:$A$30,0)) -> 0 | J14: =H14*(1-I14) -> 2000 | K14: 100 | L14: W | M14: =IF(K14="","",J14/K14) -> 20 | N14: 7.8 | O14: 0.01806 | P14: List panel weight; volume = panel size +10% (list packaging is per pallet) | Q14: =MAX(N14/DRIVERS!$B$5,O14/DRIVERS!$B$6) -> 0.0026 | R14: =ROUNDDOWN(1/Q14,0) -> 384 | S14: =DRIVERS!$B$23*Q14/DRIVERS!$B$24 -> 13.496407 | T14: =J14*INDEX(DRIVERS!$C$32:$C$42,MATCH(B14,DRIVERS!$A$32:$A$42,0)) -> 0 | U14: =J14*INDEX(SUPPLIERS!$E$3:$E$30,MATCH(C14,SUPPLIERS!$A$3:$A$30,0)) -> 0 | V14: 0 | W14: =J14+S14+T14+U14+V14 -> 2013.4964 | X14: =W14/J14-1 -> 0.0067482036 | Y14: =INDEX(DRIVERS!$B$32:$B$42,MATCH(B14,DRIVERS!$A$32:$A$42,0)) -> 0.1 | Z14: =W14*(1+Y14) -> 2214.846 | AA14: =W14*(1+Y14+DRIVERS!$B$26)*(1+DRIVERS!$B$27) -> 2593.3834 | AB14: Sep 11, 2026
A15: OP-PNL-004 | B15: Solar Panel | C15: One Point | D15: TRINA-MONO-620W - N TYPE | E15: Trina Solar; 620 W; N-type | F15: pc | G15: pc | H15: 5900 | I15: =INDEX(SUPPLIERS!$D$3:$D$30,MATCH(C15,SUPPLIERS!$A$3:$A$30,0)) -> 0 | J15: =H15*(1-I15) -> 5900 | K15: 620 | L15: W | M15: =IF(K15="","",J15/K15) -> 9.516129 | N15: 27.9 | O15: 0.08914 | P15: List panel weight; volume = panel size +10% (list packaging is per pallet) | Q15: =MAX(N15/DRIVERS!$B$5,O15/DRIVERS!$B$6) -> 0.0093 | R15: =ROUNDDOWN(1/Q15,0) -> 107 | S15: =DRIVERS!$B$23*Q15/DRIVERS!$B$24 -> 48.27561 | T15: =J15*INDEX(DRIVERS!$C$32:$C$42,MATCH(B15,DRIVERS!$A$32:$A$42,0)) -> 0 | U15: =J15*INDEX(SUPPLIERS!$E$3:$E$30,MATCH(C15,SUPPLIERS!$A$3:$A$30,0)) -> 0 | V15: 0 | W15: =J15+S15+T15+U15+V15 -> 5948.2756 | X15: =W15/J15-1 -> 0.0081823068 | Y15: =INDEX(DRIVERS!$B$32:$B$42,MATCH(B15,DRIVERS!$A$32:$A$42,0)) -> 0.1 | Z15: =W15*(1+Y15) -> 6543.1032 | AA15: =W15*(1+Y15+DRIVERS!$B$26)*(1+DRIVERS!$B$27) -> 7661.379 | AB15: Sep 11, 2026
A16: OP-PNL-005 | B16: Solar Panel | C16: One Point | D16: TRINA-MONO-630W - N TYPE | E16: Trina Solar; 630 W; N-type | F16: pc | G16: pc | H16: 6000 | I16: =INDEX(SUPPLIERS!$D$3:$D$30,MATCH(C16,SUPPLIERS!$A$3:$A$30,0)) -> 0 | J16: =H16*(1-I16) -> 6000 | K16: 630 | L16: W | M16: =IF(K16="","",J16/K16) -> 9.5238095 | N16: 27.9 | O16: 0.08914 | P16: List panel weight; volume = panel size +10% (list packaging is per pallet) | Q16: =MAX(N16/DRIVERS!$B$5,O16/DRIVERS!$B$6) -> 0.0093 | R16: =ROUNDDOWN(1/Q16,0) -> 107 | S16: =DRIVERS!$B$23*Q16/DRIVERS!$B$24 -> 48.27561 | T16: =J16*INDEX(DRIVERS!$C$32:$C$42,MATCH(B16,DRIVERS!$A$32:$A$42,0)) -> 0 | U16: =J16*INDEX(SUPPLIERS!$E$3:$E$30,MATCH(C16,SUPPLIERS!$A$3:$A$30,0)) -> 0 | V16: 0 | W16: =J16+S16+T16+U16+V16 -> 6048.2756 | X16: =W16/J16-1 -> 0.008045935 | Y16: =INDEX(DRIVERS!$B$32:$B$42,MATCH(B16,DRIVERS!$A$32:$A$42,0)) -> 0.1 | Z16: =W16*(1+Y16) -> 6653.1032 | AA16: =W16*(1+Y16+DRIVERS!$B$26)*(1+DRIVERS!$B$27) -> 7790.179 | AB16: Sep 11, 2026
A17: OP-PNL-006 | B17: Solar Panel | C17: One Point | D17: AIKO ABC - 665W BI-FACIAL | E17: Aiko; 665 W; bifacial; back-contact | F17: pc | G17: pc | H17: 6600 | I17: =INDEX(SUPPLIERS!$D$3:$D$30,MATCH(C17,SUPPLIERS!$A$3:$A$30,0)) -> 0 | J17: =H17*(1-I17) -> 6600 | K17: 665 | L17: W | M17: =IF(K17="","",J17/K17) -> 9.924812 | N17: 32.5 | O17: 0.08914 | P17: List panel weight; volume = panel size +10% (list packaging is per pallet) | Q17: =MAX(N17/DRIVERS!$B$5,O17/DRIVERS!$B$6) -> 0.010833333 | R17: =ROUNDDOWN(1/Q17,0) -> 92 | S17: =DRIVERS!$B$23*Q17/DRIVERS!$B$24 -> 56.23503 | T17: =J17*INDEX(DRIVERS!$C$32:$C$42,MATCH(B17,DRIVERS!$A$32:$A$42,0)) -> 0 | U17: =J17*INDEX(SUPPLIERS!$E$3:$E$30,MATCH(C17,SUPPLIERS!$A$3:$A$30,0)) -> 0 | V17: 0 | W17: =J17+S17+T17+U17+V17 -> 6656.235 | X17: =W17/J17-1 -> 0.0085204591 | Y17: =INDEX(DRIVERS!$B$32:$B$42,MATCH(B17,DRIVERS!$A$32:$A$42,0)) -> 0.1 | Z17: =W17*(1+Y17) -> 7321.8585 | AA17: =W17*(1+Y17+DRIVERS!$B$26)*(1+DRIVERS!$B$27) -> 8573.2307 | AB17: Sep 11, 2026
A18: BC-INV-001 | B18: Inverter | C18: Blue Carbon | D18: 4 kW 24V hybrid off-grid inverter, single use | E18: BCT-FXC-4KW | F18: pc | G18: pc | H18: 12600 | I18: =INDEX(SUPPLIERS!$D$3:$D$30,MATCH(C18,SUPPLIERS!$A$3:$A$30,0)) -> 0 | J18: =H18*(1-I18) -> 12600 | K18: 4 | L18: kW | M18: =IF(K18="","",J18/K18) -> 3150 | N18: 8 | O18: 0.045 | P18: Est. | Q18: =MAX(N18/DRIVERS!$B$5,O18/DRIVERS!$B$6) -> 0.0031525535 | R18: =ROUNDDOWN(1/Q18,0) -> 317 | S18: =DRIVERS!$B$23*Q18/DRIVERS!$B$24 -> 16.364671 | T18: =J18*INDEX(DRIVERS!$C$32:$C$42,MATCH(B18,DRIVERS!$A$32:$A$42,0)) -> 0 | U18: =J18*INDEX(SUPPLIERS!$E$3:$E$30,MATCH(C18,SUPPLIERS!$A$3:$A$30,0)) -> 0 | V18: 0 | W18: =J18+S18+T18+U18+V18 -> 12616.365 | X18: =W18/J18-1 -> 0.0012987834 | Y18: =INDEX(DRIVERS!$B$32:$B$42,MATCH(B18,DRIVERS!$A$32:$A$42,0)) -> 0.1 | Z18: =W18*(1+Y18) -> 13878.001 | AA18: =W18*(1+Y18+DRIVERS!$B$26)*(1+DRIVERS!$B$27) -> 16249.878 | AB18: Sep 19, 2026 | AC18: 12600 | AD18: Off-grid type
A19: BC-INV-002 | B19: Inverter | C19: Blue Carbon | D19: 6 kW 48V hybrid off-grid inverter, single use | E19: BCT-FXC-6KW | F19: pc | G19: pc | H19: 16200 | I19: =INDEX(SUPPLIERS!$D$3:$D$30,MATCH(C19,SUPPLIERS!$A$3:$A$30,0)) -> 0 | J19: =H19*(1-I19) -> 16200 | K19: 6 | L19: kW | M19: =IF(K19="","",J19/K19) -> 2700 | N19: 9 | O19: 0.048 | P19: Weight: -P datasheet; volume Est. | Q19: =MAX(N19/DRIVERS!$B$5,O19/DRIVERS!$B$6) -> 0.0033627237 | R19: =ROUNDDOWN(1/Q19,0) -> 297 | S19: =DRIVERS!$B$23*Q19/DRIVERS!$B$24 -> 17.455649 | T19: =J19*INDEX(DRIVERS!$C$32:$C$42,MATCH(B19,DRIVERS!$A$32:$A$42,0)) -> 0 | U19: =J19*INDEX(SUPPLIERS!$E$3:$E$30,MATCH(C19,SUPPLIERS!$A$3:$A$30,0)) -> 0 | V19: 0 | W19: =J19+S19+T19+U19+V19 -> 16217.456 | X19: =W19/J19-1 -> 0.0010775092 | Y19: =INDEX(DRIVERS!$B$32:$B$42,MATCH(B19,DRIVERS!$A$32:$A$42,0)) -> 0.1 | Z19: =W19*(1+Y19) -> 17839.201 | AA19: =W19*(1+Y19+DRIVERS!$B$26)*(1+DRIVERS!$B$27) -> 20888.083 | AB19: Sep 19, 2026 | AC19: 16200 | AD19: Off-grid type
A20: BC-INV-003 | B20: Inverter | C20: Blue Carbon | D20: 6 kW 48V hybrid off-grid inverter, parallel | E20: BCT-FXC-6KW-P, 510x306x115 mm | F20: pc | G20: pc | H20: 17400 | I20: =INDEX(SUPPLIERS!$D$3:$D$30,MATCH(C20,SUPPLIERS!$A$3:$A$30,0)) -> 0 | J20: =H20*(1-I20) -> 17400 | K20: 6 | L20: kW | M20: =IF(K20="","",J20/K20) -> 2900 | N20: 9 | O20: 0.048 | P20: Weight: datasheet; volume Est. | Q20: =MAX(N20/DRIVERS!$B$5,O20/DRIVERS!$B$6) -> 0.0033627237 | R20: =ROUNDDOWN(1/Q20,0) -> 297 | S20: =DRIVERS!$B$23*Q20/DRIVERS!$B$24 -> 17.455649 | T20: =J20*INDEX(DRIVERS!$C$32:$C$42,MATCH(B20,DRIVERS!$A$32:$A$42,0)) -> 0 | U20: =J20*INDEX(SUPPLIERS!$E$3:$E$30,MATCH(C20,SUPPLIERS!$A$3:$A$30,0)) -> 0 | V20: 0 | W20: =J20+S20+T20+U20+V20 -> 17417.456 | X20: =W20/J20-1 -> 0.0010031982 | Y20: =INDEX(DRIVERS!$B$32:$B$42,MATCH(B20,DRIVERS!$A$32:$A$42,0)) -> 0.1 | Z20: =W20*(1+Y20) -> 19159.201 | AA20: =W20*(1+Y20+DRIVERS!$B$26)*(1+DRIVERS!$B$27) -> 22433.683 | AB20: Sep 19, 2026 | AC20: 17400 | AD20: Off-grid type with feed-in; PV max 18A / 6,000 W, 500 Voc. CHECK grid-tie certification before any net-metered job
A21: BC-INV-004 | B21: Inverter | C21: Blue Carbon | D21: 6.5 kW 48V hybrid off-grid inverter, parallel | E21: BCT-FXC-6.5KW-P | F21: pc | G21: pc | H21: 20500 | I21: =INDEX(SUPPLIERS!$D$3:$D$30,MATCH(C21,SUPPLIERS!$A$3:$A$30,0)) -> 0 | J21: =H21*(1-I21) -> 20500 | K21: 6.5 | L21: kW | M21: =IF(K21="","",J21/K21) -> 3153.8462 | N21: 10 | O21: 0.05 | P21: Est. (datasheet not received) | Q21: =MAX(N21/DRIVERS!$B$5,O21/DRIVERS!$B$6) -> 0.0035028372 | R21: =ROUNDDOWN(1/Q21,0) -> 285 | S21: =DRIVERS!$B$23*Q21/DRIVERS!$B$24 -> 18.182968 | T21: =J21*INDEX(DRIVERS!$C$32:$C$42,MATCH(B21,DRIVERS!$A$32:$A$42,0)) -> 0 | U21: =J21*INDEX(SUPPLIERS!$E$3:$E$30,MATCH(C21,SUPPLIERS!$A$3:$A$30,0)) -> 0 | V21: 0 | W21: =J21+S21+T21+U21+V21 -> 20518.183 | X21: =W21/J21-1 -> 0.00088697405 | Y21: =INDEX(DRIVERS!$B$32:$B$42,MATCH(B21,DRIVERS!$A$32:$A$42,0)) -> 0.1 | Z21: =W21*(1+Y21) -> 22570.001 | AA21: =W21*(1+Y21+DRIVERS!$B$26)*(1+DRIVERS!$B$27) -> 26427.42 | AB21: Sep 19, 2026 | AC21: 20500 | AD21: Off-grid type
A22: BC-INV-005 | B22: Inverter | C22: Blue Carbon | D22: 6.5 kW 48V hybrid off-grid inverter, parallel (H) | E22: BCT-FXC-6.5KW-P-H | F22: pc | G22: pc | H22: 22000 | I22: =INDEX(SUPPLIERS!$D$3:$D$30,MATCH(C22,SUPPLIERS!$A$3:$A$30,0)) -> 0 | J22: =H22*(1-I22) -> 22000 | K22: 6.5 | L22: kW | M22: =IF(K22="","",J22/K22) -> 3384.6154 | N22: 10 | O22: 0.05 | P22: Est. | Q22: =MAX(N22/DRIVERS!$B$5,O22/DRIVERS!$B$6) -> 0.0035028372 | R22: =ROUNDDOWN(1/Q22,0) -> 285 | S22: =DRIVERS!$B$23*Q22/DRIVERS!$B$24 -> 18.182968 | T22: =J22*INDEX(DRIVERS!$C$32:$C$42,MATCH(B22,DRIVERS!$A$32:$A$42,0)) -> 0 | U22: =J22*INDEX(SUPPLIERS!$E$3:$E$30,MATCH(C22,SUPPLIERS!$A$3:$A$30,0)) -> 0 | V22: 0 | W22: =J22+S22+T22+U22+V22 -> 22018.183 | X22: =W22/J22-1 -> 0.00082649854 | Y22: =INDEX(DRIVERS!$B$32:$B$42,MATCH(B22,DRIVERS!$A$32:$A$42,0)) -> 0.1 | Z22: =W22*(1+Y22) -> 24220.001 | AA22: =W22*(1+Y22+DRIVERS!$B$26)*(1+DRIVERS!$B$27) -> 28359.42 | AB22: Sep 19, 2026 | AC22: 22000 | AD22: Off-grid type
A23: BC-INV-006 | B23: Inverter | C23: Blue Carbon | D23: 8 kW hybrid inverter (on/off-grid) | E23: BCT-DLL-L1M3-8KW | F23: pc | G23: pc | H23: 63500 | I23: =INDEX(SUPPLIERS!$D$3:$D$30,MATCH(C23,SUPPLIERS!$A$3:$A$30,0)) -> 0 | J23: =H23*(1-I23) -> 63500 | K23: 8 | L23: kW | M23: =IF(K23="","",J23/K23) -> 7937.5 | N23: 35.6 | O23: 0.12 | P23: Est. (same cabinet as 10/12 kW assumed) | Q23: =MAX(N23/DRIVERS!$B$5,O23/DRIVERS!$B$6) -> 0.011866667 | R23: =ROUNDDOWN(1/Q23,0) -> 84 | S23: =DRIVERS!$B$23*Q23/DRIVERS!$B$24 -> 61.598986 | T23: =J23*INDEX(DRIVERS!$C$32:$C$42,MATCH(B23,DRIVERS!$A$32:$A$42,0)) -> 0 | U23: =J23*INDEX(SUPPLIERS!$E$3:$E$30,MATCH(C23,SUPPLIERS!$A$3:$A$30,0)) -> 0 | V23: 0 | W23: =J23+S23+T23+U23+V23 -> 63561.599 | X23: =W23/J23-1 -> 0.00097006278 | Y23: =INDEX(DRIVERS!$B$32:$B$42,MATCH(B23,DRIVERS!$A$32:$A$42,0)) -> 0.1 | Z23: =W23*(1+Y23) -> 69917.759 | AA23: =W23*(1+Y23+DRIVERS!$B$26)*(1+DRIVERS!$B$27) -> 81867.339 | AB23: Sep 19, 2026 | AC23: 65000
A24: BC-INV-007 | B24: Inverter | C24: Blue Carbon | D24: 10 kW hybrid inverter (on/off-grid) | E24: BCT-DLL-L1M3-10KW, 420x670x233 mm | F24: pc | G24: pc | H24: 79000 | I24: =INDEX(SUPPLIERS!$D$3:$D$30,MATCH(C24,SUPPLIERS!$A$3:$A$30,0)) -> 0 | J24: =H24*(1-I24) -> 79000 | K24: 10 | L24: kW | M24: =IF(K24="","",J24/K24) -> 7900 | N24: 35.6 | O24: 0.12 | P24: Weight: datasheet; volume Est. | Q24: =MAX(N24/DRIVERS!$B$5,O24/DRIVERS!$B$6) -> 0.011866667 | R24: =ROUNDDOWN(1/Q24,0) -> 84 | S24: =DRIVERS!$B$23*Q24/DRIVERS!$B$24 -> 61.598986 | T24: =J24*INDEX(DRIVERS!$C$32:$C$42,MATCH(B24,DRIVERS!$A$32:$A$42,0)) -> 0 | U24: =J24*INDEX(SUPPLIERS!$E$3:$E$30,MATCH(C24,SUPPLIERS!$A$3:$A$30,0)) -> 0 | V24: 0 | W24: =J24+S24+T24+U24+V24 -> 79061.599 | X24: =W24/J24-1 -> 0.00077973401 | Y24: =INDEX(DRIVERS!$B$32:$B$42,MATCH(B24,DRIVERS!$A$32:$A$42,0)) -> 0.1 | Z24: =W24*(1+Y24) -> 86967.759 | AA24: =W24*(1+Y24+DRIVERS!$B$26)*(1+DRIVERS!$B$27) -> 101831.34 | AB24: Sep 19, 2026 | AC24: 90000 | AD24: 3 MPPT at 26A each; battery 220A; 16 units parallel; 5-yr warranty
A25: BC-INV-008 | B25: Inverter | C25: Blue Carbon | D25: 12 kW hybrid inverter (on/off-grid) | E25: BCT-DLL-L1M3-12KW, 420x670x233 mm | F25: pc | G25: pc | H25: 89000 | I25: =INDEX(SUPPLIERS!$D$3:$D$30,MATCH(C25,SUPPLIERS!$A$3:$A$30,0)) -> 0 | J25: =H25*(1-I25) -> 89000 | K25: 12 | L25: kW | M25: =IF(K25="","",J25/K25) -> 7416.6667 | N25: 35.6 | O25: 0.12 | P25: Weight: datasheet; volume Est. | Q25: =MAX(N25/DRIVERS!$B$5,O25/DRIVERS!$B$6) -> 0.011866667 | R25: =ROUNDDOWN(1/Q25,0) -> 84 | S25: =DRIVERS!$B$23*Q25/DRIVERS!$B$24 -> 61.598986 | T25: =J25*INDEX(DRIVERS!$C$32:$C$42,MATCH(B25,DRIVERS!$A$32:$A$42,0)) -> 0 | U25: =J25*INDEX(SUPPLIERS!$E$3:$E$30,MATCH(C25,SUPPLIERS!$A$3:$A$30,0)) -> 0 | V25: 0 | W25: =J25+S25+T25+U25+V25 -> 89061.599 | X25: =W25/J25-1 -> 0.00069212344 | Y25: =INDEX(DRIVERS!$B$32:$B$42,MATCH(B25,DRIVERS!$A$32:$A$42,0)) -> 0.1 | Z25: =W25*(1+Y25) -> 97967.759 | AA25: =W25*(1+Y25+DRIVERS!$B$26)*(1+DRIVERS!$B$27) -> 114711.34 | AB25: Sep 19, 2026 | AC25: 95000 | AD25: 3 MPPT at 26A each; battery 250A; 5-yr warranty
A26: FS-INV-001 | B26: Inverter | C26: Felicity Solar | D26: 6 kW low-voltage hybrid inverter (grid-tie + backup) | E26: IVGM6KLP1G2, 470x376x251 mm | F26: pc | G26: pc | H26: 43000 | I26: =INDEX(SUPPLIERS!$D$3:$D$30,MATCH(C26,SUPPLIERS!$A$3:$A$30,0)) -> 0 | J26: =H26*(1-I26) -> 43000 | K26: 6 | L26: kW | M26: =IF(K26="","",J26/K26) -> 7166.6667 | N26: 24.5 | O26: 0.09448 | P26: Brochure: gross weight, package | Q26: =MAX(N26/DRIVERS!$B$5,O26/DRIVERS!$B$6) -> 0.0081666667 | R26: =ROUNDDOWN(1/Q26,0) -> 122 | S26: =DRIVERS!$B$23*Q26/DRIVERS!$B$24 -> 42.392561 | T26: =J26*INDEX(DRIVERS!$C$32:$C$42,MATCH(B26,DRIVERS!$A$32:$A$42,0)) -> 0 | U26: =J26*INDEX(SUPPLIERS!$E$3:$E$30,MATCH(C26,SUPPLIERS!$A$3:$A$30,0)) -> 0 | V26: 0 | W26: =J26+S26+T26+U26+V26 -> 43042.393 | X26: =W26/J26-1 -> 0.00098587351 | Y26: =INDEX(DRIVERS!$B$32:$B$42,MATCH(B26,DRIVERS!$A$32:$A$42,0)) -> 0.1 | Z26: =W26*(1+Y26) -> 47346.632 | AA26: =W26*(1+Y26+DRIVERS!$B$26)*(1+DRIVERS!$B$27) -> 55438.602 | AB26: September 2026 | AD26: 2 MPPT, 18A each (27A short-circuit); battery 135A; IEC 61727 / 62116 listed; 10-yr warranty. Same price as the 6 kW inverter in the packages
A27: FS-INV-002 | B27: Inverter | C27: Felicity Solar | D27: 8 kW low-voltage hybrid inverter (grid-tie + backup) | E27: IVGM8KLP1G1, 430x654x243 mm | F27: pc | G27: pc | H27: 63000 | I27: =INDEX(SUPPLIERS!$D$3:$D$30,MATCH(C27,SUPPLIERS!$A$3:$A$30,0)) -> 0 | J27: =H27*(1-I27) -> 63000 | K27: 8 | L27: kW | M27: =IF(K27="","",J27/K27) -> 7875 | N27: 40.5 | O27: 0.15412 | P27: Brochure: gross weight, package | Q27: =MAX(N27/DRIVERS!$B$5,O27/DRIVERS!$B$6) -> 0.0135 | R27: =ROUNDDOWN(1/Q27,0) -> 74 | S27: =DRIVERS!$B$23*Q27/DRIVERS!$B$24 -> 70.077499 | T27: =J27*INDEX(DRIVERS!$C$32:$C$42,MATCH(B27,DRIVERS!$A$32:$A$42,0)) -> 0 | U27: =J27*INDEX(SUPPLIERS!$E$3:$E$30,MATCH(C27,SUPPLIERS!$A$3:$A$30,0)) -> 0 | V27: 0 | W27: =J27+S27+T27+U27+V27 -> 63070.077 | X27: =W27/J27-1 -> 0.0011123412 | Y27: =INDEX(DRIVERS!$B$32:$B$42,MATCH(B27,DRIVERS!$A$32:$A$42,0)) -> 0.1 | Z27: =W27*(1+Y27) -> 69377.085 | AA27: =W27*(1+Y27+DRIVERS!$B$26)*(1+DRIVERS!$B$27) -> 81234.26 | AB27: September 2026 | AD27: 2 MPPT, 26A each; battery 190A; 10-yr warranty. CHECK: grid certifications marked "in progress" and IEC 61727 / 62116 not listed - confirm before a net-metered job
A28: FS-INV-003 | B28: Inverter | C28: Felicity Solar | D28: 12 kW low-voltage hybrid inverter (grid-tie + backup) | E28: IVGM16KLP1G1 | F28: pc | G28: pc | H28: 102000 | I28: =INDEX(SUPPLIERS!$D$3:$D$30,MATCH(C28,SUPPLIERS!$A$3:$A$30,0)) -> 0 | J28: =H28*(1-I28) -> 102000 | K28: 12 | L28: kW | M28: =IF(K28="","",J28/K28) -> 8500 | N28: 40.5 | O28: 0.154 | P28: Est. (no spec in brochure; 8 kW used) | Q28: =MAX(N28/DRIVERS!$B$5,O28/DRIVERS!$B$6) -> 0.0135 | R28: =ROUNDDOWN(1/Q28,0) -> 74 | S28: =DRIVERS!$B$23*Q28/DRIVERS!$B$24 -> 70.077499 | T28: =J28*INDEX(DRIVERS!$C$32:$C$42,MATCH(B28,DRIVERS!$A$32:$A$42,0)) -> 0 | U28: =J28*INDEX(SUPPLIERS!$E$3:$E$30,MATCH(C28,SUPPLIERS!$A$3:$A$30,0)) -> 0 | V28: 0 | W28: =J28+S28+T28+U28+V28 -> 102070.08 | X28: =W28/J28-1 -> 0.0006870343 | Y28: =INDEX(DRIVERS!$B$32:$B$42,MATCH(B28,DRIVERS!$A$32:$A$42,0)) -> 0.1 | Z28: =W28*(1+Y28) -> 112277.09 | AA28: =W28*(1+Y28+DRIVERS!$B$26)*(1+DRIVERS!$B$27) -> 131466.26 | AB28: September 2026 | AD28: CHECK: model code says 16K, price list says 12 kW. No spec sheet received. 10-yr warranty
A29: FS-INV-004 | B29: Inverter | C29: Felicity Solar | D29: 50 kW high-voltage hybrid inverter, 3-phase | E29: IVGM50KHP3G1, 940x582x340 mm | F29: pc | G29: pc | H29: 216000 | I29: =INDEX(SUPPLIERS!$D$3:$D$30,MATCH(C29,SUPPLIERS!$A$3:$A$30,0)) -> 0 | J29: =H29*(1-I29) -> 216000 | K29: 50 | L29: kW | M29: =IF(K29="","",J29/K29) -> 4320 | N29: 107.1 | O29: 0.40439 | P29: Brochure: gross weight, package | Q29: =MAX(N29/DRIVERS!$B$5,O29/DRIVERS!$B$6) -> 0.0357 | R29: =ROUNDDOWN(1/Q29,0) -> 28 | S29: =DRIVERS!$B$23*Q29/DRIVERS!$B$24 -> 185.31605 | T29: =J29*INDEX(DRIVERS!$C$32:$C$42,MATCH(B29,DRIVERS!$A$32:$A$42,0)) -> 0 | U29: =J29*INDEX(SUPPLIERS!$E$3:$E$30,MATCH(C29,SUPPLIERS!$A$3:$A$30,0)) -> 0 | V29: 0 | W29: =J29+S29+T29+U29+V29 -> 216185.32 | X29: =W29/J29-1 -> 0.00085794469 | Y29: =INDEX(DRIVERS!$B$32:$B$42,MATCH(B29,DRIVERS!$A$32:$A$42,0)) -> 0.1 | Z29: =W29*(1+Y29) -> 237803.85 | AA29: =W29*(1+Y29+DRIVERS!$B$26)*(1+DRIVERS!$B$27) -> 278446.69 | AB29: September 2026 | AD29: Commercial, 3-phase, high-voltage battery. 10-yr warranty
A30: FS-INV-005 | B30: Inverter | C30: Felicity Solar | D30: 6 kW low-voltage off-grid inverter | E30: IVEM6048-II, 420x335x142 mm | F30: pc | G30: pc | H30: 19000 | I30: =INDEX(SUPPLIERS!$D$3:$D$30,MATCH(C30,SUPPLIERS!$A$3:$A$30,0)) -> 0 | J30: =H30*(1-I30) -> 19000 | K30: 6 | L30: kW | M30: =IF(K30="","",J30/K30) -> 3166.6667 | N30: 14.5 | O30: 0.04612 | P30: Brochure: package; gross weight Est. (net 12.5 kg) | Q30: =MAX(N30/DRIVERS!$B$5,O30/DRIVERS!$B$6) -> 0.0048333333 | R30: =ROUNDDOWN(1/Q30,0) -> 206 | S30: =DRIVERS!$B$23*Q30/DRIVERS!$B$24 -> 25.089475 | T30: =J30*INDEX(DRIVERS!$C$32:$C$42,MATCH(B30,DRIVERS!$A$32:$A$42,0)) -> 0 | U30: =J30*INDEX(SUPPLIERS!$E$3:$E$30,MATCH(C30,SUPPLIERS!$A$3:$A$30,0)) -> 0 | V30: 0 | W30: =J30+S30+T30+U30+V30 -> 19025.089 | X30: =W30/J30-1 -> 0.0013204987 | Y30: =INDEX(DRIVERS!$B$32:$B$42,MATCH(B30,DRIVERS!$A$32:$A$42,0)) -> 0.1 | Z30: =W30*(1+Y30) -> 20927.598 | AA30: =W30*(1+Y30+DRIVERS!$B$26)*(1+DRIVERS!$B$27) -> 24504.315 | AB30: September 2026 | AD30: Off-grid type, 1 MPPT 27A, 500 Voc. 2-yr warranty
A31: FS-INV-006 | B31: Inverter | C31: Felicity Solar | D31: 8 kW low-voltage off-grid inverter | E31: IVEM8048-II, 607x464x141 mm | F31: pc | G31: pc | H31: 32000 | I31: =INDEX(SUPPLIERS!$D$3:$D$30,MATCH(C31,SUPPLIERS!$A$3:$A$30,0)) -> 0 | J31: =H31*(1-I31) -> 32000 | K31: 8 | L31: kW | M31: =IF(K31="","",J31/K31) -> 4000 | N31: 26 | O31: 0.10733 | P31: Brochure: package; gross weight Est. (net 23.7 kg) | Q31: =MAX(N31/DRIVERS!$B$5,O31/DRIVERS!$B$6) -> 0.0086666667 | R31: =ROUNDDOWN(1/Q31,0) -> 115 | S31: =DRIVERS!$B$23*Q31/DRIVERS!$B$24 -> 44.988024 | T31: =J31*INDEX(DRIVERS!$C$32:$C$42,MATCH(B31,DRIVERS!$A$32:$A$42,0)) -> 0 | U31: =J31*INDEX(SUPPLIERS!$E$3:$E$30,MATCH(C31,SUPPLIERS!$A$3:$A$30,0)) -> 0 | V31: 0 | W31: =J31+S31+T31+U31+V31 -> 32044.988 | X31: =W31/J31-1 -> 0.0014058757 | Y31: =INDEX(DRIVERS!$B$32:$B$42,MATCH(B31,DRIVERS!$A$32:$A$42,0)) -> 0.1 | Z31: =W31*(1+Y31) -> 35249.487 | AA31: =W31*(1+Y31+DRIVERS!$B$26)*(1+DRIVERS!$B$27) -> 41273.945 | AB31: September 2026 | AD31: Off-grid type, 2 x 20A PV. 2-yr warranty
A32: FS-INV-007 | B32: Inverter | C32: Felicity Solar | D32: 12 kW low-voltage off-grid inverter | E32: IVEM12048(-II), 634x476x141 mm | F32: pc | G32: pc | H32: 39000 | I32: =INDEX(SUPPLIERS!$D$3:$D$30,MATCH(C32,SUPPLIERS!$A$3:$A$30,0)) -> 0 | J32: =H32*(1-I32) -> 39000 | K32: 12 | L32: kW | M32: =IF(K32="","",J32/K32) -> 3250 | N32: 29.5 | O32: 0.11126 | P32: Brochure: package; gross weight Est. (net 26.8 kg) | Q32: =MAX(N32/DRIVERS!$B$5,O32/DRIVERS!$B$6) -> 0.0098333333 | R32: =ROUNDDOWN(1/Q32,0) -> 101 | S32: =DRIVERS!$B$23*Q32/DRIVERS!$B$24 -> 51.044104 | T32: =J32*INDEX(DRIVERS!$C$32:$C$42,MATCH(B32,DRIVERS!$A$32:$A$42,0)) -> 0 | U32: =J32*INDEX(SUPPLIERS!$E$3:$E$30,MATCH(C32,SUPPLIERS!$A$3:$A$30,0)) -> 0 | V32: 0 | W32: =J32+S32+T32+U32+V32 -> 39051.044 | X32: =W32/J32-1 -> 0.0013088232 | Y32: =INDEX(DRIVERS!$B$32:$B$42,MATCH(B32,DRIVERS!$A$32:$A$42,0)) -> 0.1 | Z32: =W32*(1+Y32) -> 42956.149 | AA32: =W32*(1+Y32+DRIVERS!$B$26)*(1+DRIVERS!$B$27) -> 50297.745 | AB32: September 2026 | AD32: Off-grid type, 2 x 27A PV. 2-yr warranty. Price list says IVEM12048, brochure IVEM12048-II
A33: FS-INV-008 | B33: Inverter | C33: Felicity Solar | D33: 6 kW low-voltage eco-hybrid inverter | E33: IVAM6048P1G1, 435x320x183 mm | F33: pc | G33: pc | H33: 25000 | I33: =INDEX(SUPPLIERS!$D$3:$D$30,MATCH(C33,SUPPLIERS!$A$3:$A$30,0)) -> 0 | J33: =H33*(1-I33) -> 25000 | K33: 6 | L33: kW | M33: =IF(K33="","",J33/K33) -> 4166.6667 | N33: 15.5 | O33: 0.05918 | P33: Brochure: package; gross weight Est. (net 13.5 kg) | Q33: =MAX(N33/DRIVERS!$B$5,O33/DRIVERS!$B$6) -> 0.0051666667 | R33: =ROUNDDOWN(1/Q33,0) -> 193 | S33: =DRIVERS!$B$23*Q33/DRIVERS!$B$24 -> 26.819783 | T33: =J33*INDEX(DRIVERS!$C$32:$C$42,MATCH(B33,DRIVERS!$A$32:$A$42,0)) -> 0 | U33: =J33*INDEX(SUPPLIERS!$E$3:$E$30,MATCH(C33,SUPPLIERS!$A$3:$A$30,0)) -> 0 | V33: 0 | W33: =J33+S33+T33+U33+V33 -> 25026.82 | X33: =W33/J33-1 -> 0.0010727913 | Y33: =INDEX(DRIVERS!$B$32:$B$42,MATCH(B33,DRIVERS!$A$32:$A$42,0)) -> 0.1 | Z33: =W33*(1+Y33) -> 27529.502 | AA33: =W33*(1+Y33+DRIVERS!$B$26)*(1+DRIVERS!$B$27) -> 32234.544 | AB33: September 2026 | AD33: Off-grid high-frequency type, 2 MPPT 20A each, battery 135A. Brochure: pilot production, specs may change. 5-yr warranty
A34: IAN-INV-001 | B34: Inverter | C34: IAN Solar | D34: SOLIS S6-GR1P6K GRID-TIE 6kW | E34: Solis; 6 kW; Grid-tie 1P; -S = Bluetooth version | F34: pc | G34: pc | H34: 25600 | I34: =INDEX(SUPPLIERS!$D$3:$D$30,MATCH(C34,SUPPLIERS!$A$3:$A$30,0)) -> 0 | J34: =H34*(1-I34) -> 25600 | K34: 6 | L34: kW | M34: =IF(K34="","",J34/K34) -> 4266.6667 | N34: 15 | O34: 0.06929 | P34: List: gross weight, packaging size | Q34: =MAX(N34/DRIVERS!$B$5,O34/DRIVERS!$B$6) -> 0.005 | R34: =ROUNDDOWN(1/Q34,0) -> 200 | S34: =DRIVERS!$B$23*Q34/DRIVERS!$B$24 -> 25.954629 | T34: =J34*INDEX(DRIVERS!$C$32:$C$42,MATCH(B34,DRIVERS!$A$32:$A$42,0)) -> 0 | U34: =J34*INDEX(SUPPLIERS!$E$3:$E$30,MATCH(C34,SUPPLIERS!$A$3:$A$30,0)) -> 0 | V34: 0 | W34: =J34+S34+T34+U34+V34 -> 25625.955 | X34: =W34/J34-1 -> 0.0010138527 | Y34: =INDEX(DRIVERS!$B$32:$B$42,MATCH(B34,DRIVERS!$A$32:$A$42,0)) -> 0.1 | Z34: =W34*(1+Y34) -> 28188.55 | AA34: =W34*(1+Y34+DRIVERS!$B$26)*(1+DRIVERS!$B$27) -> 33006.23 | AB34: Sep 3, 2026
A35: IAN-INV-002 | B35: Inverter | C35: IAN Solar | D35: SOLIS S6-GR1P10K03-NV-ND GRID-TIE 10kW | E35: Solis; 10 kW; Grid-tie 1P | F35: pc | G35: pc | H35: 47000 | I35: =INDEX(SUPPLIERS!$D$3:$D$30,MATCH(C35,SUPPLIERS!$A$3:$A$30,0)) -> 0 | J35: =H35*(1-I35) -> 47000 | K35: 10 | L35: kW | M35: =IF(K35="","",J35/K35) -> 4700 | N35: 21.5 | O35: 0.08463 | P35: List: gross weight, packaging size | Q35: =MAX(N35/DRIVERS!$B$5,O35/DRIVERS!$B$6) -> 0.0071666667 | R35: =ROUNDDOWN(1/Q35,0) -> 139 | S35: =DRIVERS!$B$23*Q35/DRIVERS!$B$24 -> 37.201635 | T35: =J35*INDEX(DRIVERS!$C$32:$C$42,MATCH(B35,DRIVERS!$A$32:$A$42,0)) -> 0 | U35: =J35*INDEX(SUPPLIERS!$E$3:$E$30,MATCH(C35,SUPPLIERS!$A$3:$A$30,0)) -> 0 | V35: 0 | W35: =J35+S35+T35+U35+V35 -> 47037.202 | X35: =W35/J35-1 -> 0.00079152415 | Y35: =INDEX(DRIVERS!$B$32:$B$42,MATCH(B35,DRIVERS!$A$32:$A$42,0)) -> 0.1 | Z35: =W35*(1+Y35) -> 51740.922 | AA35: =W35*(1+Y35+DRIVERS!$B$26)*(1+DRIVERS!$B$27) -> 60583.916 | AB35: Sep 3, 2026
A36: IAN-INV-003 | B36: Inverter | C36: IAN Solar | D36: SOLIS S5-GR1P8K GRID-TIE 8kW | E36: Solis; 8 kW; Grid-tie 1P | F36: pc | G36: pc | H36: 40000 | I36: =INDEX(SUPPLIERS!$D$3:$D$30,MATCH(C36,SUPPLIERS!$A$3:$A$30,0)) -> 0 | J36: =H36*(1-I36) -> 40000 | K36: 8 | L36: kW | M36: =IF(K36="","",J36/K36) -> 5000 | N36: 21.5 | O36: 0.10234 | P36: List: gross weight, packaging size | Q36: =MAX(N36/DRIVERS!$B$5,O36/DRIVERS!$B$6) -> 0.0071696071 | R36: =ROUNDDOWN(1/Q36,0) -> 139 | S36: =DRIVERS!$B$23*Q36/DRIVERS!$B$24 -> 37.216899 | T36: =J36*INDEX(DRIVERS!$C$32:$C$42,MATCH(B36,DRIVERS!$A$32:$A$42,0)) -> 0 | U36: =J36*INDEX(SUPPLIERS!$E$3:$E$30,MATCH(C36,SUPPLIERS!$A$3:$A$30,0)) -> 0 | V36: 0 | W36: =J36+S36+T36+U36+V36 -> 40037.217 | X36: =W36/J36-1 -> 0.00093042247 | Y36: =INDEX(DRIVERS!$B$32:$B$42,MATCH(B36,DRIVERS!$A$32:$A$42,0)) -> 0.1 | Z36: =W36*(1+Y36) -> 44040.939 | AA36: =W36*(1+Y36+DRIVERS!$B$26)*(1+DRIVERS!$B$27) -> 51567.935 | AB36: Sep 3, 2026
A37: IAN-INV-004 | B37: Inverter | C37: IAN Solar | D37: SOLIS S6-GR1P5K GRID-TIE 5kW | E37: Solis; 5 kW; Grid-tie 1P | F37: pc | G37: pc | H37: 25600 | I37: =INDEX(SUPPLIERS!$D$3:$D$30,MATCH(C37,SUPPLIERS!$A$3:$A$30,0)) -> 0 | J37: =H37*(1-I37) -> 25600 | K37: 5 | L37: kW | M37: =IF(K37="","",J37/K37) -> 5120 | N37: 15 | O37: 0.06145 | P37: List: gross weight, packaging size | Q37: =MAX(N37/DRIVERS!$B$5,O37/DRIVERS!$B$6) -> 0.005 | R37: =ROUNDDOWN(1/Q37,0) -> 200 | S37: =DRIVERS!$B$23*Q37/DRIVERS!$B$24 -> 25.954629 | T37: =J37*INDEX(DRIVERS!$C$32:$C$42,MATCH(B37,DRIVERS!$A$32:$A$42,0)) -> 0 | U37: =J37*INDEX(SUPPLIERS!$E$3:$E$30,MATCH(C37,SUPPLIERS!$A$3:$A$30,0)) -> 0 | V37: 0 | W37: =J37+S37+T37+U37+V37 -> 25625.955 | X37: =W37/J37-1 -> 0.0010138527 | Y37: =INDEX(DRIVERS!$B$32:$B$42,MATCH(B37,DRIVERS!$A$32:$A$42,0)) -> 0.1 | Z37: =W37*(1+Y37) -> 28188.55 | AA37: =W37*(1+Y37+DRIVERS!$B$26)*(1+DRIVERS!$B$27) -> 33006.23 | AB37: Sep 3, 2026
A38: IAN-INV-005 | B38: Inverter | C38: IAN Solar | D38: SOLIS S6-GR1P3K GRID-TIE 3kW | E38: Solis; 3 kW; Grid-tie 1P | F38: pc | G38: pc | H38: 22000 | I38: =INDEX(SUPPLIERS!$D$3:$D$30,MATCH(C38,SUPPLIERS!$A$3:$A$30,0)) -> 0 | J38: =H38*(1-I38) -> 22000 | K38: 3 | L38: kW | M38: =IF(K38="","",J38/K38) -> 7333.3333 | N38: 9 | O38: 0.05383 | P38: List: gross weight, packaging size | Q38: =MAX(N38/DRIVERS!$B$5,O38/DRIVERS!$B$6) -> 0.0037711545 | R38: =ROUNDDOWN(1/Q38,0) -> 265 | S38: =DRIVERS!$B$23*Q38/DRIVERS!$B$24 -> 19.575783 | T38: =J38*INDEX(DRIVERS!$C$32:$C$42,MATCH(B38,DRIVERS!$A$32:$A$42,0)) -> 0 | U38: =J38*INDEX(SUPPLIERS!$E$3:$E$30,MATCH(C38,SUPPLIERS!$A$3:$A$30,0)) -> 0 | V38: 0 | W38: =J38+S38+T38+U38+V38 -> 22019.576 | X38: =W38/J38-1 -> 0.00088980833 | Y38: =INDEX(DRIVERS!$B$32:$B$42,MATCH(B38,DRIVERS!$A$32:$A$42,0)) -> 0.1 | Z38: =W38*(1+Y38) -> 24221.533 | AA38: =W38*(1+Y38+DRIVERS!$B$26)*(1+DRIVERS!$B$27) -> 28361.214 | AB38: Sep 3, 2026
A39: IAN-INV-006 | B39: Inverter | C39: IAN Solar | D39: SOLIS S6-GC3P200K07-ND GRID-TIE 200kW 480V | E39: Solis; 200 kW; 480V | F39: pc | G39: pc | H39: 290000 | I39: =INDEX(SUPPLIERS!$D$3:$D$30,MATCH(C39,SUPPLIERS!$A$3:$A$30,0)) -> 0 | J39: =H39*(1-I39) -> 290000 | K39: 200 | L39: kW | M39: =IF(K39="","",J39/K39) -> 1450 | N39: 120 | O39: 0.69575 | P39: List: gross weight, packaging size | Q39: =MAX(N39/DRIVERS!$B$5,O39/DRIVERS!$B$6) -> 0.048741979 | R39: =ROUNDDOWN(1/Q39,0) -> 20 | S39: =DRIVERS!$B$23*Q39/DRIVERS!$B$24 -> 253.016 | T39: =J39*INDEX(DRIVERS!$C$32:$C$42,MATCH(B39,DRIVERS!$A$32:$A$42,0)) -> 0 | U39: =J39*INDEX(SUPPLIERS!$E$3:$E$30,MATCH(C39,SUPPLIERS!$A$3:$A$30,0)) -> 0 | V39: 0 | W39: =J39+S39+T39+U39+V39 -> 290253.02 | X39: =W39/J39-1 -> 0.00087246896 | Y39: =INDEX(DRIVERS!$B$32:$B$42,MATCH(B39,DRIVERS!$A$32:$A$42,0)) -> 0.1 | Z39: =W39*(1+Y39) -> 319278.32 | AA39: =W39*(1+Y39+DRIVERS!$B$26)*(1+DRIVERS!$B$27) -> 373845.88 | AB39: Sep 3, 2026
A40: IAN-INV-007 | B40: Inverter | C40: IAN Solar | D40: SOLIS S6-GC3P150K07-NV GRID-TIE 3P 150kW 380-400V | E40: Solis; 150 kW; 380-400V | F40: pc | G40: pc | H40: 250000 | I40: =INDEX(SUPPLIERS!$D$3:$D$30,MATCH(C40,SUPPLIERS!$A$3:$A$30,0)) -> 0 | J40: =H40*(1-I40) -> 250000 | K40: 150 | L40: kW | M40: =IF(K40="","",J40/K40) -> 1666.6667 | N40: 120 | O40: 0.598 | P40: List: gross weight, packaging size | Q40: =MAX(N40/DRIVERS!$B$5,O40/DRIVERS!$B$6) -> 0.041893933 | R40: =ROUNDDOWN(1/Q40,0) -> 23 | S40: =DRIVERS!$B$23*Q40/DRIVERS!$B$24 -> 217.4683 | T40: =J40*INDEX(DRIVERS!$C$32:$C$42,MATCH(B40,DRIVERS!$A$32:$A$42,0)) -> 0 | U40: =J40*INDEX(SUPPLIERS!$E$3:$E$30,MATCH(C40,SUPPLIERS!$A$3:$A$30,0)) -> 0 | V40: 0 | W40: =J40+S40+T40+U40+V40 -> 250217.47 | X40: =W40/J40-1 -> 0.00086987319 | Y40: =INDEX(DRIVERS!$B$32:$B$42,MATCH(B40,DRIVERS!$A$32:$A$42,0)) -> 0.1 | Z40: =W40*(1+Y40) -> 275239.22 | AA40: =W40*(1+Y40+DRIVERS!$B$26)*(1+DRIVERS!$B$27) -> 322280.1 | AB40: Sep 3, 2026
A41: IAN-INV-008 | B41: Inverter | C41: IAN Solar | D41: SOLIS-110K-5G-PRO GRID-TIE 3P 110kW 380-400V | E41: Solis; 110 kW; 380-400V | F41: pc | G41: pc | H41: 217000 | I41: =INDEX(SUPPLIERS!$D$3:$D$30,MATCH(C41,SUPPLIERS!$A$3:$A$30,0)) -> 0 | J41: =H41*(1-I41) -> 217000 | K41: 110 | L41: kW | M41: =IF(K41="","",J41/K41) -> 1972.7273 | N41: 100 | O41: 0.288 | P41: List: gross weight, packaging size | Q41: =MAX(N41/DRIVERS!$B$5,O41/DRIVERS!$B$6) -> 0.033333333 | R41: =ROUNDDOWN(1/Q41,0) -> 30 | S41: =DRIVERS!$B$23*Q41/DRIVERS!$B$24 -> 173.03086 | T41: =J41*INDEX(DRIVERS!$C$32:$C$42,MATCH(B41,DRIVERS!$A$32:$A$42,0)) -> 0 | U41: =J41*INDEX(SUPPLIERS!$E$3:$E$30,MATCH(C41,SUPPLIERS!$A$3:$A$30,0)) -> 0 | V41: 0 | W41: =J41+S41+T41+U41+V41 -> 217173.03 | X41: =W41/J41-1 -> 0.00079737724 | Y41: =INDEX(DRIVERS!$B$32:$B$42,MATCH(B41,DRIVERS!$A$32:$A$42,0)) -> 0.1 | Z41: =W41*(1+Y41) -> 238890.33 | AA41: =W41*(1+Y41+DRIVERS!$B$26)*(1+DRIVERS!$B$27) -> 279718.86 | AB41: Sep 3, 2026
A42: IAN-INV-009 | B42: Inverter | C42: IAN Solar | D42: SOLIS S5-GC125K-HV GRID-TIE 125kW 440-480V | E42: Solis; 125 kW; 440-480V | F42: pc | G42: pc | H42: 253000 | I42: =INDEX(SUPPLIERS!$D$3:$D$30,MATCH(C42,SUPPLIERS!$A$3:$A$30,0)) -> 0 | J42: =H42*(1-I42) -> 253000 | K42: 125 | L42: kW | M42: =IF(K42="","",J42/K42) -> 2024 | N42: 118 | O42: 0.432 | P42: List: gross weight, packaging size | Q42: =MAX(N42/DRIVERS!$B$5,O42/DRIVERS!$B$6) -> 0.039333333 | R42: =ROUNDDOWN(1/Q42,0) -> 25 | S42: =DRIVERS!$B$23*Q42/DRIVERS!$B$24 -> 204.17642 | T42: =J42*INDEX(DRIVERS!$C$32:$C$42,MATCH(B42,DRIVERS!$A$32:$A$42,0)) -> 0 | U42: =J42*INDEX(SUPPLIERS!$E$3:$E$30,MATCH(C42,SUPPLIERS!$A$3:$A$30,0)) -> 0 | V42: 0 | W42: =J42+S42+T42+U42+V42 -> 253204.18 | X42: =W42/J42-1 -> 0.00080702141 | Y42: =INDEX(DRIVERS!$B$32:$B$42,MATCH(B42,DRIVERS!$A$32:$A$42,0)) -> 0.1 | Z42: =W42*(1+Y42) -> 278524.59 | AA42: =W42*(1+Y42+DRIVERS!$B$26)*(1+DRIVERS!$B$27) -> 326126.98 | AB42: Sep 3, 2026
A43: IAN-INV-010 | B43: Inverter | C43: IAN Solar | D43: SOLIS S5-GC100K-HV GRID-TIE 100kW 440-480V | E43: Solis; 100 kW; 440-480V | F43: pc | G43: pc | H43: 229000 | I43: =INDEX(SUPPLIERS!$D$3:$D$30,MATCH(C43,SUPPLIERS!$A$3:$A$30,0)) -> 0 | J43: =H43*(1-I43) -> 229000 | K43: 100 | L43: kW | M43: =IF(K43="","",J43/K43) -> 2290 | N43: 100 | O43: 0.45 | P43: List: gross weight, packaging size | Q43: =MAX(N43/DRIVERS!$B$5,O43/DRIVERS!$B$6) -> 0.033333333 | R43: =ROUNDDOWN(1/Q43,0) -> 30 | S43: =DRIVERS!$B$23*Q43/DRIVERS!$B$24 -> 173.03086 | T43: =J43*INDEX(DRIVERS!$C$32:$C$42,MATCH(B43,DRIVERS!$A$32:$A$42,0)) -> 0 | U43: =J43*INDEX(SUPPLIERS!$E$3:$E$30,MATCH(C43,SUPPLIERS!$A$3:$A$30,0)) -> 0 | V43: 0 | W43: =J43+S43+T43+U43+V43 -> 229173.03 | X43: =W43/J43-1 -> 0.00075559328 | Y43: =INDEX(DRIVERS!$B$32:$B$42,MATCH(B43,DRIVERS!$A$32:$A$42,0)) -> 0.1 | Z43: =W43*(1+Y43) -> 252090.33 | AA43: =W43*(1+Y43+DRIVERS!$B$26)*(1+DRIVERS!$B$27) -> 295174.86 | AB43: Sep 3, 2026
A44: IAN-INV-011 | B44: Inverter | C44: IAN Solar | D44: SOLIS S5-GC60K-HV GRID-TIE 60kW 440-480V | E44: Solis; 60 kW; 440-480V | F44: pc | G44: pc | H44: 149000 | I44: =INDEX(SUPPLIERS!$D$3:$D$30,MATCH(C44,SUPPLIERS!$A$3:$A$30,0)) -> 0 | J44: =H44*(1-I44) -> 149000 | K44: 60 | L44: kW | M44: =IF(K44="","",J44/K44) -> 2483.3333 | N44: 63 | O44: 0.2448 | P44: List: gross weight, packaging size | Q44: =MAX(N44/DRIVERS!$B$5,O44/DRIVERS!$B$6) -> 0.021 | R44: =ROUNDDOWN(1/Q44,0) -> 47 | S44: =DRIVERS!$B$23*Q44/DRIVERS!$B$24 -> 109.00944 | T44: =J44*INDEX(DRIVERS!$C$32:$C$42,MATCH(B44,DRIVERS!$A$32:$A$42,0)) -> 0 | U44: =J44*INDEX(SUPPLIERS!$E$3:$E$30,MATCH(C44,SUPPLIERS!$A$3:$A$30,0)) -> 0 | V44: 0 | W44: =J44+S44+T44+U44+V44 -> 149109.01 | X44: =W44/J44-1 -> 0.000731607 | Y44: =INDEX(DRIVERS!$B$32:$B$42,MATCH(B44,DRIVERS!$A$32:$A$42,0)) -> 0.1 | Z44: =W44*(1+Y44) -> 164019.91 | AA44: =W44*(1+Y44+DRIVERS!$B$26)*(1+DRIVERS!$B$27) -> 192052.4 | AB44: Sep 3, 2026
A45: IAN-INV-012 | B45: Inverter | C45: IAN Solar | D45: SOLIS S5-GC50K-HV GRID-TIE 50kW 440-480V | E45: Solis; 50 kW; 440-480V | F45: pc | G45: pc | H45: 138000 | I45: =INDEX(SUPPLIERS!$D$3:$D$30,MATCH(C45,SUPPLIERS!$A$3:$A$30,0)) -> 0 | J45: =H45*(1-I45) -> 138000 | K45: 50 | L45: kW | M45: =IF(K45="","",J45/K45) -> 2760 | N45: 48 | O45: 0.1971 | P45: List: gross weight, packaging size | Q45: =MAX(N45/DRIVERS!$B$5,O45/DRIVERS!$B$6) -> 0.016 | R45: =ROUNDDOWN(1/Q45,0) -> 62 | S45: =DRIVERS!$B$23*Q45/DRIVERS!$B$24 -> 83.054813 | T45: =J45*INDEX(DRIVERS!$C$32:$C$42,MATCH(B45,DRIVERS!$A$32:$A$42,0)) -> 0 | U45: =J45*INDEX(SUPPLIERS!$E$3:$E$30,MATCH(C45,SUPPLIERS!$A$3:$A$30,0)) -> 0 | V45: 0 | W45: =J45+S45+T45+U45+V45 -> 138083.05 | X45: =W45/J45-1 -> 0.00060184647 | Y45: =INDEX(DRIVERS!$B$32:$B$42,MATCH(B45,DRIVERS!$A$32:$A$42,0)) -> 0.1 | Z45: =W45*(1+Y45) -> 151891.36 | AA45: =W45*(1+Y45+DRIVERS!$B$26)*(1+DRIVERS!$B$27) -> 177850.97 | AB45: Sep 3, 2026
... A55: IAN-INV-022 | B55: Inverter | C55: IAN Solar | D55: SOLIS S6-EH1P10K-L-PLUS HYBRID 10kW | E55: Solis; 10 kW; LV battery; Hybrid 1P LV battery (21A) | F55: pc | G55: pc | H55: 68000 | I55: =INDEX(SUPPLIERS!$D$3:$D$30,MATCH(C55,SUPPLIERS!$A$3:$A$30,0)) -> 0 | J55: =H55*(1-I55) -> 68000 | K55: 10 | L55: kW | M55: =IF(K55="","",J55/K55) -> 6800 | N55: 33 | O55: 0.1295 | P55: List: gross weight, packaging size | Q55: =MAX(N55/DRIVERS!$B$5,O55/DRIVERS!$B$6) -> 0.011 | R55: =ROUNDDOWN(1/Q55,0) -> 90 | S55: =DRIVERS!$B$23*Q55/DRIVERS!$B$24 -> 57.100184 | T55: =J55*INDEX(DRIVERS!$C$32:$C$42,MATCH(B55,DRIVERS!$A$32:$A$42,0)) -> 0 | U55: =J55*INDEX(SUPPLIERS!$E$3:$E$30,MATCH(C55,SUPPLIERS!$A$3:$A$30,0)) -> 0 | V55: 0 | W55: =J55+S55+T55+U55+V55 -> 68057.1 | X55: =W55/J55-1 -> 0.00083970859 | Y55: =INDEX(DRIVERS!$B$32:$B$42,MATCH(B55,DRIVERS!$A$32:$A$42,0)) -> 0.1 | Z55: =W55*(1+Y55) -> 74862.81 | AA55: =W55*(1+Y55+DRIVERS!$B$26)*(1+DRIVERS!$B$27) -> 87657.545 | AB55: Sep 3, 2026
A56: IAN-INV-023 | B56: Inverter | C56: IAN Solar | D56: SOLIS S6-EH1P12K03-NV-YD-L HYBRID 12kW | E56: Solis; 12 kW; List says '12W' - typo for 12kW | F56: pc | G56: pc | H56: 82000 | I56: =INDEX(SUPPLIERS!$D$3:$D$30,MATCH(C56,SUPPLIERS!$A$3:$A$30,0)) -> 0 | J56: =H56*(1-I56) -> 82000 | K56: 12 | L56: kW | M56: =IF(K56="","",J56/K56) -> 6833.3333 | N56: 61.5 | O56: 0.24067 | P56: List: gross weight, packaging size | Q56: =MAX(N56/DRIVERS!$B$5,O56/DRIVERS!$B$6) -> 0.0205 | R56: =ROUNDDOWN(1/Q56,0) -> 48 | S56: =DRIVERS!$B$23*Q56/DRIVERS!$B$24 -> 106.41398 | T56: =J56*INDEX(DRIVERS!$C$32:$C$42,MATCH(B56,DRIVERS!$A$32:$A$42,0)) -> 0 | U56: =J56*INDEX(SUPPLIERS!$E$3:$E$30,MATCH(C56,SUPPLIERS!$A$3:$A$30,0)) -> 0 | V56: 0 | W56: =J56+S56+T56+U56+V56 -> 82106.414 | X56: =W56/J56-1 -> 0.0012977315 | Y56: =INDEX(DRIVERS!$B$32:$B$42,MATCH(B56,DRIVERS!$A$32:$A$42,0)) -> 0.1 | Z56: =W56*(1+Y56) -> 90317.055 | AA56: =W56*(1+Y56+DRIVERS!$B$26)*(1+DRIVERS!$B$27) -> 105753.06 | AB56: Sep 3, 2026 | AD56: CHECK: see Model / spec column
A57: IAN-INV-024 | B57: Inverter | C57: IAN Solar | D57: SOLIS S6-EH1P16K03-NV-YD-L HYBRID 16kW | E57: Solis; 16 kW; LV battery; Hybrid 1P LV battery | F57: pc | G57: pc | H57: 113000 | I57: =INDEX(SUPPLIERS!$D$3:$D$30,MATCH(C57,SUPPLIERS!$A$3:$A$30,0)) -> 0 | J57: =H57*(1-I57) -> 113000 | K57: 16 | L57: kW | M57: =IF(K57="","",J57/K57) -> 7062.5 | N57: 55.5 | O57: 0.19323 | P57: List: gross weight, packaging size | Q57: =MAX(N57/DRIVERS!$B$5,O57/DRIVERS!$B$6) -> 0.0185 | R57: =ROUNDDOWN(1/Q57,0) -> 54 | S57: =DRIVERS!$B$23*Q57/DRIVERS!$B$24 -> 96.032128 | T57: =J57*INDEX(DRIVERS!$C$32:$C$42,MATCH(B57,DRIVERS!$A$32:$A$42,0)) -> 0 | U57: =J57*INDEX(SUPPLIERS!$E$3:$E$30,MATCH(C57,SUPPLIERS!$A$3:$A$30,0)) -> 0 | V57: 0 | W57: =J57+S57+T57+U57+V57 -> 113096.03 | X57: =W57/J57-1 -> 0.00084984184 | Y57: =INDEX(DRIVERS!$B$32:$B$42,MATCH(B57,DRIVERS!$A$32:$A$42,0)) -> 0.1 | Z57: =W57*(1+Y57) -> 124405.64 | AA57: =W57*(1+Y57+DRIVERS!$B$26)*(1+DRIVERS!$B$27) -> 145667.69 | AB57: Sep 3, 2026
A58: IAN-INV-025 | B58: Inverter | C58: IAN Solar | D58: SOLIS S6-EH1P6K-L-PLUS HYBRID 6kW | E58: Solis; 6 kW; LV battery; Hybrid 1P LV battery | F58: pc | G58: pc | H58: 43000 | I58: =INDEX(SUPPLIERS!$D$3:$D$30,MATCH(C58,SUPPLIERS!$A$3:$A$30,0)) -> 0 | J58: =H58*(1-I58) -> 43000 | K58: 6 | L58: kW | M58: =IF(K58="","",J58/K58) -> 7166.6667 | N58: 27.5 | O58: 0.10613 | P58: List: gross weight, packaging size | Q58: =MAX(N58/DRIVERS!$B$5,O58/DRIVERS!$B$6) -> 0.0091666667 | R58: =ROUNDDOWN(1/Q58,0) -> 109 | S58: =DRIVERS!$B$23*Q58/DRIVERS!$B$24 -> 47.583487 | T58: =J58*INDEX(DRIVERS!$C$32:$C$42,MATCH(B58,DRIVERS!$A$32:$A$42,0)) -> 0 | U58: =J58*INDEX(SUPPLIERS!$E$3:$E$30,MATCH(C58,SUPPLIERS!$A$3:$A$30,0)) -> 0 | V58: 0 | W58: =J58+S58+T58+U58+V58 -> 43047.583 | X58: =W58/J58-1 -> 0.0011065927 | Y58: =INDEX(DRIVERS!$B$32:$B$42,MATCH(B58,DRIVERS!$A$32:$A$42,0)) -> 0.1 | Z58: =W58*(1+Y58) -> 47352.342 | AA58: =W58*(1+Y58+DRIVERS!$B$26)*(1+DRIVERS!$B$27) -> 55445.288 | AB58: Sep 3, 2026
A59: IAN-INV-026 | B59: Inverter | C59: IAN Solar | D59: SOLIS S6-EH1P8K-L-PLUS HYBRID 8kW | E59: Solis; 8 kW; LV battery; Hybrid 1P LV battery | F59: pc | G59: pc | H59: 59000 | I59: =INDEX(SUPPLIERS!$D$3:$D$30,MATCH(C59,SUPPLIERS!$A$3:$A$30,0)) -> 0 | J59: =H59*(1-I59) -> 59000 | K59: 8 | L59: kW | M59: =IF(K59="","",J59/K59) -> 7375 | N59: 33.4 | O59: 0.1295 | P59: List: gross weight, packaging size | Q59: =MAX(N59/DRIVERS!$B$5,O59/DRIVERS!$B$6) -> 0.011133333 | R59: =ROUNDDOWN(1/Q59,0) -> 89 | S59: =DRIVERS!$B$23*Q59/DRIVERS!$B$24 -> 57.792308 | T59: =J59*INDEX(DRIVERS!$C$32:$C$42,MATCH(B59,DRIVERS!$A$32:$A$42,0)) -> 0 | U59: =J59*INDEX(SUPPLIERS!$E$3:$E$30,MATCH(C59,SUPPLIERS!$A$3:$A$30,0)) -> 0 | V59: 0 | W59: =J59+S59+T59+U59+V59 -> 59057.792 | X59: =W59/J59-1 -> 0.00097953064 | Y59: =INDEX(DRIVERS!$B$32:$B$42,MATCH(B59,DRIVERS!$A$32:$A$42,0)) -> 0.1 | Z59: =W59*(1+Y59) -> 64963.572 | AA59: =W59*(1+Y59+DRIVERS!$B$26)*(1+DRIVERS!$B$27) -> 76066.436 | AB59: Sep 3, 2026
A60: IAN-INV-027 | B60: Inverter | C60: IAN Solar | D60: SOLIS S6-EH1P5K-L-PLUS HYBRID 5kW | E60: Solis; 5 kW; LV battery; Hybrid 1P LV battery | F60: pc | G60: pc | H60: 41000 | I60: =INDEX(SUPPLIERS!$D$3:$D$30,MATCH(C60,SUPPLIERS!$A$3:$A$30,0)) -> 0 | J60: =H60*(1-I60) -> 41000 | K60: 5 | L60: kW | M60: =IF(K60="","",J60/K60) -> 8200 | N60: 25 | O60: 0.0649 | P60: List: gross weight, packaging size | Q60: =MAX(N60/DRIVERS!$B$5,O60/DRIVERS!$B$6) -> 0.0083333333 | R60: =ROUNDDOWN(1/Q60,0) -> 120 | S60: =DRIVERS!$B$23*Q60/DRIVERS!$B$24 -> 43.257715 | T60: =J60*INDEX(DRIVERS!$C$32:$C$42,MATCH(B60,DRIVERS!$A$32:$A$42,0)) -> 0 | U60: =J60*INDEX(SUPPLIERS!$E$3:$E$30,MATCH(C60,SUPPLIERS!$A$3:$A$30,0)) -> 0 | V60: 0 | W60: =J60+S60+T60+U60+V60 -> 41043.258 | X60: =W60/J60-1 -> 0.0010550662 | Y60: =INDEX(DRIVERS!$B$32:$B$42,MATCH(B60,DRIVERS!$A$32:$A$42,0)) -> 0.1 | Z60: =W60*(1+Y60) -> 45147.583 | AA60: =W60*(1+Y60+DRIVERS!$B$26)*(1+DRIVERS!$B$27) -> 52863.716 | AB60: Sep 3, 2026
A61: IAN-INV-028 | B61: Inverter | C61: IAN Solar | D61: SOLIS S6-EH3P125K10-NV-YD-H HYBRID 3P 125kW 380-400V | E61: Solis; 125 kW; 380-400V; HV battery | F61: pc | G61: pc | H61: 580000 | I61: =INDEX(SUPPLIERS!$D$3:$D$30,MATCH(C61,SUPPLIERS!$A$3:$A$30,0)) -> 0 | J61: =H61*(1-I61) -> 580000 | K61: 125 | L61: kW | M61: =IF(K61="","",J61/K61) -> 4640 | N61: 235 | O61: 0.78 | P61: List: gross weight, packaging size | Q61: =MAX(N61/DRIVERS!$B$5,O61/DRIVERS!$B$6) -> 0.078333333 | R61: =ROUNDDOWN(1/Q61,0) -> 12 | S61: =DRIVERS!$B$23*Q61/DRIVERS!$B$24 -> 406.62252 | T61: =J61*INDEX(DRIVERS!$C$32:$C$42,MATCH(B61,DRIVERS!$A$32:$A$42,0)) -> 0 | U61: =J61*INDEX(SUPPLIERS!$E$3:$E$30,MATCH(C61,SUPPLIERS!$A$3:$A$30,0)) -> 0 | V61: 0 | W61: =J61+S61+T61+U61+V61 -> 580406.62 | X61: =W61/J61-1 -> 0.00070107332 | Y61: =INDEX(DRIVERS!$B$32:$B$42,MATCH(B61,DRIVERS!$A$32:$A$42,0)) -> 0.1 | Z61: =W61*(1+Y61) -> 638447.28 | AA61: =W61*(1+Y61+DRIVERS!$B$26)*(1+DRIVERS!$B$27) -> 747563.73 | AB61: Sep 3, 2026
A62: IAN-INV-029 | B62: Inverter | C62: IAN Solar | D62: SOLIS S6-EH3P50K-H HYBRID 3P 50kW 380-400V | E62: Solis; 50 kW; 380-400V; HV battery | F62: pc | G62: pc | H62: 310000 | I62: =INDEX(SUPPLIERS!$D$3:$D$30,MATCH(C62,SUPPLIERS!$A$3:$A$30,0)) -> 0 | J62: =H62*(1-I62) -> 310000 | K62: 50 | L62: kW | M62: =IF(K62="","",J62/K62) -> 6200 | N62: 88 | O62: 0.30712 | P62: List: gross weight, packaging size | Q62: =MAX(N62/DRIVERS!$B$5,O62/DRIVERS!$B$6) -> 0.029333333 | R62: =ROUNDDOWN(1/Q62,0) -> 34 | S62: =DRIVERS!$B$23*Q62/DRIVERS!$B$24 -> 152.26716 | T62: =J62*INDEX(DRIVERS!$C$32:$C$42,MATCH(B62,DRIVERS!$A$32:$A$42,0)) -> 0 | U62: =J62*INDEX(SUPPLIERS!$E$3:$E$30,MATCH(C62,SUPPLIERS!$A$3:$A$30,0)) -> 0 | V62: 0 | W62: =J62+S62+T62+U62+V62 -> 310152.27 | X62: =W62/J62-1 -> 0.00049118438 | Y62: =INDEX(DRIVERS!$B$32:$B$42,MATCH(B62,DRIVERS!$A$32:$A$42,0)) -> 0.1 | Z62: =W62*(1+Y62) -> 341167.49 | AA62: =W62*(1+Y62+DRIVERS!$B$26)*(1+DRIVERS!$B$27) -> 399476.12 | AB62: Sep 3, 2026
A63: IAN-INV-030 | B63: Inverter | C63: IAN Solar | D63: SOLIS S6-EH3P75K10-LV-YD-H HYBRID 3P 75kW 220-230V | E63: Solis; 75 kW; 220-230V; HV battery | F63: pc | G63: pc | H63: 580000 | I63: =INDEX(SUPPLIERS!$D$3:$D$30,MATCH(C63,SUPPLIERS!$A$3:$A$30,0)) -> 0 | J63: =H63*(1-I63) -> 580000 | K63: 75 | L63: kW | M63: =IF(K63="","",J63/K63) -> 7733.3333 | N63: 170.1 | O63: 0.51718 | P63: List: gross weight, packaging size | Q63: =MAX(N63/DRIVERS!$B$5,O63/DRIVERS!$B$6) -> 0.0567 | R63: =ROUNDDOWN(1/Q63,0) -> 17 | S63: =DRIVERS!$B$23*Q63/DRIVERS!$B$24 -> 294.32549 | T63: =J63*INDEX(DRIVERS!$C$32:$C$42,MATCH(B63,DRIVERS!$A$32:$A$42,0)) -> 0 | U63: =J63*INDEX(SUPPLIERS!$E$3:$E$30,MATCH(C63,SUPPLIERS!$A$3:$A$30,0)) -> 0 | V63: 0 | W63: =J63+S63+T63+U63+V63 -> 580294.33 | X63: =W63/J63-1 -> 0.00050745775 | Y63: =INDEX(DRIVERS!$B$32:$B$42,MATCH(B63,DRIVERS!$A$32:$A$42,0)) -> 0.1 | Z63: =W63*(1+Y63) -> 638323.76 | AA63: =W63*(1+Y63+DRIVERS!$B$26)*(1+DRIVERS!$B$27) -> 747419.09 | AB63: Sep 3, 2026
A64: IAN-INV-031 | B64: Inverter | C64: IAN Solar | D64: SOLIS S6-EH3P15K02-NV-YD-L HYBRID 3P 15kW 380-400V | E64: Solis; 15 kW; 380-400V; LV battery | F64: pc | G64: pc | H64: 124000 | I64: =INDEX(SUPPLIERS!$D$3:$D$30,MATCH(C64,SUPPLIERS!$A$3:$A$30,0)) -> 0 | J64: =H64*(1-I64) -> 124000 | K64: 15 | L64: kW | M64: =IF(K64="","",J64/K64) -> 8266.6667 | N64: 48 | O64: 0.17601 | P64: List: gross weight, packaging size | Q64: =MAX(N64/DRIVERS!$B$5,O64/DRIVERS!$B$6) -> 0.016 | R64: =ROUNDDOWN(1/Q64,0) -> 62 | S64: =DRIVERS!$B$23*Q64/DRIVERS!$B$24 -> 83.054813 | T64: =J64*INDEX(DRIVERS!$C$32:$C$42,MATCH(B64,DRIVERS!$A$32:$A$42,0)) -> 0 | U64: =J64*INDEX(SUPPLIERS!$E$3:$E$30,MATCH(C64,SUPPLIERS!$A$3:$A$30,0)) -> 0 | V64: 0 | W64: =J64+S64+T64+U64+V64 -> 124083.05 | X64: =W64/J64-1 -> 0.00066979688 | Y64: =INDEX(DRIVERS!$B$32:$B$42,MATCH(B64,DRIVERS!$A$32:$A$42,0)) -> 0.1 | Z64: =W64*(1+Y64) -> 136491.36 | AA64: =W64*(1+Y64+DRIVERS!$B$26)*(1+DRIVERS!$B$27) -> 159818.97 | AB64: Sep 3, 2026
A65: IAN-INV-032 | B65: Inverter | C65: IAN Solar | D65: SOLIS S6-EH3P60K10-LV-YD-H HYBRID 3P 60kW 220-230V | E65: Solis; 60 kW; 220-230V; HV battery | F65: pc | G65: pc | H65: 500000 | I65: =INDEX(SUPPLIERS!$D$3:$D$30,MATCH(C65,SUPPLIERS!$A$3:$A$30,0)) -> 0 | J65: =H65*(1-I65) -> 500000 | K65: 60 | L65: kW | M65: =IF(K65="","",J65/K65) -> 8333.3333 | N65: 205 | O65: 0.7938 | P65: List: gross weight, packaging size | Q65: =MAX(N65/DRIVERS!$B$5,O65/DRIVERS!$B$6) -> 0.068333333 | R65: =ROUNDDOWN(1/Q65,0) -> 14 | S65: =DRIVERS!$B$23*Q65/DRIVERS!$B$24 -> 354.71326 | T65: =J65*INDEX(DRIVERS!$C$32:$C$42,MATCH(B65,DRIVERS!$A$32:$A$42,0)) -> 0 | U65: =J65*INDEX(SUPPLIERS!$E$3:$E$30,MATCH(C65,SUPPLIERS!$A$3:$A$30,0)) -> 0 | V65: 0 | W65: =J65+S65+T65+U65+V65 -> 500354.71 | X65: =W65/J65-1 -> 0.00070942653 | Y65: =INDEX(DRIVERS!$B$32:$B$42,MATCH(B65,DRIVERS!$A$32:$A$42,0)) -> 0.1 | Z65: =W65*(1+Y65) -> 550390.18 | AA65: =W65*(1+Y65+DRIVERS!$B$26)*(1+DRIVERS!$B$27) -> 644456.87 | AB65: Sep 3, 2026
A66: IAN-INV-033 | B66: Inverter | C66: IAN Solar | D66: SOLIS S6-EH3P30K-H-LV HYBRID 3P 30kW 220-230V | E66: Solis; confirm 30 kW; 220-230V; HV battery; HV battery; list shows '259,00' - | F66: pc | G66: pc | H66: 259000 | I66: =INDEX(SUPPLIERS!$D$3:$D$30,MATCH(C66,SUPPLIERS!$A$3:$A$30,0)) -> 0 | J66: =H66*(1-I66) -> 259000 | K66: 30 | L66: kW | M66: =IF(K66="","",J66/K66) -> 8633.3333 | N66: 80 | O66: 0.1995 | P66: List: gross weight, packaging size | Q66: =MAX(N66/DRIVERS!$B$5,O66/DRIVERS!$B$6) -> 0.026666667 | R66: =ROUNDDOWN(1/Q66,0) -> 37 | S66: =DRIVERS!$B$23*Q66/DRIVERS!$B$24 -> 138.42469 | T66: =J66*INDEX(DRIVERS!$C$32:$C$42,MATCH(B66,DRIVERS!$A$32:$A$42,0)) -> 0 | U66: =J66*INDEX(SUPPLIERS!$E$3:$E$30,MATCH(C66,SUPPLIERS!$A$3:$A$30,0)) -> 0 | V66: 0 | W66: =J66+S66+T66+U66+V66 -> 259138.42 | X66: =W66/J66-1 -> 0.00053445826 | Y66: =INDEX(DRIVERS!$B$32:$B$42,MATCH(B66,DRIVERS!$A$32:$A$42,0)) -> 0.1 | Z66: =W66*(1+Y66) -> 285052.27 | AA66: =W66*(1+Y66+DRIVERS!$B$26)*(1+DRIVERS!$B$27) -> 333770.29 | AB66: Sep 3, 2026 | AD66: CHECK: see Model / spec column
A67: IAN-INV-034 | B67: Inverter | C67: IAN Solar | D67: SOLIS S6-EH3P9K02-LV-YD-L HYBRID 3P 9kW 220-230V | E67: Solis; 9 kW; 220-230V; LV battery | F67: pc | G67: pc | H67: 110000 | I67: =INDEX(SUPPLIERS!$D$3:$D$30,MATCH(C67,SUPPLIERS!$A$3:$A$30,0)) -> 0 | J67: =H67*(1-I67) -> 110000 | K67: 9 | L67: kW | M67: =IF(K67="","",J67/K67) -> 12222.222 | N67: 45 | O67: 0.156 | P67: List: gross weight, packaging size | Q67: =MAX(N67/DRIVERS!$B$5,O67/DRIVERS!$B$6) -> 0.015 | R67: =ROUNDDOWN(1/Q67,0) -> 66 | S67: =DRIVERS!$B$23*Q67/DRIVERS!$B$24 -> 77.863887 | T67: =J67*INDEX(DRIVERS!$C$32:$C$42,MATCH(B67,DRIVERS!$A$32:$A$42,0)) -> 0 | U67: =J67*INDEX(SUPPLIERS!$E$3:$E$30,MATCH(C67,SUPPLIERS!$A$3:$A$30,0)) -> 0 | V67: 0 | W67: =J67+S67+T67+U67+V67 -> 110077.86 | X67: =W67/J67-1 -> 0.00070785352 | Y67: =INDEX(DRIVERS!$B$32:$B$42,MATCH(B67,DRIVERS!$A$32:$A$42,0)) -> 0.1 | Z67: =W67*(1+Y67) -> 121085.65 | AA67: =W67*(1+Y67+DRIVERS!$B$26)*(1+DRIVERS!$B$27) -> 141780.29 | AB67: Sep 3, 2026
A68: IAN-INV-035 | B68: Inverter | C68: IAN Solar | D68: SOLIS S6-EO1P5K-48 OFF-GRID 5kW | E68: Solis; 5 kW; Off-grid 1P LV | F68: pc | G68: pc | H68: 30000 | I68: =INDEX(SUPPLIERS!$D$3:$D$30,MATCH(C68,SUPPLIERS!$A$3:$A$30,0)) -> 0 | J68: =H68*(1-I68) -> 30000 | K68: 5 | L68: kW | M68: =IF(K68="","",J68/K68) -> 6000 | N68: 16 | O68: 0.0588 | P68: List: gross weight, packaging size | Q68: =MAX(N68/DRIVERS!$B$5,O68/DRIVERS!$B$6) -> 0.0053333333 | R68: =ROUNDDOWN(1/Q68,0) -> 187 | S68: =DRIVERS!$B$23*Q68/DRIVERS!$B$24 -> 27.684938 | T68: =J68*INDEX(DRIVERS!$C$32:$C$42,MATCH(B68,DRIVERS!$A$32:$A$42,0)) -> 0 | U68: =J68*INDEX(SUPPLIERS!$E$3:$E$30,MATCH(C68,SUPPLIERS!$A$3:$A$30,0)) -> 0 | V68: 0 | W68: =J68+S68+T68+U68+V68 -> 30027.685 | X68: =W68/J68-1 -> 0.00092283126 | Y68: =INDEX(DRIVERS!$B$32:$B$42,MATCH(B68,DRIVERS!$A$32:$A$42,0)) -> 0.1 | Z68: =W68*(1+Y68) -> 33030.453 | AA68: =W68*(1+Y68+DRIVERS!$B$26)*(1+DRIVERS!$B$27) -> 38675.658 | AB68: Sep 3, 2026
A69: OP-INV-001 | B69: Inverter | C69: One Point | D69: 40A ONE MPPT - 12/24/48V | E69: One Solar | F69: pc | G69: pc | H69: 4500 | I69: =INDEX(SUPPLIERS!$D$3:$D$30,MATCH(C69,SUPPLIERS!$A$3:$A$30,0)) -> 0 | J69: =H69*(1-I69) -> 4500 | M69: =IF(K69="","",J69/K69) | N69: 2.5 | O69: 0.00653 | P69: List: gross weight, packaging size | Q69: =MAX(N69/DRIVERS!$B$5,O69/DRIVERS!$B$6) -> 0.00083333333 | R69: =ROUNDDOWN(1/Q69,0) -> 1200 | S69: =DRIVERS!$B$23*Q69/DRIVERS!$B$24 -> 4.3257715 | T69: =J69*INDEX(DRIVERS!$C$32:$C$42,MATCH(B69,DRIVERS!$A$32:$A$42,0)) -> 0 | U69: =J69*INDEX(SUPPLIERS!$E$3:$E$30,MATCH(C69,SUPPLIERS!$A$3:$A$30,0)) -> 0 | V69: 0 | W69: =J69+S69+T69+U69+V69 -> 4504.3258 | X69: =W69/J69-1 -> 0.00096128256 | Y69: =INDEX(DRIVERS!$B$32:$B$42,MATCH(B69,DRIVERS!$A$32:$A$42,0)) -> 0.1 | Z69: =W69*(1+Y69) -> 4954.7583 | AA69: =W69*(1+Y69+DRIVERS!$B$26)*(1+DRIVERS!$B$27) -> 5801.5716 | AB69: Sep 11, 2026
A70: OP-INV-002 | B70: Inverter | C70: One Point | D70: 60A ONE MPPT - 12/24/48V | E70: One Solar | F70: pc | G70: pc | H70: 5500 | I70: =INDEX(SUPPLIERS!$D$3:$D$30,MATCH(C70,SUPPLIERS!$A$3:$A$30,0)) -> 0 | J70: =H70*(1-I70) -> 5500 | M70: =IF(K70="","",J70/K70) | N70: 3.9 | O70: 0.01612 | P70: List: gross weight, packaging size | Q70: =MAX(N70/DRIVERS!$B$5,O70/DRIVERS!$B$6) -> 0.0013 | R70: =ROUNDDOWN(1/Q70,0) -> 769 | S70: =DRIVERS!$B$23*Q70/DRIVERS!$B$24 -> 6.7482036 | T70: =J70*INDEX(DRIVERS!$C$32:$C$42,MATCH(B70,DRIVERS!$A$32:$A$42,0)) -> 0 | U70: =J70*INDEX(SUPPLIERS!$E$3:$E$30,MATCH(C70,SUPPLIERS!$A$3:$A$30,0)) -> 0 | V70: 0 | W70: =J70+S70+T70+U70+V70 -> 5506.7482 | X70: =W70/J70-1 -> 0.0012269461 | Y70: =INDEX(DRIVERS!$B$32:$B$42,MATCH(B70,DRIVERS!$A$32:$A$42,0)) -> 0.1 | Z70: =W70*(1+Y70) -> 6057.423 | AA70: =W70*(1+Y70+DRIVERS!$B$26)*(1+DRIVERS!$B$27) -> 7092.6917 | AB70: Sep 11, 2026
A71: OP-INV-003 | B71: Inverter | C71: One Point | D71: 100A ONE MPPT - 12/24/48V | E71: One Solar | F71: pc | G71: pc | H71: 6500 | I71: =INDEX(SUPPLIERS!$D$3:$D$30,MATCH(C71,SUPPLIERS!$A$3:$A$30,0)) -> 0 | J71: =H71*(1-I71) -> 6500 | M71: =IF(K71="","",J71/K71) | N71: 0.95 | O71: 0.00294 | P71: List: gross weight, packaging size | Q71: =MAX(N71/DRIVERS!$B$5,O71/DRIVERS!$B$6) -> 0.00031666667 | R71: =ROUNDDOWN(1/Q71,0) -> 3157 | S71: =DRIVERS!$B$23*Q71/DRIVERS!$B$24 -> 1.6437932 | T71: =J71*INDEX(DRIVERS!$C$32:$C$42,MATCH(B71,DRIVERS!$A$32:$A$42,0)) -> 0 | U71: =J71*INDEX(SUPPLIERS!$E$3:$E$30,MATCH(C71,SUPPLIERS!$A$3:$A$30,0)) -> 0 | V71: 0 | W71: =J71+S71+T71+U71+V71 -> 6501.6438 | X71: =W71/J71-1 -> 0.00025289126 | Y71: =INDEX(DRIVERS!$B$32:$B$42,MATCH(B71,DRIVERS!$A$32:$A$42,0)) -> 0.1 | Z71: =W71*(1+Y71) -> 7151.8082 | AA71: =W71*(1+Y71+DRIVERS!$B$26)*(1+DRIVERS!$B$27) -> 8374.1172 | AB71: Sep 11, 2026
A72: OP-INV-004 | B72: Inverter | C72: One Point | D72: DEYE 1P-8.0KW GRID-TIE | E72: Deye; 8 kW | F72: pc | G72: pc | H72: 28000 | I72: =INDEX(SUPPLIERS!$D$3:$D$30,MATCH(C72,SUPPLIERS!$A$3:$A$30,0)) -> 0 | J72: =H72*(1-I72) -> 28000 | K72: 8 | L72: kW | M72: =IF(K72="","",J72/K72) -> 3500 | N72: 18 | O72: 0.05 | P72: List: gross weight, packaging size | Q72: =MAX(N72/DRIVERS!$B$5,O72/DRIVERS!$B$6) -> 0.006 | R72: =ROUNDDOWN(1/Q72,0) -> 166 | S72: =DRIVERS!$B$23*Q72/DRIVERS!$B$24 -> 31.145555 | T72: =J72*INDEX(DRIVERS!$C$32:$C$42,MATCH(B72,DRIVERS!$A$32:$A$42,0)) -> 0 | U72: =J72*INDEX(SUPPLIERS!$E$3:$E$30,MATCH(C72,SUPPLIERS!$A$3:$A$30,0)) -> 0 | V72: 0 | W72: =J72+S72+T72+U72+V72 -> 28031.146 | X72: =W72/J72-1 -> 0.0011123412 | Y72: =INDEX(DRIVERS!$B$32:$B$42,MATCH(B72,DRIVERS!$A$32:$A$42,0)) -> 0.1 | Z72: =W72*(1+Y72) -> 30834.26 | AA72: =W72*(1+Y72+DRIVERS!$B$26)*(1+DRIVERS!$B$27) -> 36104.115 | AB72: Sep 11, 2026
A73: OP-INV-005 | B73: Inverter | C73: One Point | D73: DEYE 1P-10.0KW GRID-TIE | E73: Deye; 10 kW | F73: pc | G73: pc | H73: 35000 | I73: =INDEX(SUPPLIERS!$D$3:$D$30,MATCH(C73,SUPPLIERS!$A$3:$A$30,0)) -> 0 | J73: =H73*(1-I73) -> 35000 | K73: 10 | L73: kW | M73: =IF(K73="","",J73/K73) -> 3500 | N73: 18 | O73: 0.07093 | P73: List: gross weight, packaging size | Q73: =MAX(N73/DRIVERS!$B$5,O73/DRIVERS!$B$6) -> 0.006 | R73: =ROUNDDOWN(1/Q73,0) -> 166 | S73: =DRIVERS!$B$23*Q73/DRIVERS!$B$24 -> 31.145555 | T73: =J73*INDEX(DRIVERS!$C$32:$C$42,MATCH(B73,DRIVERS!$A$32:$A$42,0)) -> 0 | U73: =J73*INDEX(SUPPLIERS!$E$3:$E$30,MATCH(C73,SUPPLIERS!$A$3:$A$30,0)) -> 0 | V73: 0 | W73: =J73+S73+T73+U73+V73 -> 35031.146 | X73: =W73/J73-1 -> 0.000889873 | Y73: =INDEX(DRIVERS!$B$32:$B$42,MATCH(B73,DRIVERS!$A$32:$A$42,0)) -> 0.1 | Z73: =W73*(1+Y73) -> 38534.26 | AA73: =W73*(1+Y73+DRIVERS!$B$26)*(1+DRIVERS!$B$27) -> 45120.115 | AB73: Sep 11, 2026
A74: OP-INV-006 | B74: Inverter | C74: One Point | D74: DEYE 1P-6.0KW GRID-TIE | E74: Deye; 6 kW | F74: pc | G74: pc | H74: 25000 | I74: =INDEX(SUPPLIERS!$D$3:$D$30,MATCH(C74,SUPPLIERS!$A$3:$A$30,0)) -> 0 | J74: =H74*(1-I74) -> 25000 | K74: 6 | L74: kW | M74: =IF(K74="","",J74/K74) -> 4166.6667 | N74: 9.5 | O74: 0.05676 | P74: List: gross weight, packaging size | Q74: =MAX(N74/DRIVERS!$B$5,O74/DRIVERS!$B$6) -> 0.0039764208 | R74: =ROUNDDOWN(1/Q74,0) -> 251 | S74: =DRIVERS!$B$23*Q74/DRIVERS!$B$24 -> 20.641305 | T74: =J74*INDEX(DRIVERS!$C$32:$C$42,MATCH(B74,DRIVERS!$A$32:$A$42,0)) -> 0 | U74: =J74*INDEX(SUPPLIERS!$E$3:$E$30,MATCH(C74,SUPPLIERS!$A$3:$A$30,0)) -> 0 | V74: 0 | W74: =J74+S74+T74+U74+V74 -> 25020.641 | X74: =W74/J74-1 -> 0.00082565221 | Y74: =INDEX(DRIVERS!$B$32:$B$42,MATCH(B74,DRIVERS!$A$32:$A$42,0)) -> 0.1 | Z74: =W74*(1+Y74) -> 27522.705 | AA74: =W74*(1+Y74+DRIVERS!$B$26)*(1+DRIVERS!$B$27) -> 32226.586 | AB74: Sep 11, 2026
A75: OP-INV-007 | B75: Inverter | C75: One Point | D75: DEYE 1P-3.6KW GRID-TIE | E75: Deye; 3.6 kW | F75: pc | G75: pc | H75: 16000 | I75: =INDEX(SUPPLIERS!$D$3:$D$30,MATCH(C75,SUPPLIERS!$A$3:$A$30,0)) -> 0 | J75: =H75*(1-I75) -> 16000 | K75: 3.6 | L75: kW | M75: =IF(K75="","",J75/K75) -> 4444.4444 | N75: 13.5 | O75: 0.05084 | P75: List: gross weight, packaging size | Q75: =MAX(N75/DRIVERS!$B$5,O75/DRIVERS!$B$6) -> 0.0045 | R75: =ROUNDDOWN(1/Q75,0) -> 222 | S75: =DRIVERS!$B$23*Q75/DRIVERS!$B$24 -> 23.359166 | T75: =J75*INDEX(DRIVERS!$C$32:$C$42,MATCH(B75,DRIVERS!$A$32:$A$42,0)) -> 0 | U75: =J75*INDEX(SUPPLIERS!$E$3:$E$30,MATCH(C75,SUPPLIERS!$A$3:$A$30,0)) -> 0 | V75: 0 | W75: =J75+S75+T75+U75+V75 -> 16023.359 | X75: =W75/J75-1 -> 0.0014599479 | Y75: =INDEX(DRIVERS!$B$32:$B$42,MATCH(B75,DRIVERS!$A$32:$A$42,0)) -> 0.1 | Z75: =W75*(1+Y75) -> 17625.695 | AA75: =W75*(1+Y75+DRIVERS!$B$26)*(1+DRIVERS!$B$27) -> 20638.087 | AB75: Sep 11, 2026
A76: OP-INV-008 | B76: Inverter | C76: One Point | D76: DEYE-3P-050KW 380V | E76: Deye; 50 kW; 380V | F76: pc | G76: pc | H76: 100000 | I76: =INDEX(SUPPLIERS!$D$3:$D$30,MATCH(C76,SUPPLIERS!$A$3:$A$30,0)) -> 0 | J76: =H76*(1-I76) -> 100000 | K76: 50 | L76: kW | M76: =IF(K76="","",J76/K76) -> 2000 | N76: 45 | O76: 0.1134 | P76: List: gross weight, packaging size | Q76: =MAX(N76/DRIVERS!$B$5,O76/DRIVERS!$B$6) -> 0.015 | R76: =ROUNDDOWN(1/Q76,0) -> 66 | S76: =DRIVERS!$B$23*Q76/DRIVERS!$B$24 -> 77.863887 | T76: =J76*INDEX(DRIVERS!$C$32:$C$42,MATCH(B76,DRIVERS!$A$32:$A$42,0)) -> 0 | U76: =J76*INDEX(SUPPLIERS!$E$3:$E$30,MATCH(C76,SUPPLIERS!$A$3:$A$30,0)) -> 0 | V76: 0 | W76: =J76+S76+T76+U76+V76 -> 100077.86 | X76: =W76/J76-1 -> 0.00077863887 | Y76: =INDEX(DRIVERS!$B$32:$B$42,MATCH(B76,DRIVERS!$A$32:$A$42,0)) -> 0.1 | Z76: =W76*(1+Y76) -> 110085.65 | AA76: =W76*(1+Y76+DRIVERS!$B$26)*(1+DRIVERS!$B$27) -> 128900.29 | AB76: Sep 11, 2026
A77: OP-INV-009 | B77: Inverter | C77: One Point | D77: DEYE-3P-100KW 380V | E77: Deye; 100 kW; 380V | F77: pc | G77: pc | H77: 200000 | I77: =INDEX(SUPPLIERS!$D$3:$D$30,MATCH(C77,SUPPLIERS!$A$3:$A$30,0)) -> 0 | J77: =H77*(1-I77) -> 200000 | K77: 100 | L77: kW | M77: =IF(K77="","",J77/K77) -> 2000 | N77: 96 | O77: 0.50358 | P77: List: gross weight, packaging size | Q77: =MAX(N77/DRIVERS!$B$5,O77/DRIVERS!$B$6) -> 0.035279175 | R77: =ROUNDDOWN(1/Q77,0) -> 28 | S77: =DRIVERS!$B$23*Q77/DRIVERS!$B$24 -> 183.13158 | T77: =J77*INDEX(DRIVERS!$C$32:$C$42,MATCH(B77,DRIVERS!$A$32:$A$42,0)) -> 0 | U77: =J77*INDEX(SUPPLIERS!$E$3:$E$30,MATCH(C77,SUPPLIERS!$A$3:$A$30,0)) -> 0 | V77: 0 | W77: =J77+S77+T77+U77+V77 -> 200183.13 | X77: =W77/J77-1 -> 0.0009156579 | Y77: =INDEX(DRIVERS!$B$32:$B$42,MATCH(B77,DRIVERS!$A$32:$A$42,0)) -> 0.1 | Z77: =W77*(1+Y77) -> 220201.44 | AA77: =W77*(1+Y77+DRIVERS!$B$26)*(1+DRIVERS!$B$27) -> 257835.87 | AB77: Sep 11, 2026
A78: OP-INV-010 | B78: Inverter | C78: One Point | D78: DEYE-3P-125KW 480V | E78: Deye; 125 kW; 480V | F78: pc | G78: pc | H78: 250000 | I78: =INDEX(SUPPLIERS!$D$3:$D$30,MATCH(C78,SUPPLIERS!$A$3:$A$30,0)) -> 0 | J78: =H78*(1-I78) -> 250000 | K78: 125 | L78: kW | M78: =IF(K78="","",J78/K78) -> 2000 | N78: 113 | O78: 0.264 | P78: List: gross weight, packaging size | Q78: =MAX(N78/DRIVERS!$B$5,O78/DRIVERS!$B$6) -> 0.037666667 | R78: =ROUNDDOWN(1/Q78,0) -> 26 | S78: =DRIVERS!$B$23*Q78/DRIVERS!$B$24 -> 195.52487 | T78: =J78*INDEX(DRIVERS!$C$32:$C$42,MATCH(B78,DRIVERS!$A$32:$A$42,0)) -> 0 | U78: =J78*INDEX(SUPPLIERS!$E$3:$E$30,MATCH(C78,SUPPLIERS!$A$3:$A$30,0)) -> 0 | V78: 0 | W78: =J78+S78+T78+U78+V78 -> 250195.52 | X78: =W78/J78-1 -> 0.00078209949 | Y78: =INDEX(DRIVERS!$B$32:$B$42,MATCH(B78,DRIVERS!$A$32:$A$42,0)) -> 0.1 | Z78: =W78*(1+Y78) -> 275215.08 | AA78: =W78*(1+Y78+DRIVERS!$B$26)*(1+DRIVERS!$B$27) -> 322251.84 | AB78: Sep 11, 2026
A79: OP-INV-011 | B79: Inverter | C79: One Point | D79: DEYE 3P-75KW LV - GRID TIE | E79: Deye; 75 kW | F79: pc | G79: pc | H79: 200000 | I79: =INDEX(SUPPLIERS!$D$3:$D$30,MATCH(C79,SUPPLIERS!$A$3:$A$30,0)) -> 0 | J79: =H79*(1-I79) -> 200000 | K79: 75 | L79: kW | M79: =IF(K79="","",J79/K79) -> 2666.6667 | N79: 120 | O79: 0.36984 | P79: List net (gross 103 kg is below net 120 kg) | Q79: =MAX(N79/DRIVERS!$B$5,O79/DRIVERS!$B$6) -> 0.04 | R79: =ROUNDDOWN(1/Q79,0) -> 25 | S79: =DRIVERS!$B$23*Q79/DRIVERS!$B$24 -> 207.63703 | T79: =J79*INDEX(DRIVERS!$C$32:$C$42,MATCH(B79,DRIVERS!$A$32:$A$42,0)) -> 0 | U79: =J79*INDEX(SUPPLIERS!$E$3:$E$30,MATCH(C79,SUPPLIERS!$A$3:$A$30,0)) -> 0 | V79: 0 | W79: =J79+S79+T79+U79+V79 -> 200207.64 | X79: =W79/J79-1 -> 0.0010381852 | Y79: =INDEX(DRIVERS!$B$32:$B$42,MATCH(B79,DRIVERS!$A$32:$A$42,0)) -> 0.1 | Z79: =W79*(1+Y79) -> 220228.4 | AA79: =W79*(1+Y79+DRIVERS!$B$26)*(1+DRIVERS!$B$27) -> 257867.44 | AB79: Sep 11, 2026
A80: OP-INV-012 | B80: Inverter | C80: One Point | D80: DEYE 3P-50KW LV - GRID TIE | E80: Deye; 50 kW | F80: pc | G80: pc | H80: 150000 | I80: =INDEX(SUPPLIERS!$D$3:$D$30,MATCH(C80,SUPPLIERS!$A$3:$A$30,0)) -> 0 | J80: =H80*(1-I80) -> 150000 | K80: 50 | L80: kW | M80: =IF(K80="","",J80/K80) -> 3000 | N80: 80 | O80: 0.25725 | P80: List: gross weight, packaging size | Q80: =MAX(N80/DRIVERS!$B$5,O80/DRIVERS!$B$6) -> 0.026666667 | R80: =ROUNDDOWN(1/Q80,0) -> 37 | S80: =DRIVERS!$B$23*Q80/DRIVERS!$B$24 -> 138.42469 | T80: =J80*INDEX(DRIVERS!$C$32:$C$42,MATCH(B80,DRIVERS!$A$32:$A$42,0)) -> 0 | U80: =J80*INDEX(SUPPLIERS!$E$3:$E$30,MATCH(C80,SUPPLIERS!$A$3:$A$30,0)) -> 0 | V80: 0 | W80: =J80+S80+T80+U80+V80 -> 150138.42 | X80: =W80/J80-1 -> 0.00092283126 | Y80: =INDEX(DRIVERS!$B$32:$B$42,MATCH(B80,DRIVERS!$A$32:$A$42,0)) -> 0.1 | Z80: =W80*(1+Y80) -> 165152.27 | AA80: =W80*(1+Y80+DRIVERS!$B$26)*(1+DRIVERS!$B$27) -> 193378.29 | AB80: Sep 11, 2026
A81: OP-INV-013 | B81: Inverter | C81: One Point | D81: DEYE 3P-60KW LV - GRID TIE | E81: Deye; 60 kW | F81: pc | G81: pc | H81: 180000 | I81: =INDEX(SUPPLIERS!$D$3:$D$30,MATCH(C81,SUPPLIERS!$A$3:$A$30,0)) -> 0 | J81: =H81*(1-I81) -> 180000 | K81: 60 | L81: kW | M81: =IF(K81="","",J81/K81) -> 3000 | N81: 125 | O81: 0.4025 | P81: List: gross weight, packaging size | Q81: =MAX(N81/DRIVERS!$B$5,O81/DRIVERS!$B$6) -> 0.041666667 | R81: =ROUNDDOWN(1/Q81,0) -> 24 | S81: =DRIVERS!$B$23*Q81/DRIVERS!$B$24 -> 216.28858 | T81: =J81*INDEX(DRIVERS!$C$32:$C$42,MATCH(B81,DRIVERS!$A$32:$A$42,0)) -> 0 | U81: =J81*INDEX(SUPPLIERS!$E$3:$E$30,MATCH(C81,SUPPLIERS!$A$3:$A$30,0)) -> 0 | V81: 0 | W81: =J81+S81+T81+U81+V81 -> 180216.29 | X81: =W81/J81-1 -> 0.0012016032 | Y81: =INDEX(DRIVERS!$B$32:$B$42,MATCH(B81,DRIVERS!$A$32:$A$42,0)) -> 0.1 | Z81: =W81*(1+Y81) -> 198237.92 | AA81: =W81*(1+Y81+DRIVERS!$B$26)*(1+DRIVERS!$B$27) -> 232118.58 | AB81: Sep 11, 2026
A82: OP-INV-014 | B82: Inverter | C82: One Point | D82: DEYE 3P-30KW LV - GRID TIE | E82: Deye; 30 kW | F82: pc | G82: pc | H82: 100000 | I82: =INDEX(SUPPLIERS!$D$3:$D$30,MATCH(C82,SUPPLIERS!$A$3:$A$30,0)) -> 0 | J82: =H82*(1-I82) -> 100000 | K82: 30 | L82: kW | M82: =IF(K82="","",J82/K82) -> 3333.3333 | N82: 43 | O82: 0.12852 | P82: List: gross weight, packaging size | Q82: =MAX(N82/DRIVERS!$B$5,O82/DRIVERS!$B$6) -> 0.014333333 | R82: =ROUNDDOWN(1/Q82,0) -> 69 | S82: =DRIVERS!$B$23*Q82/DRIVERS!$B$24 -> 74.40327 | T82: =J82*INDEX(DRIVERS!$C$32:$C$42,MATCH(B82,DRIVERS!$A$32:$A$42,0)) -> 0 | U82: =J82*INDEX(SUPPLIERS!$E$3:$E$30,MATCH(C82,SUPPLIERS!$A$3:$A$30,0)) -> 0 | V82: 0 | W82: =J82+S82+T82+U82+V82 -> 100074.4 | X82: =W82/J82-1 -> 0.0007440327 | Y82: =INDEX(DRIVERS!$B$32:$B$42,MATCH(B82,DRIVERS!$A$32:$A$42,0)) -> 0.1 | Z82: =W82*(1+Y82) -> 110081.84 | AA82: =W82*(1+Y82+DRIVERS!$B$26)*(1+DRIVERS!$B$27) -> 128895.83 | AB82: Sep 11, 2026
A83: OP-INV-015 | B83: Inverter | C83: One Point | D83: DEYE 3P-20KW LV - GRID TIE | E83: Deye; 20 kW | F83: pc | G83: pc | H83: 80000 | I83: =INDEX(SUPPLIERS!$D$3:$D$30,MATCH(C83,SUPPLIERS!$A$3:$A$30,0)) -> 0 | J83: =H83*(1-I83) -> 80000 | K83: 20 | L83: kW | M83: =IF(K83="","",J83/K83) -> 4000 | N83: 35 | O83: 0.065 | P83: List: gross weight, packaging size | Q83: =MAX(N83/DRIVERS!$B$5,O83/DRIVERS!$B$6) -> 0.011666667 | R83: =ROUNDDOWN(1/Q83,0) -> 85 | S83: =DRIVERS!$B$23*Q83/DRIVERS!$B$24 -> 60.560801 | T83: =J83*INDEX(DRIVERS!$C$32:$C$42,MATCH(B83,DRIVERS!$A$32:$A$42,0)) -> 0 | U83: =J83*INDEX(SUPPLIERS!$E$3:$E$30,MATCH(C83,SUPPLIERS!$A$3:$A$30,0)) -> 0 | V83: 0 | W83: =J83+S83+T83+U83+V83 -> 80060.561 | X83: =W83/J83-1 -> 0.00075701002 | Y83: =INDEX(DRIVERS!$B$32:$B$42,MATCH(B83,DRIVERS!$A$32:$A$42,0)) -> 0.1 | Z83: =W83*(1+Y83) -> 88066.617 | AA83: =W83*(1+Y83+DRIVERS!$B$26)*(1+DRIVERS!$B$27) -> 103118 | AB83: Sep 11, 2026
... A102: OP-INV-034 | B102: Inverter | C102: One Point | D102: 12V1200W HYBRID OFF-GRID 40A | E102: One Solar; 1.2 kW | F102: pc | G102: pc | H102: 9000 | I102: =INDEX(SUPPLIERS!$D$3:$D$30,MATCH(C102,SUPPLIERS!$A$3:$A$30,0)) -> 0 | J102: =H102*(1-I102) -> 9000 | K102: 1.2 | L102: kW | M102: =IF(K102="","",J102/K102) -> 7500 | N102: 11.5 | O102: 0.03284 | P102: List: gross weight, packaging size | Q102: =MAX(N102/DRIVERS!$B$5,O102/DRIVERS!$B$6) -> 0.0038333333 | R102: =ROUNDDOWN(1/Q102,0) -> 260 | S102: =DRIVERS!$B$23*Q102/DRIVERS!$B$24 -> 19.898549 | T102: =J102*INDEX(DRIVERS!$C$32:$C$42,MATCH(B102,DRIVERS!$A$32:$A$42,0)) -> 0 | U102: =J102*INDEX(SUPPLIERS!$E$3:$E$30,MATCH(C102,SUPPLIERS!$A$3:$A$30,0)) -> 0 | V102: 0 | W102: =J102+S102+T102+U102+V102 -> 9019.8985 | X102: =W102/J102-1 -> 0.0022109499 | Y102: =INDEX(DRIVERS!$B$32:$B$42,MATCH(B102,DRIVERS!$A$32:$A$42,0)) -> 0.1 | Z102: =W102*(1+Y102) -> 9921.8884 | AA102: =W102*(1+Y102+DRIVERS!$B$26)*(1+DRIVERS!$B$27) -> 11617.629 | AB102: Sep 11, 2026
A103: BC-BAT-001 | B103: Battery | C103: Blue Carbon | D103: LiFePO4 25.6V 200Ah (5.12 kWh) | E103: BCT-V-24-200, 614x507x212 mm | F103: pc | G103: pc | H103: 38000 | I103: =INDEX(SUPPLIERS!$D$3:$D$30,MATCH(C103,SUPPLIERS!$A$3:$A$30,0)) -> 0 | J103: =H103*(1-I103) -> 38000 | K103: 5.12 | L103: kWh | M103: =IF(K103="","",J103/K103) -> 7421.875 | N103: 48 | O103: 0.15469 | P103: Volume: datasheet package; weight Est. | Q103: =MAX(N103/DRIVERS!$B$5,O103/DRIVERS!$B$6) -> 0.016 | R103: =ROUNDDOWN(1/Q103,0) -> 62 | S103: =DRIVERS!$B$23*Q103/DRIVERS!$B$24 -> 83.054813 | T103: =J103*INDEX(DRIVERS!$C$32:$C$42,MATCH(B103,DRIVERS!$A$32:$A$42,0)) -> 0 | U103: =J103*INDEX(SUPPLIERS!$E$3:$E$30,MATCH(C103,SUPPLIERS!$A$3:$A$30,0)) -> 0 | V103: 0 | W103: =J103+S103+T103+U103+V103 -> 38083.055 | X103: =W103/J103-1 -> 0.002185653 | Y103: =INDEX(DRIVERS!$B$32:$B$42,MATCH(B103,DRIVERS!$A$32:$A$42,0)) -> 0.15 | Z103: =W103*(1+Y103) -> 43795.513 | AA103: =W103*(1+Y103+DRIVERS!$B$26)*(1+DRIVERS!$B$27) -> 51183.626 | AB103: Sep 19, 2026 | AC103: 38000 | AD103: 24V systems only
A104: BC-BAT-002 | B104: Battery | C104: Blue Carbon | D104: LiFePO4 51.2V 100Ah smart BMS (5.12 kWh) | E104: SMART-BCT-V-48-100 | F104: pc | G104: pc | H104: 44000 | I104: =INDEX(SUPPLIERS!$D$3:$D$30,MATCH(C104,SUPPLIERS!$A$3:$A$30,0)) -> 0 | J104: =H104*(1-I104) -> 44000 | K104: 5.12 | L104: kWh | M104: =IF(K104="","",J104/K104) -> 8593.75 | N104: 48 | O104: 0.155 | P104: Est. (datasheet not received) | Q104: =MAX(N104/DRIVERS!$B$5,O104/DRIVERS!$B$6) -> 0.016 | R104: =ROUNDDOWN(1/Q104,0) -> 62 | S104: =DRIVERS!$B$23*Q104/DRIVERS!$B$24 -> 83.054813 | T104: =J104*INDEX(DRIVERS!$C$32:$C$42,MATCH(B104,DRIVERS!$A$32:$A$42,0)) -> 0 | U104: =J104*INDEX(SUPPLIERS!$E$3:$E$30,MATCH(C104,SUPPLIERS!$A$3:$A$30,0)) -> 0 | V104: 0 | W104: =J104+S104+T104+U104+V104 -> 44083.055 | X104: =W104/J104-1 -> 0.0018876094 | Y104: =INDEX(DRIVERS!$B$32:$B$42,MATCH(B104,DRIVERS!$A$32:$A$42,0)) -> 0.15 | Z104: =W104*(1+Y104) -> 50695.513 | AA104: =W104*(1+Y104+DRIVERS!$B$26)*(1+DRIVERS!$B$27) -> 59247.626 | AB104: Sep 19, 2026 | AC104: 44000
A105: BC-BAT-003 | B105: Battery | C105: Blue Carbon | D105: LiFePO4 51.2V 200Ah smart BMS (10.24 kWh) | E105: SMART-BCT-V-48-200(P), 1218x507x212 mm | F105: pc | G105: pc | H105: 82000 | I105: =INDEX(SUPPLIERS!$D$3:$D$30,MATCH(C105,SUPPLIERS!$A$3:$A$30,0)) -> 0 | J105: =H105*(1-I105) -> 82000 | K105: 10.24 | L105: kWh | M105: =IF(K105="","",J105/K105) -> 8007.8125 | N105: 95 | O105: 0.29543 | P105: Volume: datasheet package; weight Est. | Q105: =MAX(N105/DRIVERS!$B$5,O105/DRIVERS!$B$6) -> 0.031666667 | R105: =ROUNDDOWN(1/Q105,0) -> 31 | S105: =DRIVERS!$B$23*Q105/DRIVERS!$B$24 -> 164.37932 | T105: =J105*INDEX(DRIVERS!$C$32:$C$42,MATCH(B105,DRIVERS!$A$32:$A$42,0)) -> 0 | U105: =J105*INDEX(SUPPLIERS!$E$3:$E$30,MATCH(C105,SUPPLIERS!$A$3:$A$30,0)) -> 0 | V105: 0 | W105: =J105+S105+T105+U105+V105 -> 82164.379 | X105: =W105/J105-1 -> 0.0020046258 | Y105: =INDEX(DRIVERS!$B$32:$B$42,MATCH(B105,DRIVERS!$A$32:$A$42,0)) -> 0.15 | Z105: =W105*(1+Y105) -> 94489.036 | AA105: =W105*(1+Y105+DRIVERS!$B$26)*(1+DRIVERS!$B$27) -> 110428.93 | AB105: Sep 19, 2026 | AC105: 82000 | AD105: CHECK: continuous current 100A on the 200P datasheet (about 5 kW), 120A on the combined sheet. Warranty 5 yrs (datasheet) vs 10 yrs (price list)
A106: BC-BAT-004 | B106: Battery | C106: Blue Carbon | D106: LiFePO4 51.2V 300Ah smart BMS (15.36 kWh) | E106: SMART-BCT-V-48-300(P), 1218x507x212 mm | F106: pc | G106: pc | H106: 93000 | I106: =INDEX(SUPPLIERS!$D$3:$D$30,MATCH(C106,SUPPLIERS!$A$3:$A$30,0)) -> 0 | J106: =H106*(1-I106) -> 93000 | K106: 15.36 | L106: kWh | M106: =IF(K106="","",J106/K106) -> 6054.6875 | N106: 130 | O106: 0.29543 | P106: Volume: datasheet package; weight Est. | Q106: =MAX(N106/DRIVERS!$B$5,O106/DRIVERS!$B$6) -> 0.043333333 | R106: =ROUNDDOWN(1/Q106,0) -> 23 | S106: =DRIVERS!$B$23*Q106/DRIVERS!$B$24 -> 224.94012 | T106: =J106*INDEX(DRIVERS!$C$32:$C$42,MATCH(B106,DRIVERS!$A$32:$A$42,0)) -> 0 | U106: =J106*INDEX(SUPPLIERS!$E$3:$E$30,MATCH(C106,SUPPLIERS!$A$3:$A$30,0)) -> 0 | V106: 0 | W106: =J106+S106+T106+U106+V106 -> 93224.94 | X106: =W106/J106-1 -> 0.002418711 | Y106: =INDEX(DRIVERS!$B$32:$B$42,MATCH(B106,DRIVERS!$A$32:$A$42,0)) -> 0.15 | Z106: =W106*(1+Y106) -> 107208.68 | AA106: =W106*(1+Y106+DRIVERS!$B$26)*(1+DRIVERS!$B$27) -> 125294.32 | AB106: Sep 19, 2026 | AC106: 93000 | AD106: CHECK: continuous current 100A (about 5 kW) - an 8-12 kW inverter needs 2 or more packs in parallel to run at full power from the battery. Cheapest per kWh on this list
A107: FS-BAT-001 | B107: Battery | C107: Felicity Solar | D107: LiFePO4 51.2V 100Ah (5.12 kWh), FLA wall/floor | E107: FLA48100, 663x400x178 mm | F107: pc | G107: pc | H107: 43000 | I107: =INDEX(SUPPLIERS!$D$3:$D$30,MATCH(C107,SUPPLIERS!$A$3:$A$30,0)) -> 0 | J107: =H107*(1-I107) -> 43000 | K107: 5.12 | L107: kWh | M107: =IF(K107="","",J107/K107) -> 8398.4375 | N107: 55 | O107: 0.10695 | P107: Brochure: package | Q107: =MAX(N107/DRIVERS!$B$5,O107/DRIVERS!$B$6) -> 0.018333333 | R107: =ROUNDDOWN(1/Q107,0) -> 54 | S107: =DRIVERS!$B$23*Q107/DRIVERS!$B$24 -> 95.166974 | T107: =J107*INDEX(DRIVERS!$C$32:$C$42,MATCH(B107,DRIVERS!$A$32:$A$42,0)) -> 0 | U107: =J107*INDEX(SUPPLIERS!$E$3:$E$30,MATCH(C107,SUPPLIERS!$A$3:$A$30,0)) -> 0 | V107: 0 | W107: =J107+S107+T107+U107+V107 -> 43095.167 | X107: =W107/J107-1 -> 0.0022131854 | Y107: =INDEX(DRIVERS!$B$32:$B$42,MATCH(B107,DRIVERS!$A$32:$A$42,0)) -> 0.15 | Z107: =W107*(1+Y107) -> 49559.442 | AA107: =W107*(1+Y107+DRIVERS!$B$26)*(1+DRIVERS!$B$27) -> 57919.904 | AB107: September 2026 | AD107: Continuous 100A (5 kW). 7-yr warranty
A108: FS-BAT-002 | B108: Battery | C108: Felicity Solar | D108: LiFePO4 51.2V 200Ah (10 kWh), FLA wall/floor | E108: FLA48200, 735x433x188 mm | F108: pc | G108: pc | H108: 71000 | I108: =INDEX(SUPPLIERS!$D$3:$D$30,MATCH(C108,SUPPLIERS!$A$3:$A$30,0)) -> 0 | J108: =H108*(1-I108) -> 71000 | K108: 10 | L108: kWh | M108: =IF(K108="","",J108/K108) -> 7100 | N108: 88 | O108: 0.16904 | P108: Brochure: package | Q108: =MAX(N108/DRIVERS!$B$5,O108/DRIVERS!$B$6) -> 0.029333333 | R108: =ROUNDDOWN(1/Q108,0) -> 34 | S108: =DRIVERS!$B$23*Q108/DRIVERS!$B$24 -> 152.26716 | T108: =J108*INDEX(DRIVERS!$C$32:$C$42,MATCH(B108,DRIVERS!$A$32:$A$42,0)) -> 0 | U108: =J108*INDEX(SUPPLIERS!$E$3:$E$30,MATCH(C108,SUPPLIERS!$A$3:$A$30,0)) -> 0 | V108: 0 | W108: =J108+S108+T108+U108+V108 -> 71152.267 | X108: =W108/J108-1 -> 0.0021446079 | Y108: =INDEX(DRIVERS!$B$32:$B$42,MATCH(B108,DRIVERS!$A$32:$A$42,0)) -> 0.15 | Z108: =W108*(1+Y108) -> 81825.107 | AA108: =W108*(1+Y108+DRIVERS!$B$26)*(1+DRIVERS!$B$27) -> 95628.647 | AB108: September 2026 | AD108: 10 kWh per brochure (list says "10KW"). Continuous 120A (6 kW). 7-yr warranty
A109: FS-BAT-003 | B109: Battery | C109: Felicity Solar | D109: LiFePO4 51.2V 300Ah (15 kWh), FLA floor | E109: FLA48300 (brochure FLA48300TG2), 435x880x247 mm | F109: pc | G109: pc | H109: 97000 | I109: =INDEX(SUPPLIERS!$D$3:$D$30,MATCH(C109,SUPPLIERS!$A$3:$A$30,0)) -> 0 | J109: =H109*(1-I109) -> 97000 | K109: 15 | L109: kWh | M109: =IF(K109="","",J109/K109) -> 6466.6667 | N109: 140.5 | O109: 0.23976 | P109: Brochure: package | Q109: =MAX(N109/DRIVERS!$B$5,O109/DRIVERS!$B$6) -> 0.046833333 | R109: =ROUNDDOWN(1/Q109,0) -> 21 | S109: =DRIVERS!$B$23*Q109/DRIVERS!$B$24 -> 243.10836 | T109: =J109*INDEX(DRIVERS!$C$32:$C$42,MATCH(B109,DRIVERS!$A$32:$A$42,0)) -> 0 | U109: =J109*INDEX(SUPPLIERS!$E$3:$E$30,MATCH(C109,SUPPLIERS!$A$3:$A$30,0)) -> 0 | V109: 0 | W109: =J109+S109+T109+U109+V109 -> 97243.108 | X109: =W109/J109-1 -> 0.0025062717 | Y109: =INDEX(DRIVERS!$B$32:$B$42,MATCH(B109,DRIVERS!$A$32:$A$42,0)) -> 0.15 | Z109: =W109*(1+Y109) -> 111829.57 | AA109: =W109*(1+Y109+DRIVERS!$B$26)*(1+DRIVERS!$B$27) -> 130694.74 | AB109: September 2026 | AD109: 15 kWh (list says "15KW"). Continuous 160A (8 kW). 7-yr warranty
A110: FS-BAT-004 | B110: Battery | C110: Felicity Solar | D110: LiFePO4 51.2V 500Ah (25 kWh), FLA floor | E110: FLA48500 (brochure FLA48500TG2), 570x250x980 mm | F110: pc | G110: pc | H110: 174000 | I110: =INDEX(SUPPLIERS!$D$3:$D$30,MATCH(C110,SUPPLIERS!$A$3:$A$30,0)) -> 0 | J110: =H110*(1-I110) -> 174000 | K110: 25 | L110: kWh | M110: =IF(K110="","",J110/K110) -> 6960 | N110: 219.5 | O110: 0.36416 | P110: Brochure: package | Q110: =MAX(N110/DRIVERS!$B$5,O110/DRIVERS!$B$6) -> 0.073166667 | R110: =ROUNDDOWN(1/Q110,0) -> 13 | S110: =DRIVERS!$B$23*Q110/DRIVERS!$B$24 -> 379.80274 | T110: =J110*INDEX(DRIVERS!$C$32:$C$42,MATCH(B110,DRIVERS!$A$32:$A$42,0)) -> 0 | U110: =J110*INDEX(SUPPLIERS!$E$3:$E$30,MATCH(C110,SUPPLIERS!$A$3:$A$30,0)) -> 0 | V110: 0 | W110: =J110+S110+T110+U110+V110 -> 174379.8 | X110: =W110/J110-1 -> 0.0021827744 | Y110: =INDEX(DRIVERS!$B$32:$B$42,MATCH(B110,DRIVERS!$A$32:$A$42,0)) -> 0.15 | Z110: =W110*(1+Y110) -> 200536.77 | AA110: =W110*(1+Y110+DRIVERS!$B$26)*(1+DRIVERS!$B$27) -> 234366.45 | AB110: September 2026 | AD110: 25 kWh (list says "25KW"). Continuous 250A (12.5 kW). 7-yr warranty
A111: FS-BAT-005 | B111: Battery | C111: Felicity Solar | D111: LiFePO4 51.2V 100Ah (5.12 kWh), FLB IP65 | E111: FLB48100WG1, 650x450x174 mm | F111: pc | G111: pc | H111: 46000 | I111: =INDEX(SUPPLIERS!$D$3:$D$30,MATCH(C111,SUPPLIERS!$A$3:$A$30,0)) -> 0 | J111: =H111*(1-I111) -> 46000 | K111: 5.12 | L111: kWh | M111: =IF(K111="","",J111/K111) -> 8984.375 | N111: 53 | O111: 0.10502 | P111: Brochure: package | Q111: =MAX(N111/DRIVERS!$B$5,O111/DRIVERS!$B$6) -> 0.017666667 | R111: =ROUNDDOWN(1/Q111,0) -> 56 | S111: =DRIVERS!$B$23*Q111/DRIVERS!$B$24 -> 91.706356 | T111: =J111*INDEX(DRIVERS!$C$32:$C$42,MATCH(B111,DRIVERS!$A$32:$A$42,0)) -> 0 | U111: =J111*INDEX(SUPPLIERS!$E$3:$E$30,MATCH(C111,SUPPLIERS!$A$3:$A$30,0)) -> 0 | V111: 0 | W111: =J111+S111+T111+U111+V111 -> 46091.706 | X111: =W111/J111-1 -> 0.0019936164 | Y111: =INDEX(DRIVERS!$B$32:$B$42,MATCH(B111,DRIVERS!$A$32:$A$42,0)) -> 0.15 | Z111: =W111*(1+Y111) -> 53005.462 | AA111: =W111*(1+Y111+DRIVERS!$B$26)*(1+DRIVERS!$B$27) -> 61947.253 | AB111: September 2026 | AD111: Continuous 100A. IP65. 10-yr warranty
A112: FS-BAT-006 | B112: Battery | C112: Felicity Solar | D112: LiFePO4 51.2V 230Ah (11.7 kWh), FLB IP65 | E112: FLB48230WG1, 683x450x258 mm | F112: pc | G112: pc | H112: 87000 | I112: =INDEX(SUPPLIERS!$D$3:$D$30,MATCH(C112,SUPPLIERS!$A$3:$A$30,0)) -> 0 | J112: =H112*(1-I112) -> 87000 | K112: 11.7 | L112: kWh | M112: =IF(K112="","",J112/K112) -> 7435.8974 | N112: 111 | O112: 0.18674 | P112: Brochure: package | Q112: =MAX(N112/DRIVERS!$B$5,O112/DRIVERS!$B$6) -> 0.037 | R112: =ROUNDDOWN(1/Q112,0) -> 27 | S112: =DRIVERS!$B$23*Q112/DRIVERS!$B$24 -> 192.06426 | T112: =J112*INDEX(DRIVERS!$C$32:$C$42,MATCH(B112,DRIVERS!$A$32:$A$42,0)) -> 0 | U112: =J112*INDEX(SUPPLIERS!$E$3:$E$30,MATCH(C112,SUPPLIERS!$A$3:$A$30,0)) -> 0 | V112: 0 | W112: =J112+S112+T112+U112+V112 -> 87192.064 | X112: =W112/J112-1 -> 0.0022076351 | Y112: =INDEX(DRIVERS!$B$32:$B$42,MATCH(B112,DRIVERS!$A$32:$A$42,0)) -> 0.15 | Z112: =W112*(1+Y112) -> 100270.87 | AA112: =W112*(1+Y112+DRIVERS!$B$26)*(1+DRIVERS!$B$27) -> 117186.13 | AB112: September 2026 | AD112: Continuous 150A (7.7 kW). IP65. 10-yr warranty. Closest match to the 11.8 kWh battery in the packages
A113: FS-BAT-007 | B113: Battery | C113: Felicity Solar | D113: LiFePO4 51.2V 314Ah (16 kWh), FLB IP65 | E113: FLB48314TG1, 895x450x235 mm | F113: pc | G113: pc | H113: 108000 | I113: =INDEX(SUPPLIERS!$D$3:$D$30,MATCH(C113,SUPPLIERS!$A$3:$A$30,0)) -> 0 | J113: =H113*(1-I113) -> 108000 | K113: 16 | L113: kWh | M113: =IF(K113="","",J113/K113) -> 6750 | N113: 143 | O113: 0.22259 | P113: Brochure: package | Q113: =MAX(N113/DRIVERS!$B$5,O113/DRIVERS!$B$6) -> 0.047666667 | R113: =ROUNDDOWN(1/Q113,0) -> 20 | S113: =DRIVERS!$B$23*Q113/DRIVERS!$B$24 -> 247.43413 | T113: =J113*INDEX(DRIVERS!$C$32:$C$42,MATCH(B113,DRIVERS!$A$32:$A$42,0)) -> 0 | U113: =J113*INDEX(SUPPLIERS!$E$3:$E$30,MATCH(C113,SUPPLIERS!$A$3:$A$30,0)) -> 0 | V113: 0 | W113: =J113+S113+T113+U113+V113 -> 108247.43 | X113: =W113/J113-1 -> 0.0022910568 | Y113: =INDEX(DRIVERS!$B$32:$B$42,MATCH(B113,DRIVERS!$A$32:$A$42,0)) -> 0.15 | Z113: =W113*(1+Y113) -> 124484.55 | AA113: =W113*(1+Y113+DRIVERS!$B$26)*(1+DRIVERS!$B$27) -> 145484.55 | AB113: September 2026 | AD113: Continuous 160A (8 kW). IP65, 8,000 cycles. 10-yr warranty
A114: FS-BAT-008 | B114: Battery | C114: Felicity Solar | D114: High-voltage battery controller module, 51.2V 100Ah | E114: FLH48100UCG2, 482.6x565x150 mm | F114: pc | G114: pc | H114: 40000 | I114: =INDEX(SUPPLIERS!$D$3:$D$30,MATCH(C114,SUPPLIERS!$A$3:$A$30,0)) -> 0 | J114: =H114*(1-I114) -> 40000 | K114: 5.12 | L114: kWh | M114: =IF(K114="","",J114/K114) -> 7812.5 | N114: 24.7 | O114: 0.10386 | P114: Brochure: package | Q114: =MAX(N114/DRIVERS!$B$5,O114/DRIVERS!$B$6) -> 0.0082333333 | R114: =ROUNDDOWN(1/Q114,0) -> 121 | S114: =DRIVERS!$B$23*Q114/DRIVERS!$B$24 -> 42.738623 | T114: =J114*INDEX(DRIVERS!$C$32:$C$42,MATCH(B114,DRIVERS!$A$32:$A$42,0)) -> 0 | U114: =J114*INDEX(SUPPLIERS!$E$3:$E$30,MATCH(C114,SUPPLIERS!$A$3:$A$30,0)) -> 0 | V114: 0 | W114: =J114+S114+T114+U114+V114 -> 40042.739 | X114: =W114/J114-1 -> 0.0010684656 | Y114: =INDEX(DRIVERS!$B$32:$B$42,MATCH(B114,DRIVERS!$A$32:$A$42,0)) -> 0.15 | Z114: =W114*(1+Y114) -> 46049.149 | AA114: =W114*(1+Y114+DRIVERS!$B$26)*(1+DRIVERS!$B$27) -> 53817.441 | AB114: September 2026 | AD114: For the 50 kW high-voltage system (5-16 modules in series). 10-yr warranty
A115: FS-BAT-009 | B115: Battery | C115: Felicity Solar | D115: High-voltage battery module (slave), 51.2V 100Ah | E115: FLH48100UMG2, 482.6x565x133 mm | F115: pc | G115: pc | H115: 42000 | I115: =INDEX(SUPPLIERS!$D$3:$D$30,MATCH(C115,SUPPLIERS!$A$3:$A$30,0)) -> 0 | J115: =H115*(1-I115) -> 42000 | K115: 5.12 | L115: kWh | M115: =IF(K115="","",J115/K115) -> 8203.125 | N115: 46 | O115: 0.09652 | P115: Brochure: package | Q115: =MAX(N115/DRIVERS!$B$5,O115/DRIVERS!$B$6) -> 0.015333333 | R115: =ROUNDDOWN(1/Q115,0) -> 65 | S115: =DRIVERS!$B$23*Q115/DRIVERS!$B$24 -> 79.594196 | T115: =J115*INDEX(DRIVERS!$C$32:$C$42,MATCH(B115,DRIVERS!$A$32:$A$42,0)) -> 0 | U115: =J115*INDEX(SUPPLIERS!$E$3:$E$30,MATCH(C115,SUPPLIERS!$A$3:$A$30,0)) -> 0 | V115: 0 | W115: =J115+S115+T115+U115+V115 -> 42079.594 | X115: =W115/J115-1 -> 0.0018950999 | Y115: =INDEX(DRIVERS!$B$32:$B$42,MATCH(B115,DRIVERS!$A$32:$A$42,0)) -> 0.15 | Z115: =W115*(1+Y115) -> 48391.533 | AA115: =W115*(1+Y115+DRIVERS!$B$26)*(1+DRIVERS!$B$27) -> 56554.975 | AB115: September 2026 | AD115: 10-yr warranty
A116: FS-BAT-010 | B116: Battery | C116: Felicity Solar | D116: Battery rack, 13-tier (high-voltage) | E116: FLH48100 13-tier rack, 590x532x2088 mm | F116: pc | G116: pc | H116: 16000 | I116: =INDEX(SUPPLIERS!$D$3:$D$30,MATCH(C116,SUPPLIERS!$A$3:$A$30,0)) -> 0 | J116: =H116*(1-I116) -> 16000 | M116: =IF(K116="","",J116/K116) | N116: 57 | O116: 0.19647 | P116: Brochure: package | Q116: =MAX(N116/DRIVERS!$B$5,O116/DRIVERS!$B$6) -> 0.019 | R116: =ROUNDDOWN(1/Q116,0) -> 52 | S116: =DRIVERS!$B$23*Q116/DRIVERS!$B$24 -> 98.627591 | T116: =J116*INDEX(DRIVERS!$C$32:$C$42,MATCH(B116,DRIVERS!$A$32:$A$42,0)) -> 0 | U116: =J116*INDEX(SUPPLIERS!$E$3:$E$30,MATCH(C116,SUPPLIERS!$A$3:$A$30,0)) -> 0 | V116: 0 | W116: =J116+S116+T116+U116+V116 -> 16098.628 | X116: =W116/J116-1 -> 0.0061642244 | Y116: =INDEX(DRIVERS!$B$32:$B$42,MATCH(B116,DRIVERS!$A$32:$A$42,0)) -> 0.15 | Z116: =W116*(1+Y116) -> 18513.422 | AA116: =W116*(1+Y116+DRIVERS!$B$26)*(1+DRIVERS!$B$27) -> 21636.555 | AB116: September 2026 | AD116: Sheet metal; not covered by warranty. Priced in the battery tier as part of the battery system
A117: FS-BAT-011 | B117: Battery | C117: Felicity Solar | D117: Battery rack, 9-tier (high-voltage) | E117: FLH48100 9-tier rack, 590x532x1516 mm | F117: pc | G117: pc | H117: 13000 | I117: =INDEX(SUPPLIERS!$D$3:$D$30,MATCH(C117,SUPPLIERS!$A$3:$A$30,0)) -> 0 | J117: =H117*(1-I117) -> 13000 | M117: =IF(K117="","",J117/K117) | N117: 43.2 | O117: 0.14461 | P117: Brochure: package | Q117: =MAX(N117/DRIVERS!$B$5,O117/DRIVERS!$B$6) -> 0.0144 | R117: =ROUNDDOWN(1/Q117,0) -> 69 | S117: =DRIVERS!$B$23*Q117/DRIVERS!$B$24 -> 74.749332 | T117: =J117*INDEX(DRIVERS!$C$32:$C$42,MATCH(B117,DRIVERS!$A$32:$A$42,0)) -> 0 | U117: =J117*INDEX(SUPPLIERS!$E$3:$E$30,MATCH(C117,SUPPLIERS!$A$3:$A$30,0)) -> 0 | V117: 0 | W117: =J117+S117+T117+U117+V117 -> 13074.749 | X117: =W117/J117-1 -> 0.0057499486 | Y117: =INDEX(DRIVERS!$B$32:$B$42,MATCH(B117,DRIVERS!$A$32:$A$42,0)) -> 0.15 | Z117: =W117*(1+Y117) -> 15035.962 | AA117: =W117*(1+Y117+DRIVERS!$B$26)*(1+DRIVERS!$B$27) -> 17572.463 | AB117: September 2026 | AD117: Sheet metal; not covered by warranty
A118: IAN-BAT-001 | B118: Battery | C118: IAN Solar | D118: PYLONTECH RV12200 12V 200AH | E118: Pylontech; 12 V; 200 Ah; 2.4 kWh | F118: pc | G118: pc | H118: 21000 | I118: =INDEX(SUPPLIERS!$D$3:$D$30,MATCH(C118,SUPPLIERS!$A$3:$A$30,0)) -> 0 | J118: =H118*(1-I118) -> 21000 | K118: 2.4 | L118: kWh | M118: =IF(K118="","",J118/K118) -> 8750 | N118: 23 | O118: 0.03996 | P118: List: gross weight, packaging size | Q118: =MAX(N118/DRIVERS!$B$5,O118/DRIVERS!$B$6) -> 0.0076666667 | R118: =ROUNDDOWN(1/Q118,0) -> 130 | S118: =DRIVERS!$B$23*Q118/DRIVERS!$B$24 -> 39.797098 | T118: =J118*INDEX(DRIVERS!$C$32:$C$42,MATCH(B118,DRIVERS!$A$32:$A$42,0)) -> 0 | U118: =J118*INDEX(SUPPLIERS!$E$3:$E$30,MATCH(C118,SUPPLIERS!$A$3:$A$30,0)) -> 0 | V118: 0 | W118: =J118+S118+T118+U118+V118 -> 21039.797 | X118: =W118/J118-1 -> 0.0018950999 | Y118: =INDEX(DRIVERS!$B$32:$B$42,MATCH(B118,DRIVERS!$A$32:$A$42,0)) -> 0.15 | Z118: =W118*(1+Y118) -> 24195.767 | AA118: =W118*(1+Y118+DRIVERS!$B$26)*(1+DRIVERS!$B$27) -> 28277.487 | AB118: Sep 3, 2026
A119: IAN-BAT-002 | B119: Battery | C119: IAN Solar | D119: DYNESS POWERBRICK SC 51.2V 314AH 16.076kWh IP20 SCREEN | E119: Dyness; 51.2 V; 314 Ah; 16.076 kWh; IP20 | F119: pc | G119: pc | H119: 111000 | I119: =INDEX(SUPPLIERS!$D$3:$D$30,MATCH(C119,SUPPLIERS!$A$3:$A$30,0)) -> 0 | J119: =H119*(1-I119) -> 111000 | K119: 16.076 | L119: kWh | M119: =IF(K119="","",J119/K119) -> 6904.7027 | N119: 125 | O119: 0.17103 | P119: List: gross weight, packaging size | Q119: =MAX(N119/DRIVERS!$B$5,O119/DRIVERS!$B$6) -> 0.041666667 | R119: =ROUNDDOWN(1/Q119,0) -> 24 | S119: =DRIVERS!$B$23*Q119/DRIVERS!$B$24 -> 216.28858 | T119: =J119*INDEX(DRIVERS!$C$32:$C$42,MATCH(B119,DRIVERS!$A$32:$A$42,0)) -> 0 | U119: =J119*INDEX(SUPPLIERS!$E$3:$E$30,MATCH(C119,SUPPLIERS!$A$3:$A$30,0)) -> 0 | V119: 0 | W119: =J119+S119+T119+U119+V119 -> 111216.29 | X119: =W119/J119-1 -> 0.0019485457 | Y119: =INDEX(DRIVERS!$B$32:$B$42,MATCH(B119,DRIVERS!$A$32:$A$42,0)) -> 0.15 | Z119: =W119*(1+Y119) -> 127898.73 | AA119: =W119*(1+Y119+DRIVERS!$B$26)*(1+DRIVERS!$B$27) -> 149474.69 | AB119: Sep 3, 2026
A120: IAN-BAT-003 | B120: Battery | C120: IAN Solar | D120: DYNESS POWERBRICK MAX 51.2V 314AH 16.076kWh IP20 | E120: Dyness; 51.2 V; 314 Ah; 16.076 kWh; IP20 | F120: pc | G120: pc | H120: 111000 | I120: =INDEX(SUPPLIERS!$D$3:$D$30,MATCH(C120,SUPPLIERS!$A$3:$A$30,0)) -> 0 | J120: =H120*(1-I120) -> 111000 | K120: 16.076 | L120: kWh | M120: =IF(K120="","",J120/K120) -> 6904.7027 | N120: 135 | O120: 0.20212 | P120: List: gross weight, packaging size | Q120: =MAX(N120/DRIVERS!$B$5,O120/DRIVERS!$B$6) -> 0.045 | R120: =ROUNDDOWN(1/Q120,0) -> 22 | S120: =DRIVERS!$B$23*Q120/DRIVERS!$B$24 -> 233.59166 | T120: =J120*INDEX(DRIVERS!$C$32:$C$42,MATCH(B120,DRIVERS!$A$32:$A$42,0)) -> 0 | U120: =J120*INDEX(SUPPLIERS!$E$3:$E$30,MATCH(C120,SUPPLIERS!$A$3:$A$30,0)) -> 0 | V120: 0 | W120: =J120+S120+T120+U120+V120 -> 111233.59 | X120: =W120/J120-1 -> 0.0021044294 | Y120: =INDEX(DRIVERS!$B$32:$B$42,MATCH(B120,DRIVERS!$A$32:$A$42,0)) -> 0.15 | Z120: =W120*(1+Y120) -> 127918.63 | AA120: =W120*(1+Y120+DRIVERS!$B$26)*(1+DRIVERS!$B$27) -> 149497.95 | AB120: Sep 3, 2026
A121: IAN-BAT-004 | B121: Battery | C121: IAN Solar | D121: PYLONTECH FIDUS PLUS FB-L-16-0110 16kWh IP65 | E121: Pylontech; 16 kWh; IP65 | F121: pc | G121: pc | H121: 113000 | I121: =INDEX(SUPPLIERS!$D$3:$D$30,MATCH(C121,SUPPLIERS!$A$3:$A$30,0)) -> 0 | J121: =H121*(1-I121) -> 113000 | K121: 16 | L121: kWh | M121: =IF(K121="","",J121/K121) -> 7062.5 | N121: 145 | O121: 0.21945 | P121: List: gross weight, packaging size | Q121: =MAX(N121/DRIVERS!$B$5,O121/DRIVERS!$B$6) -> 0.048333333 | R121: =ROUNDDOWN(1/Q121,0) -> 20 | S121: =DRIVERS!$B$23*Q121/DRIVERS!$B$24 -> 250.89475 | T121: =J121*INDEX(DRIVERS!$C$32:$C$42,MATCH(B121,DRIVERS!$A$32:$A$42,0)) -> 0 | U121: =J121*INDEX(SUPPLIERS!$E$3:$E$30,MATCH(C121,SUPPLIERS!$A$3:$A$30,0)) -> 0 | V121: 0 | W121: =J121+S121+T121+U121+V121 -> 113250.89 | X121: =W121/J121-1 -> 0.0022203075 | Y121: =INDEX(DRIVERS!$B$32:$B$42,MATCH(B121,DRIVERS!$A$32:$A$42,0)) -> 0.15 | Z121: =W121*(1+Y121) -> 130238.53 | AA121: =W121*(1+Y121+DRIVERS!$B$26)*(1+DRIVERS!$B$27) -> 152209.2 | AB121: Sep 3, 2026
A122: IAN-BAT-005 | B122: Battery | C122: IAN Solar | D122: DYNESS POWERBRICK PLUS 51.2V 314AH 16.076kWh IP65 | E122: Dyness; 51.2 V; 314 Ah; 16.076 kWh; IP65 | F122: pc | G122: pc | H122: 115000 | I122: =INDEX(SUPPLIERS!$D$3:$D$30,MATCH(C122,SUPPLIERS!$A$3:$A$30,0)) -> 0 | J122: =H122*(1-I122) -> 115000 | K122: 16.076 | L122: kWh | M122: =IF(K122="","",J122/K122) -> 7153.5208 | N122: 132 | O122: 0.1749 | P122: List: gross weight, packaging size | Q122: =MAX(N122/DRIVERS!$B$5,O122/DRIVERS!$B$6) -> 0.044 | R122: =ROUNDDOWN(1/Q122,0) -> 22 | S122: =DRIVERS!$B$23*Q122/DRIVERS!$B$24 -> 228.40074 | T122: =J122*INDEX(DRIVERS!$C$32:$C$42,MATCH(B122,DRIVERS!$A$32:$A$42,0)) -> 0 | U122: =J122*INDEX(SUPPLIERS!$E$3:$E$30,MATCH(C122,SUPPLIERS!$A$3:$A$30,0)) -> 0 | V122: 0 | W122: =J122+S122+T122+U122+V122 -> 115228.4 | X122: =W122/J122-1 -> 0.0019860934 | Y122: =INDEX(DRIVERS!$B$32:$B$42,MATCH(B122,DRIVERS!$A$32:$A$42,0)) -> 0.15 | Z122: =W122*(1+Y122) -> 132512.66 | AA122: =W122*(1+Y122+DRIVERS!$B$26)*(1+DRIVERS!$B$27) -> 154866.97 | AB122: Sep 3, 2026
A123: IAN-BAT-006 | B123: Battery | C123: IAN Solar | D123: PYLONTECH FB-L-5.12 51.2V 100AH 5.12kWh IP65 | E123: Pylontech; 51.2 V; 100 Ah; 5.12 kWh; IP65 | F123: pc | G123: pc | H123: 42000 | I123: =INDEX(SUPPLIERS!$D$3:$D$30,MATCH(C123,SUPPLIERS!$A$3:$A$30,0)) -> 0 | J123: =H123*(1-I123) -> 42000 | K123: 5.12 | L123: kWh | M123: =IF(K123="","",J123/K123) -> 8203.125 | N123: 50 | O123: 0.07029 | P123: List: gross weight, packaging size | Q123: =MAX(N123/DRIVERS!$B$5,O123/DRIVERS!$B$6) -> 0.016666667 | R123: =ROUNDDOWN(1/Q123,0) -> 60 | S123: =DRIVERS!$B$23*Q123/DRIVERS!$B$24 -> 86.51543 | T123: =J123*INDEX(DRIVERS!$C$32:$C$42,MATCH(B123,DRIVERS!$A$32:$A$42,0)) -> 0 | U123: =J123*INDEX(SUPPLIERS!$E$3:$E$30,MATCH(C123,SUPPLIERS!$A$3:$A$30,0)) -> 0 | V123: 0 | W123: =J123+S123+T123+U123+V123 -> 42086.515 | X123: =W123/J123-1 -> 0.0020598912 | Y123: =INDEX(DRIVERS!$B$32:$B$42,MATCH(B123,DRIVERS!$A$32:$A$42,0)) -> 0.15 | Z123: =W123*(1+Y123) -> 48399.493 | AA123: =W123*(1+Y123+DRIVERS!$B$26)*(1+DRIVERS!$B$27) -> 56564.277 | AB123: Sep 3, 2026
A124: IAN-BAT-007 | B124: Battery | C124: IAN Solar | D124: SOLIS INTELLIHOUSE 16kWh IP66 | E124: Solis; 16 kWh; IP66 | F124: pc | G124: pc | H124: 134000 | I124: =INDEX(SUPPLIERS!$D$3:$D$30,MATCH(C124,SUPPLIERS!$A$3:$A$30,0)) -> 0 | J124: =H124*(1-I124) -> 134000 | K124: 16 | L124: kWh | M124: =IF(K124="","",J124/K124) -> 8375 | N124: 130 | O124: 0.15 | P124: List: gross weight, packaging size | Q124: =MAX(N124/DRIVERS!$B$5,O124/DRIVERS!$B$6) -> 0.043333333 | R124: =ROUNDDOWN(1/Q124,0) -> 23 | S124: =DRIVERS!$B$23*Q124/DRIVERS!$B$24 -> 224.94012 | T124: =J124*INDEX(DRIVERS!$C$32:$C$42,MATCH(B124,DRIVERS!$A$32:$A$42,0)) -> 0 | U124: =J124*INDEX(SUPPLIERS!$E$3:$E$30,MATCH(C124,SUPPLIERS!$A$3:$A$30,0)) -> 0 | V124: 0 | W124: =J124+S124+T124+U124+V124 -> 134224.94 | X124: =W124/J124-1 -> 0.0016786576 | Y124: =INDEX(DRIVERS!$B$32:$B$42,MATCH(B124,DRIVERS!$A$32:$A$42,0)) -> 0.15 | Z124: =W124*(1+Y124) -> 154358.68 | AA124: =W124*(1+Y124+DRIVERS!$B$26)*(1+DRIVERS!$B$27) -> 180398.32 | AB124: Sep 3, 2026
A125: IAN-BAT-008 | B125: Battery | C125: IAN Solar | D125: DYNESS DL5.0C 51.2V 100AH IP20 | E125: Dyness; 51.2 V; 100 Ah; 5.12 kWh; IP20 | F125: pc | G125: pc | H125: 43000 | I125: =INDEX(SUPPLIERS!$D$3:$D$30,MATCH(C125,SUPPLIERS!$A$3:$A$30,0)) -> 0 | J125: =H125*(1-I125) -> 43000 | K125: 5.12 | L125: kWh | M125: =IF(K125="","",J125/K125) -> 8398.4375 | N125: 59 | O125: 0.09269 | P125: List: gross weight, packaging size | Q125: =MAX(N125/DRIVERS!$B$5,O125/DRIVERS!$B$6) -> 0.019666667 | R125: =ROUNDDOWN(1/Q125,0) -> 50 | S125: =DRIVERS!$B$23*Q125/DRIVERS!$B$24 -> 102.08821 | T125: =J125*INDEX(DRIVERS!$C$32:$C$42,MATCH(B125,DRIVERS!$A$32:$A$42,0)) -> 0 | U125: =J125*INDEX(SUPPLIERS!$E$3:$E$30,MATCH(C125,SUPPLIERS!$A$3:$A$30,0)) -> 0 | V125: 0 | W125: =J125+S125+T125+U125+V125 -> 43102.088 | X125: =W125/J125-1 -> 0.0023741444 | Y125: =INDEX(DRIVERS!$B$32:$B$42,MATCH(B125,DRIVERS!$A$32:$A$42,0)) -> 0.15 | Z125: =W125*(1+Y125) -> 49567.401 | AA125: =W125*(1+Y125+DRIVERS!$B$26)*(1+DRIVERS!$B$27) -> 57929.207 | AB125: Sep 3, 2026
A126: IAN-BAT-009 | B126: Battery | C126: IAN Solar | D126: DYNESS DL5.0F 51.2V 100AH IP20 | E126: Dyness; 51.2 V; 100 Ah; 5.12 kWh; IP20 | F126: pc | G126: pc | H126: 43000 | I126: =INDEX(SUPPLIERS!$D$3:$D$30,MATCH(C126,SUPPLIERS!$A$3:$A$30,0)) -> 0 | J126: =H126*(1-I126) -> 43000 | K126: 5.12 | L126: kWh | M126: =IF(K126="","",J126/K126) -> 8398.4375 | N126: 45 | O126: 0.06553 | P126: List: gross weight, packaging size | Q126: =MAX(N126/DRIVERS!$B$5,O126/DRIVERS!$B$6) -> 0.015 | R126: =ROUNDDOWN(1/Q126,0) -> 66 | S126: =DRIVERS!$B$23*Q126/DRIVERS!$B$24 -> 77.863887 | T126: =J126*INDEX(DRIVERS!$C$32:$C$42,MATCH(B126,DRIVERS!$A$32:$A$42,0)) -> 0 | U126: =J126*INDEX(SUPPLIERS!$E$3:$E$30,MATCH(C126,SUPPLIERS!$A$3:$A$30,0)) -> 0 | V126: 0 | W126: =J126+S126+T126+U126+V126 -> 43077.864 | X126: =W126/J126-1 -> 0.0018107881 | Y126: =INDEX(DRIVERS!$B$32:$B$42,MATCH(B126,DRIVERS!$A$32:$A$42,0)) -> 0.15 | Z126: =W126*(1+Y126) -> 49539.543 | AA126: =W126*(1+Y126+DRIVERS!$B$26)*(1+DRIVERS!$B$27) -> 57896.649 | AB126: Sep 3, 2026
A127: IAN-BAT-010 | B127: Battery | C127: IAN Solar | D127: PYLONTECH PELIO 48V 100AH | E127: Pylontech; 48 V; 100 Ah; 4.8 kWh | F127: pc | G127: pc | H127: 90000 | I127: =INDEX(SUPPLIERS!$D$3:$D$30,MATCH(C127,SUPPLIERS!$A$3:$A$30,0)) -> 0 | J127: =H127*(1-I127) -> 90000 | K127: 4.8 | L127: kWh | M127: =IF(K127="","",J127/K127) -> 18750 | N127: 50 | O127: 0.078 | P127: List: gross weight, packaging size | Q127: =MAX(N127/DRIVERS!$B$5,O127/DRIVERS!$B$6) -> 0.016666667 | R127: =ROUNDDOWN(1/Q127,0) -> 60 | S127: =DRIVERS!$B$23*Q127/DRIVERS!$B$24 -> 86.51543 | T127: =J127*INDEX(DRIVERS!$C$32:$C$42,MATCH(B127,DRIVERS!$A$32:$A$42,0)) -> 0 | U127: =J127*INDEX(SUPPLIERS!$E$3:$E$30,MATCH(C127,SUPPLIERS!$A$3:$A$30,0)) -> 0 | V127: 0 | W127: =J127+S127+T127+U127+V127 -> 90086.515 | X127: =W127/J127-1 -> 0.00096128256 | Y127: =INDEX(DRIVERS!$B$32:$B$42,MATCH(B127,DRIVERS!$A$32:$A$42,0)) -> 0.15 | Z127: =W127*(1+Y127) -> 103599.49 | AA127: =W127*(1+Y127+DRIVERS!$B$26)*(1+DRIVERS!$B$27) -> 121076.28 | AB127: Sep 3, 2026
A128: IAN-BAT-011 | B128: Battery | C128: IAN Solar | D128: PYLONTECH H32148-C HV (per kWh, min 8 modules) | E128: Pylontech; 1 kWh; 4.74 kWh/module, min 37.92 kWh | F128: kWh | G128: kWh | H128: 10000 | I128: =INDEX(SUPPLIERS!$D$3:$D$30,MATCH(C128,SUPPLIERS!$A$3:$A$30,0)) -> 0 | J128: =H128*(1-I128) -> 10000 | K128: 1 | L128: kWh | M128: =IF(K128="","",J128/K128) -> 10000 | N128: 10.9705 | O128: 0.015316 | P128: List module (4.74 kWh, 52 kg) per kWh | Q128: =MAX(N128/DRIVERS!$B$5,O128/DRIVERS!$B$6) -> 0.0036568333 | R128: =ROUNDDOWN(1/Q128,0) -> 273 | S128: =DRIVERS!$B$23*Q128/DRIVERS!$B$24 -> 18.982351 | T128: =J128*INDEX(DRIVERS!$C$32:$C$42,MATCH(B128,DRIVERS!$A$32:$A$42,0)) -> 0 | U128: =J128*INDEX(SUPPLIERS!$E$3:$E$30,MATCH(C128,SUPPLIERS!$A$3:$A$30,0)) -> 0 | V128: 0 | W128: =J128+S128+T128+U128+V128 -> 10018.982 | X128: =W128/J128-1 -> 0.0018982351 | Y128: =INDEX(DRIVERS!$B$32:$B$42,MATCH(B128,DRIVERS!$A$32:$A$42,0)) -> 0.15 | Z128: =W128*(1+Y128) -> 11521.83 | AA128: =W128*(1+Y128+DRIVERS!$B$26)*(1+DRIVERS!$B$27) -> 13465.512 | AB128: Sep 3, 2026
...

Sheet NOTES
A1: PL Development Inc. - Materials database
A2: Suppliers: Blue Carbon (Sep 19, 2026 distributor list), Felicity Solar (September 2026 list), One Point (Sep 11, 2026 Main QC list, picked up at the Alabang branch; listed as One Solar on the canvass sheet) and IAN Solar (Sep 3, 2026 list). One Point and IAN Solar sizes and weights come from the earlier canvass sheet. All four are pickup only.
A4: Landed cost = your six groups (freight is added once per job; the other five are per item)
A5: 1 Base price - supplier list price, VAT-exclusive, less any dealer discount you enter in SUPPLIERS. Take the VAT invoice (12% more): PL Dev is VAT-registered, so that 12% comes back as input VAT against the output VAT on the customer invoice. Net cost = VAT-exclusive price. Without the invoice the purchase cannot be deducted for income tax.
A6: 2 Freight - one pickup run per job in our own (shadow) truck: ownership + driver + helper per trip-day, fuel and maintenance per km, toll. Once the route is set, a trip costs the same whether the truck carries one panel or a full load, so freight is a job cost, not an item cost. The job sheet adds it as one line: trips x run cost for the suppliers that job buys from. It is NOT in the item landed cost on MATERIALS DB.
A7: 3 Handling - own crew unloading, stockpiling and moving materials to the work face (landed cost ends where the installer picks the item up).
A8: 4 Storage - zero while we buy per job. Enter a per-unit amount if an item is stocked.
A9: 5 Wastage - % of net price by category (offcuts, spares, damage).
A10: 6 Payment terms - card fees or credit charges, % of net price, per supplier.
A12: Freight and handling
A13: - Truck share per unit = the larger of (package weight / truck payload) and (package volume / cargo volume). 1 / share = how many of that item fill the truck.
A14: - Truck share does two things: (a) counts trips - a job whose items add up to more than one truck needs a second trip; (b) spreads handling, which does grow with the amount of material.
... A49: - One Point: solar water pumps and solar streetlights.

Sheet DRIVERS
A1: DRIVERS
A2: Item | B2: Value | C2: Unit | D2: Source / remarks
A3: TRUCK (shadow-owned, for pricing)
A4: Truck basis | B4: Isuzu NMR85HS closed van, 14 x 6 x 6 ft box | D4: Your pricing basis (Sep 2026)
A5: Payload | B5: 3000 | C5: kg | D5: Your figure
A6: Cargo volume | B6: =4.267*1.829*1.829 -> 14.274143 | C6: m3 | D6: 14 x 6 x 6 ft box
A7: Ownership cost per trip-day | B7: 8500 | C7: P | D7: Your computed fixed freight cost
A8: Driver per trip-day | B8: 1500 | C8: P | D8: Your figure
A9: Helper per trip-day | B9: 1000 | C9: P | D9: Your figure
A10: Diesel price | B10: 100 | C10: P/L | D10: Your basis
A11: Fuel economy, loaded | B11: 7 | C11: km/L | D11: Est. - replace with your figure
A12: Maintenance (tires, PMS) per km | B12: 3 | C12: P/km | D12: Est. - replace with your PMS table
A13: Running cost per km | B13: =B10/B11+B12 -> 17.285714 | C13: P/km | D13: Fuel + maintenance
A14: REFERENCE PICKUP RUN (Pila-area job)
A15: Route | B15: =ROUTE!B40 -> Pila > IAN Solar (Caloocan) > Felicity (Makati) > One Point (Alabang) > Blue Carbon (Santa Rosa) > Pila-area site > Pila | D15: From ROUTE: follows the suppliers the REF BASKET buys from
A16: Loop distance | B16: =ROUTE!F38 -> 235 | C16: km | D16: From ROUTE (Est. km between stops)
A17: Toll, whole run | B17: =ROUTE!G38 -> 2220 | C17: P | D17: From ROUTE (Class 2 rates on the TOLL sheet)
A18: Trip-days for the run | B18: 1 | C18: days | D18: Input. Set 2 if the stops cannot be done in one day
A19: Run cost (freight for one trip) | B19: =(B7+B8+B9)*B18+B16*B13+B17 -> 17282.143 | C19: P | D19: Ownership, driver and helper per trip-day + km x running cost + toll. Fixed per trip: the same with one panel or a full load
A20: HANDLING
A21: Helper day rate (incl. meal) | B21: 1000 | C21: P/day | D21: Your rate
A22: Handling hours, typical 6 kW job | B22: 6 | C22: helper-hours | D22: Est. - 2 helpers x 3 h: unload, stockpile, move to work face
A23: Handling cost, typical 6 kW job | B23: =B21/8*B22 -> 750 | C23: P | D23: Spread per item by truck share: more material, more handling
A24: Typical fill of the truck (from REF BASKET) | B24: ='REF BASKET'!F32 -> 0.1444829 | D24: Share of the truck a typical 6 kW job uses; used to spread handling
A25: JOB-LEVEL
A26: Agent commission (of direct cost) | B26: 0.05 | D26: Set Sep 30, 2026
A27: VAT | B27: 0.12
A28: Markup on freight (job line) | B28: 0.15 | D28: Input. 15% is about what the old per-item method charged on freight through the panel and battery tiers
A30: CATEGORIES
A31: Category | B31: Markup tier | C31: Wastage | D31: Why
A32: Solar Panel | B32: 0.1 | C32: 0 | D32: Price visible to customers, big share of cost
A33: Inverter | B33: 0.1 | C33: 0 | D33: Price visible, big share
A34: Battery | B34: 0.15 | C34: 0 | D34: Price visible, big share; warranty handling is ours
A35: All-in-one System | B35: 0.15 | C35: 0 | D35: Inverter + battery in one unit; priced like a battery. New category - drop if not wanted
A36: Mounting | B36: 0.3 | C36: 0.02 | D36: Wastage Est.: spare clamps and screws
A37: Wires and Terminations | B37: 0.3 | C37: 0.05 | D37: Wastage Est.: offcuts
A38: Protective Devices | B38: 0.3 | C38: 0
A39: Enclosures and Raceways | B39: 0.3 | C39: 0.05 | D39: Wastage Est.: conduit offcuts
A40: Grounding | B40: 0.3 | C40: 0.02 | D40: Wastage Est.
A41: Accessories | B41: 0.3 | C41: 0
A42: Consumables | B42: 0.3 | C42: 0.1 | D42: Wastage Est.

Sheet SUPPLIERS
A1: SUPPLIERS
A2: Supplier | B2: Pickup address | C2: One-way km from Pila base (from ROUTE) | D2: Dealer discount off list (input) | E2: Payment fee % (input) | F2: Delivers to site free (input Yes/No) | G2: Price list date | H2: Prices | I2: Warranty | J2: Remarks
A3: Blue Carbon | B3: Warehouse Complex, Brgy. Malitlit, Santa Rosa, Laguna | C3: =ROUTE!F8 -> 55 | D3: 0 | E3: 0 | F3: No | G3: Sep 19, 2026 (previous list Sep 7, 2026) | H3: Distributor price (the list says so); VAT-exclusive, VAT invoice available at 12% more; local freight not included; changes announced 5 working days ahead | I3: Panels 25 yrs; lithium batteries 10 yrs on the price list (battery datasheets say 5 yrs); DLL hybrid inverters 5 yrs | J3: km Est. Payment terms and delivery offer not yet known
A4: Felicity Solar | B4: Office and warehouse, Buendia, Makati (at the Skyway exit) | C4: =ROUTE!F6 -> 90 | D4: 0 | E4: 0 | F4: No | G4: September 2026 | H4: VAT-exclusive; VAT invoice available at 12% more. The list is SRP: enter your discounted prices in the MATERIALS DB list price column (keep the discount here at 0), or a flat % here | I4: Hybrid inverters 10 yrs; off-grid 2 yrs; eco-hybrid 5 yrs; FLA batteries 7 yrs; FLB and FLH batteries 10 yrs; racks not covered | J4: km Est. Payment terms and delivery offer not yet known
A5: IAN Solar | B5: 490 EDSA, East Grace Park, Caloocan City | C5: =ROUTE!F5 -> 110 | D5: 0 | E5: 0 | F5: No | G5: Sep 3, 2026 | H5: VAT-exclusive; VAT invoice available at 12% more. Luzon branch price | I5: Not stated on the list | J5: Pickup only
A6: One Point | B6: Alabang branch, Cupang, Muntinlupa (plus code C2HH+HV9). Tel 0981-655-9900 | C6: =ROUTE!F7 -> 70 | D6: 0 | E6: 0 | F6: No | G6: Sep 11, 2026 (Main QC list) | H6: VAT-exclusive; VAT invoice available at 12% more. Items marked "call for wholesale" are retail prices | I6: Not stated on the list | J6: Pickup only, at Alabang. Listed as One Solar (Main QC) on the canvass sheet; your sample package was priced from this list. Alabang prices are the same as Main QC (you confirmed)

Sheet TOLL
A1: TOLL - Class 2 rates for the shadow truck (your tables). Rows = exit, columns = entry
A3: SKYWAY STAGE 3
A4: Exit \ Entry | B4: Buendia | C4: Quirino | D4: Plaza Dilao | E4: Nagtahan | F4: E. Rodriguez | G4: Quezon Ave. | H4: Balintawak
A5: Quirino | B5: 210 | C5: -- | D5: -- | E5: -- | F5: -- | G5: 528 | H5: 528
A6: Plaza Dilao | B6: -- | C6: -- | D6: -- | E6: -- | F6: -- | G6: -- | H6: --
A7: Nagtahan | B7: 210 | C7: -- | D7: -- | E7: -- | F7: -- | G7: 528 | H7: 528
A8: E. Rodriguez | B8: -- | C8: -- | D8: -- | E8: -- | F8: -- | G8: 258 | H8: 258
A9: Quezon Ave. | B9: 528 | C9: 528 | D9: -- | E9: 528 | F9: 258 | G9: -- | H9: 258
A10: Balintawak | B10: 528 | C10: 528 | D10: -- | E10: 528 | F10: 258 | G10: 258 | H10: --
A11: NLEX | B11: 528 | C11: 528 | D11: -- | E11: 528 | F11: 258 | G11: 258 | H11: --
A13: SKYWAY / SLEX
A14: Exit \ Entry | B14: Magallanes | C14: Buendia | D14: C-5 | E14: Amorsolo | F14: Bicutan | G14: Magallanes (Skyway) | H14: NAIAX | I14: Sucat | J14: Alabang | K14: Filinvest | L14: MCX | M14: Susana Heights | N14: San Pedro | O14: Southwoods | P14: Carmona | Q14: Mamplasan | R14: Sta. Rosa | S14: ABI/Greenfield | T14: Cabuyao | U14: Silangan | V14: Calamba | W14: Merville
A15: Buendia | B15: -- | C15: -- | D15: -- | E15: -- | F15: 145 | G15: -- | H15: FREE | I15: 237 | J15: 329 | K15: -- | L15: 418 | M15: 371 | N15: 385 | O15: 420 | P15: 434 | Q15: 457 | R15: 478 | S15: 508 | T15: 527 | U15: 540 | V15: 582 | W15: --
A16: C-5 | B16: -- | C16: -- | D16: -- | E16: -- | F16: 98 | G16: -- | H16: -- | I16: 168 | J16: 237 | K16: 248 | L16: 326 | M16: 279 | N16: 293 | O16: 328 | P16: 342 | Q16: 365 | R16: 386 | S16: 416 | T16: 435 | U16: 448 | V16: 490 | W16: --
A17: Amorsolo | B17: -- | C17: -- | D17: -- | E17: -- | F17: 145 | G17: -- | H17: FREE | I17: 237 | J17: 329 | K17: -- | L17: 418 | M17: 371 | N17: 385 | O17: 420 | P17: 434 | Q17: 457 | R17: 478 | S17: 508 | T17: 527 | U17: 540 | V17: 582 | W17: --
A18: Bicutan | B18: 98 | C18: 145 | D18: 98 | E18: 145 | F18: -- | G18: 145 | H18: 145 | I18: 69 | J18: 138 | K18: 149 | L18: 227 | M18: 180 | N18: 194 | O18: 229 | P18: 243 | Q18: 266 | R18: 287 | S18: 317 | T18: 336 | U18: 349 | V18: 391 | W18: --
A19: Magallanes (Skyway) | B19: -- | C19: -- | D19: -- | E19: -- | F19: 145 | G19: -- | H19: FREE | I19: 237 | J19: 329 | K19: -- | L19: 418 | M19: 371 | N19: 385 | O19: 420 | P19: 434 | Q19: 457 | R19: 478 | S19: 508 | T19: 527 | U19: 540 | V19: 582 | W19: --
A20: NAIAX | B20: -- | C20: FREE | D20: -- | E20: FREE | F20: 145 | G20: FREE | H20: -- | I20: 237 | J20: 329 | K20: -- | L20: 418 | M20: 371 | N20: 385 | O20: 420 | P20: 434 | Q20: 457 | R20: 478 | S20: 508 | T20: 527 | U20: 540 | V20: 582 | W20: --
A21: Sucat | B21: 168 | C21: 237 | D21: 168 | E21: 237 | F21: 69 | G21: 237 | H21: 237 | I21: -- | J21: 69 | K21: 80 | L21: 158 | M21: 111 | N21: 125 | O21: 160 | P21: 174 | Q21: 197 | R21: 218 | S21: 248 | T21: 267 | U21: 280 | V21: 322 | W21: --
A22: Alabang | B22: 237 | C22: 329 | D22: 237 | E22: 329 | F22: 138 | G22: 329 | H22: 329 | I22: 69 | J22: -- | K22: 11 | L22: 89 | M22: 42 | N22: 56 | O22: 91 | P22: 105 | Q22: 128 | R22: 149 | S22: 179 | T22: 198 | U22: 211 | V22: 253 | W22: --
A23: Filinvest | B23: 248 | C23: -- | D23: 248 | E23: -- | F23: 149 | G23: -- | H23: -- | I23: 80 | J23: 11 | K23: -- | L23: 78 | M23: 31 | N23: 45 | O23: 80 | P23: 94 | Q23: 117 | R23: 138 | S23: 168 | T23: 187 | U23: 200 | V23: 242 | W23: --
A24: MCX | B24: 326 | C24: 418 | D24: 326 | E24: 418 | F24: 227 | G24: 418 | H24: 418 | I24: 158 | J24: 89 | K24: 78 | L24: -- | M24: 47 | N24: 61 | O24: 96 | P24: 110 | Q24: 133 | R24: 154 | S24: 184 | T24: 203 | U24: 216 | V24: 258 | W24: --
A25: Susana Heights | B25: 279 | C25: 371 | D25: 279 | E25: 371 | F25: 180 | G25: 371 | H25: 371 | I25: 111 | J25: 42 | K25: 31 | L25: 47 | M25: -- | N25: 14 | O25: 49 | P25: 63 | Q25: 86 | R25: 107 | S25: 137 | T25: 156 | U25: 169 | V25: 211 | W25: --
A26: San Pedro | B26: 293 | C26: 385 | D26: 293 | E26: 385 | F26: 194 | G26: 385 | H26: 385 | I26: 125 | J26: 56 | K26: 45 | L26: 61 | M26: 14 | N26: -- | O26: 35 | P26: 49 | Q26: 72 | R26: 93 | S26: 123 | T26: 142 | U26: 155 | V26: 197 | W26: --
A27: Southwoods | B27: 328 | C27: 420 | D27: 328 | E27: 420 | F27: 229 | G27: 420 | H27: 420 | I27: 160 | J27: 91 | K27: 80 | L27: 96 | M27: 49 | N27: 35 | O27: -- | P27: 14 | Q27: 37 | R27: 58 | S27: 88 | T27: 107 | U27: 120 | V27: 162 | W27: --
A28: Carmona | B28: 342 | C28: 434 | D28: 342 | E28: 434 | F28: 243 | G28: 434 | H28: 434 | I28: 174 | J28: 105 | K28: 94 | L28: 110 | M28: 63 | N28: 49 | O28: 14 | P28: -- | Q28: 23 | R28: 44 | S28: 74 | T28: 93 | U28: 106 | V28: 148 | W28: --
A29: Mamplasan | B29: 365 | C29: 457 | D29: 365 | E29: 457 | F29: 266 | G29: 457 | H29: 457 | I29: 197 | J29: 128 | K29: 117 | L29: 133 | M29: 86 | N29: 72 | O29: 37 | P29: 23 | Q29: -- | R29: 21 | S29: 51 | T29: 69 | U29: 83 | V29: 124 | W29: --
A30: Sta. Rosa | B30: 386 | C30: 478 | D30: 386 | E30: 478 | F30: 287 | G30: 478 | H30: 478 | I30: 218 | J30: 149 | K30: 138 | L30: 154 | M30: 107 | N30: 93 | O30: 58 | P30: 44 | Q30: 21 | R30: -- | S30: 30 | T30: 49 | U30: 62 | V30: 104 | W30: --
A31: ABI/Greenfield | B31: 416 | C31: 508 | D31: 416 | E31: 508 | F31: 317 | G31: 508 | H31: 508 | I31: 248 | J31: 179 | K31: 168 | L31: 184 | M31: 137 | N31: 123 | O31: 88 | P31: 74 | Q31: 51 | R31: 30 | S31: -- | T31: 19 | U31: 32 | V31: 74 | W31: --
A32: Cabuyao | B32: 435 | C32: 527 | D32: 435 | E32: 527 | F32: 336 | G32: 527 | H32: 527 | I32: 267 | J32: 198 | K32: 187 | L32: 203 | M32: 156 | N32: 142 | O32: 107 | P32: 93 | Q32: 69 | R32: 49 | S32: 19 | T32: -- | U32: 13 | V32: 55 | W32: --
A33: Silangan | B33: 448 | C33: 540 | D33: 448 | E33: 540 | F33: 349 | G33: 540 | H33: 540 | I33: 280 | J33: 211 | K33: 200 | L33: 216 | M33: 169 | N33: 155 | O33: 120 | P33: 106 | Q33: 83 | R33: 62 | S33: 32 | T33: 13 | U33: -- | V33: 42 | W33: --
A34: Calamba | B34: 490 | C34: 582 | D34: 490 | E34: 582 | F34: 391 | G34: 582 | H34: 582 | I34: 322 | J34: 253 | K34: 242 | L34: 258 | M34: 211 | N34: 197 | O34: 162 | P34: 148 | Q34: 124 | R34: 104 | S34: 74 | T34: 55 | U34: 42 | V34: -- | W34: --
A35: Merville | B35: 98 | C35: -- | D35: -- | E35: -- | F35: -- | G35: -- | H35: -- | I35: -- | J35: -- | K35: -- | L35: -- | M35: -- | N35: -- | O35: -- | P35: -- | Q35: -- | R35: -- | S35: -- | T35: -- | U35: -- | V35: -- | W35: --
A36: Don Bosco | B36: -- | C36: -- | D36: -- | E36: -- | F36: 145 | G36: -- | H36: FREE | I36: 237 | J36: 329 | K36: -- | L36: 418 | M36: 371 | N36: 385 | O36: 420 | P36: 434 | Q36: 457 | R36: 478 | S36: 508 | T36: 527 | U36: 540 | V36: 582 | W36: --

Sheet ROUTE
A1: ROUTE - reference pickup run for a Pila-area job
A3: # | B3: Location | C3: Address | D3: Toll plaza used | F3: One-way km from Pila base
A4: 1 | B4: Pila base | C4: PL Development Inc., Pila, Laguna | D4: Calamba (SLEX) | F4: =INDEX($B$13:$G$18,1,A4) -> 0
A5: 2 | B5: IAN Solar | C5: 490 EDSA, East Grace Park, Caloocan City | D5: Balintawak (Skyway Stage 3) | F5: =INDEX($B$13:$G$18,1,A5) -> 110
A6: 3 | B6: Felicity Solar | C6: Buendia, Makati (Skyway exit) | D6: Buendia (Skyway) | F6: =INDEX($B$13:$G$18,1,A6) -> 90
A7: 4 | B7: One Point | C7: Alabang branch, Cupang, Muntinlupa (C2HH+HV9) | D7: Alabang (Skyway/SLEX) | F7: =INDEX($B$13:$G$18,1,A7) -> 70
A8: 5 | B8: Blue Carbon | C8: Warehouse Complex, Brgy. Malitlit, Santa Rosa, Laguna | D8: Sta. Rosa (SLEX) | F8: =INDEX($B$13:$G$18,1,A8) -> 55
A9: 6 | B9: Job site | C9: Pila-area site (reference job) | D9: Calamba (SLEX) | F9: =INDEX($B$13:$G$18,1,A9) -> 10
A11: ONE-WAY ROAD KM BETWEEN STOPS (Est. - replace with Google Maps truck-route km; row = from, column = to)
B12: Pila base | C12: IAN Solar | D12: Felicity Solar | E12: One Point | F12: Blue Carbon | G12: Job site
A13: Pila base | B13: 0 | C13: 110 | D13: 90 | E13: 70 | F13: 55 | G13: 10
A14: IAN Solar | B14: 110 | C14: 0 | D14: 22 | E14: 40 | F14: 60 | G14: 115
A15: Felicity Solar | B15: 90 | C15: 22 | D15: 0 | E15: 18 | F15: 35 | G15: 90
A16: One Point | B16: 70 | C16: 40 | D16: 18 | E16: 0 | F16: 20 | G16: 70
A17: Blue Carbon | B17: 55 | C17: 60 | D17: 35 | E17: 20 | F17: 0 | G17: 55
A18: Job site | B18: 10 | C18: 115 | D18: 90 | E18: 70 | F18: 55 | G18: 0
A20: TOLL PER LEG, P (Class 2, from the TOLL sheet via each stop's toll plaza; row = from, column = to)
B21: Pila base | C21: IAN Solar | D21: Felicity Solar | E21: One Point | F21: Blue Carbon | G21: Job site
A22: Pila base | B22: 0 | C22: =TOLL!V15+TOLL!B10 -> 1110 | D22: =TOLL!V15 -> 582 | E22: =TOLL!V22 -> 253 | F22: =TOLL!V30 -> 104 | G22: 0
A23: IAN Solar | B23: =TOLL!B10+TOLL!C34 -> 1110 | C23: 0 | D23: =TOLL!B10 -> 528 | E23: =TOLL!B10+TOLL!C22 -> 857 | F23: =TOLL!B10+TOLL!C30 -> 1006 | G23: =TOLL!B10+TOLL!C34 -> 1110
A24: Felicity Solar | B24: =TOLL!C34 -> 582 | C24: =TOLL!B10 -> 528 | D24: 0 | E24: =TOLL!C22 -> 329 | F24: =TOLL!C30 -> 478 | G24: =TOLL!C34 -> 582
A25: One Point | B25: =TOLL!J34 -> 253 | C25: =TOLL!J15+TOLL!B10 -> 857 | D25: =TOLL!J15 -> 329 | E25: 0 | F25: =TOLL!J30 -> 149 | G25: =TOLL!J34 -> 253
A26: Blue Carbon | B26: =TOLL!R34 -> 104 | C26: =TOLL!R15+TOLL!B10 -> 1006 | D26: =TOLL!R15 -> 478 | E26: =TOLL!R22 -> 149 | F26: 0 | G26: =TOLL!R34 -> 104
A27: Job site | B27: 0 | C27: =TOLL!V15+TOLL!B10 -> 1110 | D27: =TOLL!V15 -> 582 | E27: =TOLL!V22 -> 253 | F27: =TOLL!V30 -> 104 | G27: 0
A28: Balintawak to Buendia (southbound) is not on your Skyway Stage 3 table; the Buendia to Balintawak rate is used for it.
A29: REFERENCE RUN - stops in driving order: empty to the farthest supplier, load on the way back south along Skyway and SLEX
A30: Seq | B30: Stop | C30: Location # | D30: On this run? | E30: Last stop so far (location #) | F30: Leg km | G30: Leg toll | H30: Why
A31: 1 | B31: Pila base | C31: 1 | D31: Yes | E31: =C31 -> 1 | F31: 0 | G31: 0 | H31: Start, truck empty
A32: 2 | B32: IAN Solar | C32: 2 | D32: =IF(AND(INDEX(SUPPLIERS!$F$3:$F$30,MATCH(B32,SUPPLIERS!$A$3:$A$30,0))<>"Yes",SUMPRODUCT(('REF BASKET'!$B$4:$B$29=B32)*('REF BASKET'!$D$4:$D$29>0))>0),"Yes","No") -> Yes | E32: =IF(D32="Yes",C32,E31) -> 2 | F32: =IF(D32="Yes",INDEX($B$13:$G$18,E31,C32),0) -> 110 | G32: =IF(D32="Yes",INDEX($B$22:$G$27,E31,C32),0) -> 1110 | H32: On the run when the REF BASKET buys from this supplier
A33: 3 | B33: Felicity Solar | C33: 3 | D33: =IF(AND(INDEX(SUPPLIERS!$F$3:$F$30,MATCH(B33,SUPPLIERS!$A$3:$A$30,0))<>"Yes",SUMPRODUCT(('REF BASKET'!$B$4:$B$29=B33)*('REF BASKET'!$D$4:$D$29>0))>0),"Yes","No") -> Yes | E33: =IF(D33="Yes",C33,E32) -> 3 | F33: =IF(D33="Yes",INDEX($B$13:$G$18,E32,C33),0) -> 22 | G33: =IF(D33="Yes",INDEX($B$22:$G$27,E32,C33),0) -> 528 | H33: On the run when the REF BASKET buys from this supplier
A34: 4 | B34: One Point | C34: 4 | D34: =IF(AND(INDEX(SUPPLIERS!$F$3:$F$30,MATCH(B34,SUPPLIERS!$A$3:$A$30,0))<>"Yes",SUMPRODUCT(('REF BASKET'!$B$4:$B$29=B34)*('REF BASKET'!$D$4:$D$29>0))>0),"Yes","No") -> Yes | E34: =IF(D34="Yes",C34,E33) -> 4 | F34: =IF(D34="Yes",INDEX($B$13:$G$18,E33,C34),0) -> 18 | G34: =IF(D34="Yes",INDEX($B$22:$G$27,E33,C34),0) -> 329 | H34: On the run when the REF BASKET buys from this supplier
A35: 5 | B35: Blue Carbon | C35: 5 | D35: =IF(AND(INDEX(SUPPLIERS!$F$3:$F$30,MATCH(B35,SUPPLIERS!$A$3:$A$30,0))<>"Yes",SUMPRODUCT(('REF BASKET'!$B$4:$B$29=B35)*('REF BASKET'!$D$4:$D$29>0))>0),"Yes","No") -> Yes | E35: =IF(D35="Yes",C35,E34) -> 5 | F35: =IF(D35="Yes",INDEX($B$13:$G$18,E34,C35),0) -> 20 | G35: =IF(D35="Yes",INDEX($B$22:$G$27,E34,C35),0) -> 149 | H35: On the run when the REF BASKET buys from this supplier
A36: 6 | B36: Job site | C36: 6 | D36: Yes | E36: =IF(D36="Yes",C36,E35) -> 6 | F36: =IF(D36="Yes",INDEX($B$13:$G$18,E35,C36),0) -> 55 | G36: =IF(D36="Yes",INDEX($B$22:$G$27,E35,C36),0) -> 104 | H36: Unload
A37: 7 | B37: Pila base | C37: 1 | D37: Yes | E37: =IF(D37="Yes",C37,E36) -> 1 | F37: =IF(D37="Yes",INDEX($B$13:$G$18,E36,C37),0) -> 10 | G37: =IF(D37="Yes",INDEX($B$22:$G$27,E36,C37),0) -> 0 | H37: Return
A38: Loop distance and toll | F38: =SUM(F31:F37) -> 235 | G38: =SUM(G31:G37) -> 2220
A40: Route | B40: ="Pila"&IF(D32="Yes"," > IAN Solar (Caloocan)","")&IF(D33="Yes"," > Felicity (Makati)","")&IF(D34="Yes"," > One Point (Alabang)","")&IF(D35="Yes"," > Blue Carbon (Santa Rosa)","")&" > Pila-area site > Pila" -> Pila > IAN Solar (Caloocan) > Felicity (Makati) > One Point (Alabang) > Blue Carbon (Santa Rosa) > Pila-area site > Pila
A42: Shadow truck: these km and tolls price the run as if we owned the NMR85; they are not a plan for how we actually haul.

Sheet REF BASKET
A1: REF BASKET - a typical 6 kW hybrid job: sets the typical fill (spreads handling), which suppliers the reference run visits, and shows freight as one job line
A3: Code | B3: Supplier | C3: Item | D3: Qty (input) | E3: Truck share per unit | F3: Truck share, total | G3: Remarks | H3: On our truck?
A4: BC-PNL-004 | B4: =INDEX('MATERIALS DB'!$C$4:$C$465,MATCH(A4,'MATERIALS DB'!$A$4:$A$465,0)) -> Blue Carbon | C4: =INDEX('MATERIALS DB'!$D$4:$D$465,MATCH(A4,'MATERIALS DB'!$A$4:$A$465,0)) -> 630W Bifacial solar panel | D4: 8 | E4: =INDEX('MATERIALS DB'!$Q$4:$Q$465,MATCH(A4,'MATERIALS DB'!$A$4:$A$465,0)) -> 0.0092333333 | F4: =D4*E4 -> 0.073866667 | G4: 8 x 630 W panels | H4: =IF(INDEX(SUPPLIERS!$F$3:$F$30,MATCH(B4,SUPPLIERS!$A$3:$A$30,0))="Yes","No","Yes") -> Yes
A5: FS-INV-001 | B5: =INDEX('MATERIALS DB'!$C$4:$C$465,MATCH(A5,'MATERIALS DB'!$A$4:$A$465,0)) -> Felicity Solar | C5: =INDEX('MATERIALS DB'!$D$4:$D$465,MATCH(A5,'MATERIALS DB'!$A$4:$A$465,0)) -> 6 kW low-voltage hybrid inverter (grid-tie + backup) | D5: 1 | E5: =INDEX('MATERIALS DB'!$Q$4:$Q$465,MATCH(A5,'MATERIALS DB'!$A$4:$A$465,0)) -> 0.0081666667 | F5: =D5*E5 -> 0.0081666667 | G5: 6 kW hybrid inverter | H5: =IF(INDEX(SUPPLIERS!$F$3:$F$30,MATCH(B5,SUPPLIERS!$A$3:$A$30,0))="Yes","No","Yes") -> Yes
A6: FS-BAT-006 | B6: =INDEX('MATERIALS DB'!$C$4:$C$465,MATCH(A6,'MATERIALS DB'!$A$4:$A$465,0)) -> Felicity Solar | C6: =INDEX('MATERIALS DB'!$D$4:$D$465,MATCH(A6,'MATERIALS DB'!$A$4:$A$465,0)) -> LiFePO4 51.2V 230Ah (11.7 kWh), FLB IP65 | D6: 1 | E6: =INDEX('MATERIALS DB'!$Q$4:$Q$465,MATCH(A6,'MATERIALS DB'!$A$4:$A$465,0)) -> 0.037 | F6: =D6*E6 -> 0.037 | G6: 11.7 kWh battery (the packages use 11.8 kWh) | H6: =IF(INDEX(SUPPLIERS!$F$3:$F$30,MATCH(B6,SUPPLIERS!$A$3:$A$30,0))="Yes","No","Yes") -> Yes
A7: BC-MNT-001 | B7: =INDEX('MATERIALS DB'!$C$4:$C$465,MATCH(A7,'MATERIALS DB'!$A$4:$A$465,0)) -> Blue Carbon | C7: =INDEX('MATERIALS DB'!$D$4:$D$465,MATCH(A7,'MATERIALS DB'!$A$4:$A$465,0)) -> Rail 2.4 m | D7: 8 | E7: =INDEX('MATERIALS DB'!$Q$4:$Q$465,MATCH(A7,'MATERIALS DB'!$A$4:$A$465,0)) -> 0.00086666667 | F7: =D7*E7 -> 0.0069333333 | H7: =IF(INDEX(SUPPLIERS!$F$3:$F$30,MATCH(B7,SUPPLIERS!$A$3:$A$30,0))="Yes","No","Yes") -> Yes
A8: BC-MNT-006 | B8: =INDEX('MATERIALS DB'!$C$4:$C$465,MATCH(A8,'MATERIALS DB'!$A$4:$A$465,0)) -> Blue Carbon | C8: =INDEX('MATERIALS DB'!$D$4:$D$465,MATCH(A8,'MATERIALS DB'!$A$4:$A$465,0)) -> L-leg (L-foot) | D8: 24 | E8: =INDEX('MATERIALS DB'!$Q$4:$Q$465,MATCH(A8,'MATERIALS DB'!$A$4:$A$465,0)) -> 5e-05 | F8: =D8*E8 -> 0.0012 | H8: =IF(INDEX(SUPPLIERS!$F$3:$F$30,MATCH(B8,SUPPLIERS!$A$3:$A$30,0))="Yes","No","Yes") -> Yes
A9: BC-MNT-003 | B9: =INDEX('MATERIALS DB'!$C$4:$C$465,MATCH(A9,'MATERIALS DB'!$A$4:$A$465,0)) -> Blue Carbon | C9: =INDEX('MATERIALS DB'!$D$4:$D$465,MATCH(A9,'MATERIALS DB'!$A$4:$A$465,0)) -> End clamp | D9: 8 | E9: =INDEX('MATERIALS DB'!$Q$4:$Q$465,MATCH(A9,'MATERIALS DB'!$A$4:$A$465,0)) -> 2.6666667e-05 | F9: =D9*E9 -> 0.00021333333 | H9: =IF(INDEX(SUPPLIERS!$F$3:$F$30,MATCH(B9,SUPPLIERS!$A$3:$A$30,0))="Yes","No","Yes") -> Yes
A10: BC-MNT-004 | B10: =INDEX('MATERIALS DB'!$C$4:$C$465,MATCH(A10,'MATERIALS DB'!$A$4:$A$465,0)) -> Blue Carbon | C10: =INDEX('MATERIALS DB'!$D$4:$D$465,MATCH(A10,'MATERIALS DB'!$A$4:$A$465,0)) -> Mid clamp | D10: 12 | E10: =INDEX('MATERIALS DB'!$Q$4:$Q$465,MATCH(A10,'MATERIALS DB'!$A$4:$A$465,0)) -> 2.6666667e-05 | F10: =D10*E10 -> 0.00032 | H10: =IF(INDEX(SUPPLIERS!$F$3:$F$30,MATCH(B10,SUPPLIERS!$A$3:$A$30,0))="Yes","No","Yes") -> Yes
A11: BC-MNT-005 | B11: =INDEX('MATERIALS DB'!$C$4:$C$465,MATCH(A11,'MATERIALS DB'!$A$4:$A$465,0)) -> Blue Carbon | C11: =INDEX('MATERIALS DB'!$D$4:$D$465,MATCH(A11,'MATERIALS DB'!$A$4:$A$465,0)) -> Rail splice | D11: 4 | E11: =INDEX('MATERIALS DB'!$Q$4:$Q$465,MATCH(A11,'MATERIALS DB'!$A$4:$A$465,0)) -> 5e-05 | F11: =D11*E11 -> 0.0002 | H11: =IF(INDEX(SUPPLIERS!$F$3:$F$30,MATCH(B11,SUPPLIERS!$A$3:$A$30,0))="Yes","No","Yes") -> Yes
A12: BC-WIR-001 | B12: =INDEX('MATERIALS DB'!$C$4:$C$465,MATCH(A12,'MATERIALS DB'!$A$4:$A$465,0)) -> Blue Carbon | C12: =INDEX('MATERIALS DB'!$D$4:$D$465,MATCH(A12,'MATERIALS DB'!$A$4:$A$465,0)) -> Solar cable 4mm2, red | D12: 15 | E12: =INDEX('MATERIALS DB'!$Q$4:$Q$465,MATCH(A12,'MATERIALS DB'!$A$4:$A$465,0)) -> 1.8333333e-05 | F12: =D12*E12 -> 0.000275 | G12: PV wire, 30 m total | H12: =IF(INDEX(SUPPLIERS!$F$3:$F$30,MATCH(B12,SUPPLIERS!$A$3:$A$30,0))="Yes","No","Yes") -> Yes
A13: BC-WIR-002 | B13: =INDEX('MATERIALS DB'!$C$4:$C$465,MATCH(A13,'MATERIALS DB'!$A$4:$A$465,0)) -> Blue Carbon | C13: =INDEX('MATERIALS DB'!$D$4:$D$465,MATCH(A13,'MATERIALS DB'!$A$4:$A$465,0)) -> Solar cable 4mm2, black | D13: 15 | E13: =INDEX('MATERIALS DB'!$Q$4:$Q$465,MATCH(A13,'MATERIALS DB'!$A$4:$A$465,0)) -> 1.8333333e-05 | F13: =D13*E13 -> 0.000275 | H13: =IF(INDEX(SUPPLIERS!$F$3:$F$30,MATCH(B13,SUPPLIERS!$A$3:$A$30,0))="Yes","No","Yes") -> Yes
A14: IAN-WIR-004 | B14: =INDEX('MATERIALS DB'!$C$4:$C$465,MATCH(A14,'MATERIALS DB'!$A$4:$A$465,0)) -> IAN Solar | C14: =INDEX('MATERIALS DB'!$D$4:$D$465,MATCH(A14,'MATERIALS DB'!$A$4:$A$465,0)) -> THHN 8.0mm2 EURO WIRES | D14: 35 | E14: =INDEX('MATERIALS DB'!$Q$4:$Q$465,MATCH(A14,'MATERIALS DB'!$A$4:$A$465,0)) -> 3.4333333e-05 | F14: =D14*E14 -> 0.0012016667 | G14: THHN 8.0: 15 m circuits + 20 m grounding | H14: =IF(INDEX(SUPPLIERS!$F$3:$F$30,MATCH(B14,SUPPLIERS!$A$3:$A$30,0))="Yes","No","Yes") -> Yes
A15: OP-WIR-007 | B15: =INDEX('MATERIALS DB'!$C$4:$C$465,MATCH(A15,'MATERIALS DB'!$A$4:$A$465,0)) -> One Point | C15: =INDEX('MATERIALS DB'!$D$4:$D$465,MATCH(A15,'MATERIALS DB'!$A$4:$A$465,0)) -> 35mm2 - 1M w/ LUG PAIR | D15: 2 | E15: =INDEX('MATERIALS DB'!$Q$4:$Q$465,MATCH(A15,'MATERIALS DB'!$A$4:$A$465,0)) -> 0.00015666667 | F15: =D15*E15 -> 0.00031333333 | G15: 35 mm2 battery cable with lugs, 1 m pairs | H15: =IF(INDEX(SUPPLIERS!$F$3:$F$30,MATCH(B15,SUPPLIERS!$A$3:$A$30,0))="Yes","No","Yes") -> Yes
A16: OP-ENC-009 | B16: =INDEX('MATERIALS DB'!$C$4:$C$465,MATCH(A16,'MATERIALS DB'!$A$4:$A$465,0)) -> One Point | C16: =INDEX('MATERIALS DB'!$D$4:$D$465,MATCH(A16,'MATERIALS DB'!$A$4:$A$465,0)) -> Cable TRAY 60*60 - 2METER | D16: 1 | E16: =INDEX('MATERIALS DB'!$Q$4:$Q$465,MATCH(A16,'MATERIALS DB'!$A$4:$A$465,0)) -> 0.00050440855 | F16: =D16*E16 -> 0.00050440855 | G16: Cable tray | H16: =IF(INDEX(SUPPLIERS!$F$3:$F$30,MATCH(B16,SUPPLIERS!$A$3:$A$30,0))="Yes","No","Yes") -> Yes
A17: IAN-ENC-011 | B17: =INDEX('MATERIALS DB'!$C$4:$C$465,MATCH(A17,'MATERIALS DB'!$A$4:$A$465,0)) -> IAN Solar | C17: =INDEX('MATERIALS DB'!$D$4:$D$465,MATCH(A17,'MATERIALS DB'!$A$4:$A$465,0)) -> FLEX CONDUIT 32mm | D17: 30 | E17: =INDEX('MATERIALS DB'!$Q$4:$Q$465,MATCH(A17,'MATERIALS DB'!$A$4:$A$465,0)) -> 4.3333333e-05 | F17: =D17*E17 -> 0.0013 | G17: Flex conduit 32 mm (rev2 had 36 mm HDPE) | H17: =IF(INDEX(SUPPLIERS!$F$3:$F$30,MATCH(B17,SUPPLIERS!$A$3:$A$30,0))="Yes","No","Yes") -> Yes
A18: IAN-WIR-026 | B18: =INDEX('MATERIALS DB'!$C$4:$C$465,MATCH(A18,'MATERIALS DB'!$A$4:$A$465,0)) -> IAN Solar | C18: =INDEX('MATERIALS DB'!$D$4:$D$465,MATCH(A18,'MATERIALS DB'!$A$4:$A$465,0)) -> MC4 PAIR | D18: 4 | E18: =INDEX('MATERIALS DB'!$Q$4:$Q$465,MATCH(A18,'MATERIALS DB'!$A$4:$A$465,0)) -> 7e-06 | F18: =D18*E18 -> 2.8e-05 | G18: MC4 pairs | H18: =IF(INDEX(SUPPLIERS!$F$3:$F$30,MATCH(B18,SUPPLIERS!$A$3:$A$30,0))="Yes","No","Yes") -> Yes
A19: IAN-PRT-009 | B19: =INDEX('MATERIALS DB'!$C$4:$C$465,MATCH(A19,'MATERIALS DB'!$A$4:$A$465,0)) -> IAN Solar | C19: =INDEX('MATERIALS DB'!$D$4:$D$465,MATCH(A19,'MATERIALS DB'!$A$4:$A$465,0)) -> SUNTREE DC BREAKER 2P 16A/25A 600V | D19: 2 | E19: =INDEX('MATERIALS DB'!$Q$4:$Q$465,MATCH(A19,'MATERIALS DB'!$A$4:$A$465,0)) -> 8.6666667e-05 | F19: =D19*E19 -> 0.00017333333 | G19: PV string breakers | H19: =IF(INDEX(SUPPLIERS!$F$3:$F$30,MATCH(B19,SUPPLIERS!$A$3:$A$30,0))="Yes","No","Yes") -> Yes
A20: IAN-PRT-018 | B20: =INDEX('MATERIALS DB'!$C$4:$C$465,MATCH(A20,'MATERIALS DB'!$A$4:$A$465,0)) -> IAN Solar | C20: =INDEX('MATERIALS DB'!$D$4:$D$465,MATCH(A20,'MATERIALS DB'!$A$4:$A$465,0)) -> SUNTREE DC SPD 2P 600V | D20: 1 | E20: =INDEX('MATERIALS DB'!$Q$4:$Q$465,MATCH(A20,'MATERIALS DB'!$A$4:$A$465,0)) -> 0.0001 | F20: =D20*E20 -> 0.0001 | G20: DC SPD | H20: =IF(INDEX(SUPPLIERS!$F$3:$F$30,MATCH(B20,SUPPLIERS!$A$3:$A$30,0))="Yes","No","Yes") -> Yes
A21: IAN-PRT-003 | B21: =INDEX('MATERIALS DB'!$C$4:$C$465,MATCH(A21,'MATERIALS DB'!$A$4:$A$465,0)) -> IAN Solar | C21: =INDEX('MATERIALS DB'!$D$4:$D$465,MATCH(A21,'MATERIALS DB'!$A$4:$A$465,0)) -> SUNTREE DC BATTERY BREAKER 2P 250A 500V | D21: 1 | E21: =INDEX('MATERIALS DB'!$Q$4:$Q$465,MATCH(A21,'MATERIALS DB'!$A$4:$A$465,0)) -> 0.001 | F21: =D21*E21 -> 0.001 | G21: Battery breaker (rev2 had a 225A MCCB) | H21: =IF(INDEX(SUPPLIERS!$F$3:$F$30,MATCH(B21,SUPPLIERS!$A$3:$A$30,0))="Yes","No","Yes") -> Yes
A22: OP-PRT-035 | B22: =INDEX('MATERIALS DB'!$C$4:$C$465,MATCH(A22,'MATERIALS DB'!$A$4:$A$465,0)) -> One Point | C22: =INDEX('MATERIALS DB'!$D$4:$D$465,MATCH(A22,'MATERIALS DB'!$A$4:$A$465,0)) -> AC-2P-ATS-690V-63A - MINI | D22: 1 | E22: =INDEX('MATERIALS DB'!$Q$4:$Q$465,MATCH(A22,'MATERIALS DB'!$A$4:$A$465,0)) -> 0.00028333333 | F22: =D22*E22 -> 0.00028333333 | G22: ATS 63A | H22: =IF(INDEX(SUPPLIERS!$F$3:$F$30,MATCH(B22,SUPPLIERS!$A$3:$A$30,0))="Yes","No","Yes") -> Yes
A23: IAN-PRT-027 | B23: =INDEX('MATERIALS DB'!$C$4:$C$465,MATCH(A23,'MATERIALS DB'!$A$4:$A$465,0)) -> IAN Solar | C23: =INDEX('MATERIALS DB'!$D$4:$D$465,MATCH(A23,'MATERIALS DB'!$A$4:$A$465,0)) -> SUNTREE AC BREAKER 2P 32A/63A 400V | D23: 4 | E23: =INDEX('MATERIALS DB'!$Q$4:$Q$465,MATCH(A23,'MATERIALS DB'!$A$4:$A$465,0)) -> 9.3333333e-05 | F23: =D23*E23 -> 0.00037333333 | G23: DU disconnect, grid-inverter, inverter-load, grid-load | H23: =IF(INDEX(SUPPLIERS!$F$3:$F$30,MATCH(B23,SUPPLIERS!$A$3:$A$30,0))="Yes","No","Yes") -> Yes
A24: IAN-PRT-035 | B24: =INDEX('MATERIALS DB'!$C$4:$C$465,MATCH(A24,'MATERIALS DB'!$A$4:$A$465,0)) -> IAN Solar | C24: =INDEX('MATERIALS DB'!$D$4:$D$465,MATCH(A24,'MATERIALS DB'!$A$4:$A$465,0)) -> SUNTREE AC SPD 2P 275V | D24: 4 | E24: =INDEX('MATERIALS DB'!$Q$4:$Q$465,MATCH(A24,'MATERIALS DB'!$A$4:$A$465,0)) -> 0.0001 | F24: =D24*E24 -> 0.0004 | G24: One per AC breaker | H24: =IF(INDEX(SUPPLIERS!$F$3:$F$30,MATCH(B24,SUPPLIERS!$A$3:$A$30,0))="Yes","No","Yes") -> Yes
A25: OP-ENC-007 | B25: =INDEX('MATERIALS DB'!$C$4:$C$465,MATCH(A25,'MATERIALS DB'!$A$4:$A$465,0)) -> One Point | C25: =INDEX('MATERIALS DB'!$D$4:$D$465,MATCH(A25,'MATERIALS DB'!$A$4:$A$465,0)) -> METAL ENCLOSURE 50X40X20 | D25: 2 | E25: =INDEX('MATERIALS DB'!$Q$4:$Q$465,MATCH(A25,'MATERIALS DB'!$A$4:$A$465,0)) -> 0.0043344107 | F25: =D25*E25 -> 0.0086688214 | G25: Metal enclosure 50x40x20: DC box and AC box | H25: =IF(INDEX(SUPPLIERS!$F$3:$F$30,MATCH(B25,SUPPLIERS!$A$3:$A$30,0))="Yes","No","Yes") -> Yes
... A27: IAN-GND-001 | B27: =INDEX('MATERIALS DB'!$C$4:$C$465,MATCH(A27,'MATERIALS DB'!$A$4:$A$465,0)) -> IAN Solar | C27: =INDEX('MATERIALS DB'!$D$4:$D$465,MATCH(A27,'MATERIALS DB'!$A$4:$A$465,0)) -> EARTH LUG | D27: 4 | E27: =INDEX('MATERIALS DB'!$Q$4:$Q$465,MATCH(A27,'MATERIALS DB'!$A$4:$A$465,0)) -> 2.6666667e-05 | F27: =D27*E27 -> 0.00010666667 | G27: Earth lugs | H27: =IF(INDEX(SUPPLIERS!$F$3:$F$30,MATCH(B27,SUPPLIERS!$A$3:$A$30,0))="Yes","No","Yes") -> Yes
A29: Lines follow your rev2 sample package; each from the supplier with the lower landed cost or the one you used. Change a code and the ROUTE follows.
A32: Truck share this job uses (typical fill) | F32: =SUMPRODUCT((H4:H29="Yes")*F4:F29) -> 0.1444829
A33: Trips needed | F33: =ROUNDUP(F32,0) -> 1 | G33: Sum of item shares, so slightly on the safe side
A34: Freight for this job = trips x run cost | F34: =F33*DRIVERS!$B$19 -> 17282.143
A35: Freight line selling price (with freight markup) | F35: =F34*(1+DRIVERS!$B$28) -> 19874.464

Sheet LABOR RATES
A1: LABOR RATES - crew day rates, work day, and man-hours per unit calibrated to your 9.12 kWp grid-tie job
A2: Item | B2: Value | C2: Unit | D2: Source / remarks
A3: CREW DAY RATES (pakyaw, each includes the P150 allowance)
A4: Team lead (electrician) | B4: 3000 | C4: P/day | D4: Your rate, incl. P150 allowance
A5: Skilled installer | B5: 1500 | C5: P/day | D5: Your rate, incl. P150 allowance
A6: Laborer | B6: 1000 | C6: P/day | D6: Your rate, incl. P150 allowance
A7: Allowance included in each rate above | B7: 150 | C7: P/person-day | D7: For reference only; not added again
A8: You, if on site | B8: 5000 | C8: P/day | D8: Your basis in the packages workbook (P4,850 + P150)
A9: WORK DAY
A10: Paid hours per day | B10: 8 | C10: h
A11: Non-productive hours (toolbox talk, tool setup, end-of-day cleanup) | B11: 1 | C11: h | D11: Est.
A12: Round-trip travel to site (on paid time) | B12: ='MOB-DEMOB'!B18 -> 0.5 | C12: h | D12: From MOB-DEMOB
A13: Productive hours per person-day | B13: =B10-B11-B12 -> 6.5 | C13: h
A14: Pay unit (1 = whole days, 0.5 = half days) | B14: 1 | C14: day | D14: Input. Crews paid by the whole day: 1
A16: REFERENCE JOB - your 9.12 kWp grid-tie: 16 panels, 10 kW grid-tie inverter, multi-face roof, custom mounting
A17: Work block | B17: Hours (your figures) | C17: Crew | D17: Man-hours | E17: Who
A18: Roof: panels and mounting | B18: 4 | C18: 2 | D18: =B18*C18 -> 8 | E18: 1 skilled + 1 laborer
A19: Roof: wiring | B19: 2 | C19: 2 | D19: =B19*C19 -> 4 | E19: 1 skilled + 1 laborer
A20: Ground: mounting (inverter, boxes, conduit, ground rod) | B20: 4 | C20: 2 | D20: =B20*C20 -> 8 | E20: Team lead + 1 laborer
A21: Ground: wiring, energization, commissioning | B21: 2 | C21: 2 | D21: =B21*C21 -> 4 | E21: Team lead + 1 laborer
A22: Hand-off | B22: 1 | C22: 2 | D22: =B22*C22 -> 2 | E22: Team lead + 1 laborer (assumed)
A23: Total | D23: =SUM(D18:D22) -> 26
A24: Panels on that job | B24: 16
A26: ROOF RATES
A27: Roof setup per job (part of the mounting hours) | B27: 2 | C27: MH | D27: Est. - ladders, lifeline, layout, hauling tools up
A28: Mounting per panel (L-feet, rails, clamps, panel) | B28: =(D18-B27)/B24 -> 0.375 | C28: MH/panel
A29: Wiring per panel (panel-to-panel, string runs on the roof) | B29: =D19/B24 -> 0.25 | C29: MH/panel
A30: Check: 16 panels, one pair | B30: =(B27+16*(B28+B29))/2 -> 6 | C30: h | D30: Should equal 6 (4 mounting + 2 wiring)
A32: GROUND CALIBRATION
A33: Mounting: weighted units of that job | B33: =SUMPRODUCT(B39:B50,F39:F50) -> 8.95
A34: Mounting: man-hours per weighted unit | B34: =D20/B33 -> 0.89385475 | D34: Makes that job's ground mounting come out at your 4 hours
A35: Wiring: weighted units of that job | B35: =SUMPRODUCT(C39:C50,F39:F50) -> 9.3
A36: Wiring: man-hours per weighted unit | B36: =D21/B35 -> 0.43010753 | D36: Makes that job's ground wiring come out at your 2 hours
A38: Ground task | B38: Mounting weight (Est.) | C38: Wiring weight (Est.) | D38: Man-hours per unit, grid-tie pace | E38: Unit | F38: Your 9.12 kWp grid-tie: quantity (Est. - correct) | G38: Your 13.97 kWp hybrid: quantity (Est. - correct)
A39: Hybrid inverter | B39: 2 | C39: 2 | D39: =B39*$B$34+C39*$B$36 -> 2.6479246 | E39: per inverter | F39: 0 | G39: 1
A40: Grid-tie inverter | B40: 1 | C40: 1 | D40: =B40*$B$34+C40*$B$36 -> 1.3239623 | E40: per inverter | F40: 1 | G40: 1
A41: Battery pack: anchor and connect (carrying is separate below) | B41: 0.5 | C41: 1 | D41: =B41*$B$34+C41*$B$36 -> 0.8770349 | E41: per pack | F41: 0 | G41: 2
A42: Enclosure (box, DIN rail, ground bar) | B42: 1 | C42: 0 | D42: =B42*$B$34+C42*$B$36 -> 0.89385475 | E42: per box | F42: 2 | G42: 3
A43: Breaker, SPD or ATS | B43: 0.2 | C43: 0.3 | D43: =B43*$B$34+C43*$B$36 -> 0.30780321 | E43: per device | F43: 6 | G43: 15
A44: Conduit or cable tray with supports | B44: 0.15 | C44: 0 | D44: =B44*$B$34+C44*$B$36 -> 0.13407821 | E44: per m | F44: 25 | G44: 30
A45: Wire pull and terminate (PV home-run, THHN, grounding, battery) | B45: 0 | C45: 0.02 | D45: =B45*$B$34+C45*$B$36 -> 0.0086021505 | E45: per m | F45: 75 | G45: 90
A46: String home-run MC4 | B46: 0 | C46: 0.25 | D46: =B46*$B$34+C46*$B$36 -> 0.10752688 | E46: per pair | F46: 2 | G46: 3
A47: Ground rod: drive and bond | B47: 1 | C47: 0.5 | D47: =B47*$B$34+C47*$B$36 -> 1.1089085 | E47: per rod | F47: 1 | G47: 1
A48: Energize and commission: per job | B48: 0 | C48: 3 | D48: =B48*$B$34+C48*$B$36 -> 1.2903226 | E48: per job | F48: 1 | G48: 1
A49: Energize and commission: per inverter | B49: 0 | C49: 1 | D49: =B49*$B$34+C49*$B$36 -> 0.43010753 | E49: per inverter | F49: 1 | G49: 2
A50: Energize and commission: per battery pack | B50: 0 | C50: 0.5 | D50: =B50*$B$34+C50*$B$36 -> 0.21505376 | E50: per pack | F50: 0 | G50: 2
A51: Check: that job's ground work | D51: =SUMPRODUCT(D39:D50,F39:F50) -> 12 | E51: Should equal 12 (4 + 2 hours x 2 persons)
A53: The weights are my estimates of how long each ground task takes relative to the others. Rows 34 and 36 scale them so your job comes out at your hours. Battery and hybrid rows are scaled, not measured: that job had neither.
A55: BATTERY HAULING
A56: Max weight carried per person | B56: 32 | C56: kg | D56: Your practice: a 125 kg pack carried by 4 people (about 31 kg each). Common manual-handling guidance is about 25 kg per person; a battery hand truck keeps the carry within it.
A57: Carry crew = pack weight / max per person, rounded up, at least 2. Battery hauling man-hours = carry crew x hours per pack (LABOR CALC) x packs. The crew on site is never smaller than the carry crew.
A59: HYBRID REFERENCE JOB - your 13.97 kWp hybrid: 4 people, roof and ground in one normal day
A60: Crew | B60: 4 | C60: persons | D60: Your figure
A61: Man-hours in one day | B61: =B60*B13 -> 26 | C61: MH | D61: 4 persons x one model day (row 13); the troubleshooting that day stays in
A62: Panels | B62: 22 | C62: pcs | D62: Assumed 22 x 635 W = 13.97 kWp
A63: Roof factor: simple roof | B63: 0.75 | D63: Est. Your house roof was simpler than the 9.12 kWp job (1.00). Also the default for typical jobs in LABOR CALC
A64: Battery pack weight | B64: 125 | C64: kg | D64: Your figure
A65: Battery hauling hours per pack | B65: 0.5 | C65: h | D65: Est.
A66: Roof man-hours | B66: =(B27+B62*(B28+B29))*B63 -> 11.8125 | C66: MH
A67: Battery carry crew | B67: =MAX(2,ROUNDUP(B64/B56,0)) -> 4 | C67: persons
A68: Battery hauling man-hours | B68: =B67*B65*G41 -> 4 | C68: MH
A69: Hand-off | B69: =D22 -> 2 | C69: MH
A70: Ground work at the grid-tie pace | B70: =SUMPRODUCT(D39:D50,G39:G50) -> 21.833243 | C70: MH | D70: Quantities in column G above
A71: Hybrid ground pace | B71: =(B61-B66-B68-B69)/B70 -> 0.37500155 | C71: x | D71: Applied to ground work on any job with a battery or hybrid inverter. Makes this job fit 4 people in one day
A73: On paper your hybrid had more ground work than the 9.12 kWp grid-tie, yet the crew finished it in the same day. So grid-tie jobs run at the grid-tie pace and hybrid jobs at the hybrid pace, each set by your own job.

Sheet MOB-DEMOB
A1: MOB-DEMOB - getting the crew and tools to site and back
A2: Item | B2: Value | C2: Unit | D2: Source / remarks
A3: CREW VEHICLE (company pickup, priced per day used like the shadow truck)
A4: Vehicle value | B4: 1150000 | C4: P | D4: Audited interim FS, Jun 1, 2026
A5: Life | B5: 10 | C5: years | D5: Audited interim FS
A6: Insurance and registration per year | B6: 25000 | C6: P | D6: Est.
A7: Days used per year | B7: 250 | C7: days | D7: Est.
A8: Ownership cost per day used | B8: =(B4/B5+B6)/B7 -> 560 | C8: P
A9: Diesel price | B9: =DRIVERS!B10 -> 100 | C9: P/L | D9: From DRIVERS
A10: Fuel economy | B10: 10 | C10: km/L | D10: Est.
A11: Maintenance per km | B11: 2 | C11: P/km | D11: Est.
A12: Running cost per km | B12: =B9/B10+B11 -> 12 | C12: P/km
A13: SITE (reference: Pila-area job)
A14: One-way km, base to site | B14: =ROUTE!G13 -> 10 | C14: km | D14: From ROUTE
A15: Toll per round trip | B15: 0 | C15: P | D15: Input
A16: One-way travel time | B16: 0.25 | C16: h | D16: Est.
A17: Crew transport per site day | B17: =B8+2*B14*B12+B15 -> 800 | C17: P | D17: Ownership + round trip km x running cost + toll
A18: Round-trip travel time | B18: =2*B16 -> 0.5 | C18: h | D18: Comes out of the crew's productive hours (LABOR RATES)
A19: PER JOB
A20: Packaging and debris haul-out and disposal | B20: 500 | C20: P/job | D20: Est. - pallets, panel boxes, battery crates
A22: Mob/demob per job = installation days x crew transport per site day + packaging disposal.
A23: The packages workbook used P3,500 per site day.
A24: Far sites: if the crew has to stay overnight, add lodging and per diem per person-night by hand.

Sheet TOOLS
A1: TOOLS - what the crew tools and test instruments cost per installation day
A3: ORDERS
A4: Order | B4: Store | C4: Merchandise subtotal | D4: Order total paid | E4: Paid / merchandise | F4: Remarks
A5: INGCO order | B5: INGCO (Shopee Mall) | C5: 45061 | D5: 44398 | E5: =D5/C5 -> 0.98528661 | F5: Vouchers and shipping spread over the items by value
A6: Ladder order | B6: bigredph | C6: 16440 | D6: 16960 | E6: =D6/C6 -> 1.0316302 | F6: Includes 2 car ramps (P7,960), not company tools. Shipping and vouchers spread by value
A7: MC4 crimper kit | B7: Shopee Choice Global | C7: 1255 | D7: 1255 | E7: =D7/C7 -> 1 | F7: Shipping not shown
A8: UNI-T order | B8: unitrend.ph | C8: 44158 | D8: 44008 | E8: =D8/C8 -> 0.99660311 | F8: Order total as shown; discount spread by value
A9: INGCO order 2 | B9: INGCO (Shopee Mall) | C9: 2297 | D9: 2297 | E9: =D9/C9 -> 1
A10: UNI-T order 2 | B10: unitrend.ph | C10: 24980 | D10: 24230 | E10: =D10/C10 -> 0.96997598 | F10: Voucher spread by value
A11: WAXTRON order | B11: WAXTRON Brand Store PH | C11: 1699 | D11: 1514 | E11: =D11/C11 -> 0.89111242 | F11: Vouchers as shown on the order
A13: TOOLS AND TEST INSTRUMENTS
A14: Item | B14: Order | C14: Qty | D14: Price per unit (listed) | E14: Line total | F14: Paid (after vouchers, shipping) | G14: VAT invoice in PL Dev name? (input) | H14: Cost basis | I14: Life, years (Est.) | J14: Cost per year
A15: INGCO 20V cordless combo kit, 3 pcs | B15: INGCO order | C15: 2 | D15: 11956 | E15: =C15*D15 -> 23912 | F15: =E15*INDEX($E$5:$E$11,MATCH(B15,$A$5:$A$11,0)) -> 23560.173 | G15: Yes | H15: =IF(G15="Yes",F15/1.12,F15) -> 21035.869 | I15: 3 | J15: =H15/I15 -> 7011.9564
A16: INGCO 20V cordless angle grinder | B16: INGCO order | C16: 1 | D16: 7772 | E16: =C16*D16 -> 7772 | F16: =E16*INDEX($E$5:$E$11,MATCH(B16,$A$5:$A$11,0)) -> 7657.6475 | G16: Yes | H16: =IF(G16="Yes",F16/1.12,F16) -> 6837.1853 | I16: 3 | J16: =H16/I16 -> 2279.0618
A17: INGCO 20V cordless heat gun HGLI20085 | B17: INGCO order | C17: 1 | D17: 5870 | E17: =C17*D17 -> 5870 | F17: =E17*INDEX($E$5:$E$11,MATCH(B17,$A$5:$A$11,0)) -> 5783.6324 | G17: Yes | H17: =IF(G17="Yes",F17/1.12,F17) -> 5163.9575 | I17: 3 | J17: =H17/I17 -> 1721.3192
A18: INGCO HHCT0170 hexagonal hydraulic crimper | B18: INGCO order | C18: 1 | D18: 3467 | E18: =C18*D18 -> 3467 | F18: =E18*INDEX($E$5:$E$11,MATCH(B18,$A$5:$A$11,0)) -> 3415.9887 | G18: Yes | H18: =IF(G18="Yes",F18/1.12,F18) -> 3049.9899 | I18: 3 | J18: =H18/I18 -> 1016.6633
A19: INGCO HKISD1201 insulated screwdriver set, 12 pcs | B19: INGCO order | C19: 1 | D19: 1436 | E19: =C19*D19 -> 1436 | F19: =E19*INDEX($E$5:$E$11,MATCH(B19,$A$5:$A$11,0)) -> 1414.8716 | G19: Yes | H19: =IF(G19="Yes",F19/1.12,F19) -> 1263.2782 | I19: 2 | J19: =H19/I19 -> 631.6391
A20: INGCO HIKPS28318 insulated pliers set, 3 pcs | B20: INGCO order | C20: 1 | D20: 1282 | E20: =C20*D20 -> 1282 | F20: =E20*INDEX($E$5:$E$11,MATCH(B20,$A$5:$A$11,0)) -> 1263.1374 | G20: Yes | H20: =IF(G20="Yes",F20/1.12,F20) -> 1127.8013 | I20: 2 | J20: =H20/I20 -> 563.90064
A21: INGCO HISS1601 insulated scissors | B21: INGCO order | C21: 1 | D21: 770 | E21: =C21*D21 -> 770 | F21: =E21*INDEX($E$5:$E$11,MATCH(B21,$A$5:$A$11,0)) -> 758.67069 | G21: Yes | H21: =IF(G21="Yes",F21/1.12,F21) -> 677.38455 | I21: 2 | J21: =H21/I21 -> 338.69227
A22: INGCO HICK1801 insulated cable knife | B22: INGCO order | C22: 1 | D22: 552 | E22: =C22*D22 -> 552 | F22: =E22*INDEX($E$5:$E$11,MATCH(B22,$A$5:$A$11,0)) -> 543.87821 | G22: Yes | H22: =IF(G22="Yes",F22/1.12,F22) -> 485.60554 | I22: 2 | J22: =H22/I22 -> 242.80277
A23: ROVER fiberglass foldable multipurpose ladder | B23: Ladder order | C23: 1 | D23: 8480 | E23: =C23*D23 -> 8480 | F23: =E23*INDEX($E$5:$E$11,MATCH(B23,$A$5:$A$11,0)) -> 8748.2238 | G23: No | H23: =IF(G23="Yes",F23/1.12,F23) -> 8748.2238 | I23: 5 | J23: =H23/I23 -> 1749.6448
A24: Solar cable connectors with crimper (MC4 kit) | B24: MC4 crimper kit | C24: 1 | D24: 1255 | E24: =C24*D24 -> 1255 | F24: =E24*INDEX($E$5:$E$11,MATCH(B24,$A$5:$A$11,0)) -> 1255 | G24: No | H24: =IF(G24="Yes",F24/1.12,F24) -> 1255 | I24: 2 | J24: =H24/I24 -> 627.5
A25: UNI-T UT219PV PV clamp meter + UT-CS09D flexible probe | B25: UNI-T order | C25: 1 | D25: 21680 | E25: =C25*D25 -> 21680 | F25: =E25*INDEX($E$5:$E$11,MATCH(B25,$A$5:$A$11,0)) -> 21606.355 | G25: No | H25: =IF(G25="Yes",F25/1.12,F25) -> 21606.355 | I25: 5 | J25: =H25/I25 -> 4321.2711
A26: UNI-T UT381PV solar irradiance meter | B26: UNI-T order | C26: 1 | D26: 16098 | E26: =C26*D26 -> 16098 | F26: =E26*INDEX($E$5:$E$11,MATCH(B26,$A$5:$A$11,0)) -> 16043.317 | G26: No | H26: =IF(G26="Yes",F26/1.12,F26) -> 16043.317 | I26: 5 | J26: =H26/I26 -> 3208.6634
... A31: WAXTRON digital torque screwdriver set, 1-6 N.m (39 pcs) | B31: WAXTRON order | C31: 1 | D31: 1699 | E31: =C31*D31 -> 1699 | F31: =E31*INDEX($E$5:$E$11,MATCH(B31,$A$5:$A$11,0)) -> 1514 | G31: No | H31: =IF(G31="Yes",F31/1.12,F31) -> 1514 | I31: 2 | J31: =H31/I31 -> 757
A32: Total | E32: =SUM(E15:E31) -> 127930 | F32: =SUM(F15:F31) -> 126450.22 | H32: =SUM(H15:H31) -> 121447.19 | J32: =SUM(J15:J31) -> 31325.28
A34: TOOL CHARGE
A35: Repairs, bits, discs, blades, calibration per year (share of cost basis) | B35: 0.1 | C35: Est.
A36: Job-days per year | B36: 48 | C36: Est. 4 one-day jobs a month
A37: Tool cost per year | B37: =J32+B35*H32 -> 43469.999
A38: Tool charge per installation day | B38: =B37/B36 -> 905.62498
A40: VAT: request the e-invoice in PL Development Inc.'s name and TIN wherever the seller issues one; the 12% then comes back as input VAT, so cost basis is the price / 1.12. INGCO (Shopee Mall) is set to Yes; check unitrend.ph and bigredph.
A41: Charged on every installation day in LABOR CALC. Fewer job-days a year means a higher charge per day; the tools cost the same either way.
A42: Not included: the 2 car ramps.

Sheet LABOR CALC
A1: LABOR CALC - takeoff quantities to man-hours, crew, days, labor and mob/demob cost. Change any quantity; the crew follows
A3: Job | B3: Small grid-tie 3 kWp | C3: P1 5 kWp / 6 kW / 11.8 kWh | D3: P2 7 kWp / 8 kW / 15.4 kWh | E3: P3 9 kWp / 10 kW / 20.5 kWh | F3: P4 11 kWp / 12 kW / 20.5 kWh | G3: Check: your 9.12 kWp grid-tie | H3: Check: your 13.97 kWp hybrid (4 people, 1 day) | I3: This job (from the JOB sheet) | J3: Remarks
A4: TAKEOFF QUANTITIES (input; on the job sheet these come from the BOM)
A5: Panels | B5: 5 | C5: 8 | D5: 11 | E5: 14 | F5: 17 | G5: ='LABOR RATES'!B24 -> 16 | H5: ='LABOR RATES'!B62 -> 22 | I5: =JOB!B19 -> 8 | J5: 13.97 kWp hybrid column: 22 x 635 W assumed; its other quantities are my guesses
A6: Hybrid inverters | B6: 0 | C6: 1 | D6: 1 | E6: 1 | F6: 1 | G6: ='LABOR RATES'!$F$39 -> 0 | H6: ='LABOR RATES'!$G$39 -> 1 | I6: =JOB!B20 -> 1
A7: Grid-tie inverters | B7: 1 | C7: 0 | D7: 0 | E7: 0 | F7: 0 | G7: ='LABOR RATES'!$F$40 -> 1 | H7: ='LABOR RATES'!$G$40 -> 1 | I7: =JOB!B21 -> 0
A8: Battery packs | B8: 0 | C8: 1 | D8: 1 | E8: 2 | F8: 2 | G8: ='LABOR RATES'!$F$41 -> 0 | H8: ='LABOR RATES'!$G$41 -> 2 | I8: =JOB!B22 -> 1
A9: Battery pack weight, kg | B9: 0 | C9: 110 | D9: 140.5 | E9: 88 | F9: 88 | G9: 0 | H9: ='LABOR RATES'!B64 -> 125 | I9: =JOB!B23 -> 111 | J9: Boxed weight from the DB (P1 JK 230Ah 110 kg; P2 Felicity 300Ah 140.5 kg; P3/P4 Felicity 200Ah 88 kg each). Use the unboxed weight if you unbox at the truck
A10: Battery hauling hours per pack | B10: 0.5 | C10: 0.5 | D10: 0.5 | E10: 0.5 | F10: 0.5 | G10: 0.5 | H10: ='LABOR RATES'!B65 -> 0.5 | I10: =JOB!B15 -> 0.5 | J10: Est. 0.5 = ground floor, short carry from the truck; 1.0 or more upstairs or long carry
A11: Enclosures (metal boxes, DU box) | B11: 2 | C11: 3 | D11: 3 | E11: 3 | F11: 3 | G11: ='LABOR RATES'!$F$42 -> 2 | H11: ='LABOR RATES'!$G$42 -> 3 | I11: =JOB!B24 -> 2
A12: Breakers, SPDs, ATS | B12: 5 | C12: 13 | D12: 13 | E12: 13 | F12: 13 | G12: ='LABOR RATES'!$F$43 -> 6 | H12: ='LABOR RATES'!$G$43 -> 15 | I12: =JOB!B25 -> 13
A13: Conduit and cable tray, m | B13: 20 | C13: 32 | D13: 32 | E13: 32 | F13: 32 | G13: ='LABOR RATES'!$F$44 -> 25 | H13: ='LABOR RATES'!$G$44 -> 30 | I13: =JOB!B26 -> 32
A14: Wire, m (PV, THHN, grounding, battery) | B14: 50 | C14: 69 | D14: 76 | E14: 85 | F14: 92 | G14: ='LABOR RATES'!$F$45 -> 75 | H14: ='LABOR RATES'!$G$45 -> 90 | I14: =JOB!B27 -> 65
A15: String home-run MC4 pairs | B15: 2 | C15: 4 | D15: 5 | E15: 6 | F15: 7 | G15: ='LABOR RATES'!$F$46 -> 2 | H15: ='LABOR RATES'!$G$46 -> 3 | I15: =JOB!B28 -> 4
A16: Ground rods | B16: 1 | C16: 1 | D16: 1 | E16: 1 | F16: 1 | G16: ='LABOR RATES'!$F$47 -> 1 | H16: ='LABOR RATES'!$G$47 -> 1 | I16: =JOB!B29 -> 1
A17: Roof difficulty factor | B17: ='LABOR RATES'!$B$63 -> 0.75 | C17: ='LABOR RATES'!$B$63 -> 0.75 | D17: ='LABOR RATES'!$B$63 -> 0.75 | E17: ='LABOR RATES'!$B$63 -> 0.75 | F17: ='LABOR RATES'!$B$63 -> 0.75 | G17: 1 | H17: ='LABOR RATES'!$B$63 -> 0.75 | I17: =JOB!B11 -> 0.75 | J17: Simple roof (LABOR RATES row 63) for typical jobs. 1.00 = your 9.12 kWp multi-face roof with custom mounting; 1.25 two-storey or steep; 1.50 clay or concrete tile (Est.)
A18: Roof closed within (days) | B18: 1 | C18: 1 | D18: 1 | E18: 1 | F18: 1 | G18: 1 | H18: 1 | I18: =JOB!B12 -> 1 | J18: Input. 1 = no open roof penetrations overnight
A19: Max installation days | B19: 2 | C19: 2 | D19: 2 | E19: 2 | F19: 2 | G19: 2 | H19: 2 | I19: =JOB!B13 -> 2 | J19: Input
A20: Your days on site (optional) | B20: 0 | C20: 0 | D20: 0 | E20: 0 | F20: 0 | G20: 0 | H20: 0 | I20: =JOB!B16 -> 0 | J20: Input. 0 = the crew energizes and commissions, as on your 9.12 kWp job
A22: MAN-HOURS (quantity x LABOR RATES)
A23: Roof: setup + panel mounting, x roof factor | B23: =IF(B5=0,0,('LABOR RATES'!$B$27+B5*'LABOR RATES'!$B$28)*B17) -> 2.90625 | C23: =IF(C5=0,0,('LABOR RATES'!$B$27+C5*'LABOR RATES'!$B$28)*C17) -> 3.75 | D23: =IF(D5=0,0,('LABOR RATES'!$B$27+D5*'LABOR RATES'!$B$28)*D17) -> 4.59375 | E23: =IF(E5=0,0,('LABOR RATES'!$B$27+E5*'LABOR RATES'!$B$28)*E17) -> 5.4375 | F23: =IF(F5=0,0,('LABOR RATES'!$B$27+F5*'LABOR RATES'!$B$28)*F17) -> 6.28125 | G23: =IF(G5=0,0,('LABOR RATES'!$B$27+G5*'LABOR RATES'!$B$28)*G17) -> 8 | H23: =IF(H5=0,0,('LABOR RATES'!$B$27+H5*'LABOR RATES'!$B$28)*H17) -> 7.6875 | I23: =IF(I5=0,0,('LABOR RATES'!$B$27+I5*'LABOR RATES'!$B$28)*I17) -> 3.75
A24: Roof: wiring, x roof factor | B24: =B5*'LABOR RATES'!$B$29*B17 -> 0.9375 | C24: =C5*'LABOR RATES'!$B$29*C17 -> 1.5 | D24: =D5*'LABOR RATES'!$B$29*D17 -> 2.0625 | E24: =E5*'LABOR RATES'!$B$29*E17 -> 2.625 | F24: =F5*'LABOR RATES'!$B$29*F17 -> 3.1875 | G24: =G5*'LABOR RATES'!$B$29*G17 -> 4 | H24: =H5*'LABOR RATES'!$B$29*H17 -> 4.125 | I24: =I5*'LABOR RATES'!$B$29*I17 -> 1.5
A25: Roof man-hours | B25: =B23+B24 -> 3.84375 | C25: =C23+C24 -> 5.25 | D25: =D23+D24 -> 6.65625 | E25: =E23+E24 -> 8.0625 | F25: =F23+F24 -> 9.46875 | G25: =G23+G24 -> 12 | H25: =H23+H24 -> 11.8125 | I25: =I23+I24 -> 5.25
A26: Ground pace (1.00 = grid-tie; hybrid jobs use your hybrid day) | B26: =IF(B6+B8>0,'LABOR RATES'!$B$71,1) -> 1 | C26: =IF(C6+C8>0,'LABOR RATES'!$B$71,1) -> 0.37500155 | D26: =IF(D6+D8>0,'LABOR RATES'!$B$71,1) -> 0.37500155 | E26: =IF(E6+E8>0,'LABOR RATES'!$B$71,1) -> 0.37500155 | F26: =IF(F6+F8>0,'LABOR RATES'!$B$71,1) -> 0.37500155 | G26: =IF(G6+G8>0,'LABOR RATES'!$B$71,1) -> 1 | H26: =IF(H6+H8>0,'LABOR RATES'!$B$71,1) -> 0.37500155 | I26: =IF(I6+I8>0,'LABOR RATES'!$B$71,1) -> 0.37500155
A27: Persons to carry one battery pack | B27: =IF(B8=0,0,MAX(2,ROUNDUP(B9/'LABOR RATES'!$B$56,0))) -> 0 | C27: =IF(C8=0,0,MAX(2,ROUNDUP(C9/'LABOR RATES'!$B$56,0))) -> 4 | D27: =IF(D8=0,0,MAX(2,ROUNDUP(D9/'LABOR RATES'!$B$56,0))) -> 5 | E27: =IF(E8=0,0,MAX(2,ROUNDUP(E9/'LABOR RATES'!$B$56,0))) -> 3 | F27: =IF(F8=0,0,MAX(2,ROUNDUP(F9/'LABOR RATES'!$B$56,0))) -> 3 | G27: =IF(G8=0,0,MAX(2,ROUNDUP(G9/'LABOR RATES'!$B$56,0))) -> 0 | H27: =IF(H8=0,0,MAX(2,ROUNDUP(H9/'LABOR RATES'!$B$56,0))) -> 4 | I27: =IF(I8=0,0,MAX(2,ROUNDUP(I9/'LABOR RATES'!$B$56,0))) -> 4
A28: Hybrid inverters | B28: =B6*'LABOR RATES'!$D$39*B26 -> 0 | C28: =C6*'LABOR RATES'!$D$39*C26 -> 0.9929758 | D28: =D6*'LABOR RATES'!$D$39*D26 -> 0.9929758 | E28: =E6*'LABOR RATES'!$D$39*E26 -> 0.9929758 | F28: =F6*'LABOR RATES'!$D$39*F26 -> 0.9929758 | G28: =G6*'LABOR RATES'!$D$39*G26 -> 0 | H28: =H6*'LABOR RATES'!$D$39*H26 -> 0.9929758 | I28: =I6*'LABOR RATES'!$D$39*I26 -> 0.9929758
A29: Grid-tie inverters | B29: =B7*'LABOR RATES'!$D$40*B26 -> 1.3239623 | C29: =C7*'LABOR RATES'!$D$40*C26 -> 0 | D29: =D7*'LABOR RATES'!$D$40*D26 -> 0 | E29: =E7*'LABOR RATES'!$D$40*E26 -> 0 | F29: =F7*'LABOR RATES'!$D$40*F26 -> 0 | G29: =G7*'LABOR RATES'!$D$40*G26 -> 1.3239623 | H29: =H7*'LABOR RATES'!$D$40*H26 -> 0.4964879 | I29: =I7*'LABOR RATES'!$D$40*I26 -> 0
